Workbook

Sheet Portada
A1: Kuajo Automation — Planeación y evaluación del proyecto de automatización para Lácteos Pomar (PM4R)
A2: Caso académico · Proyecto Integrador APM 2026-2 · Valores en COP sin IVA · Precios y tasas a octubre de 2026
A4: Indicador | B4: Valor | C4: Lectura
A5: Precio de la oferta (Fase 1, sin IVA) | B5: =Precio_Kuajo!$C$19 -> 8.5259187e+09 | C5: Lo que Pomar paga a Kuajo
A6: Precio en US$ | B6: =Precio_Kuajo!$C$19/Supuestos!$B$6 -> 2604534.8 | C6: A la TRM de octubre de 2026
A7: Duración (semanas) | B7: =Cronograma!$G$44 -> 48 | C7: Ruta crítica del cronograma
A8: VPN para Pomar a la TIO | B8: =Flujo_Pomar!$B$33 -> 1.5013918e+10 | C8: Positivo = la inversión crea valor
A9: TIR para Pomar | B9: =Flujo_Pomar!$B$35 -> 0.48963311 | C9: Comparar con la TIO
A10: TIO de Pomar | B10: =Supuestos!$B$31 -> 0.13731408 | C10: WACC + prima de proyecto
A11: Recuperación simple de Pomar (años) | B11: =Flujo_Pomar!$B$36 -> 2.2332537
A12: Recuperación descontada de Pomar (años) | B12: =Flujo_Pomar!$B$37 -> 2.7082746
A13: Factor de beneficios de equilibrio | B13: =Sensibilidad!$M$16 -> 0.39299608 | C13: Los beneficios pueden caer hasta este nivel y el VPN sigue ≥ 0
A14: Utilidad neta de Kuajo en el proyecto | B14: =Kuajo_PyG_Flujo!$B$56 -> 9.3452821e+08 | C14: Después de salarios, gastos, contingencia e impuestos
A15: Margen neto de Kuajo | B15: =Kuajo_PyG_Flujo!$B$57 -> 0.10961026
A16: VPN para Kuajo (TIO 20 %) | B16: =Kuajo_PyG_Flujo!$B$61 -> 9.4017867e+08
A17: Saldo de caja mínimo de Kuajo | B17: =Kuajo_PyG_Flujo!$B$62 -> -1.3161225e+09 | C17: Negativo = meses financiados con el crédito rotativo
A18: Cobertura de la contingencia sobre el riesgo esperado | B18: =Riesgos!$L$20 -> 1.2277561 | C18: ≥ 1 = la contingencia cubre el valor esperado de los riesgos
A19: Crédito rotativo máximo de Kuajo | B19: =Kuajo_PyG_Flujo!$B$63 -> 1.3161225e+09 | C19: Por el cobro a 30 días; cupo y tasa en Supuestos
A20: Hojas del libro
A21: Supuestos | B21: Todos los datos de entrada con su fuente
A22: VSM_Actual | B22: Estado actual de la línea de yogures: VSM, OEE, cuello de botella, lead time y KPIs base
A23: Lineas_2_3 | B23: Resultados esperados de las líneas 2 y 3 y del proyecto de planta completa (referencia ±30 %)
A24: Recursos_compartidos | B24: Capacidad y utilización de los recursos que comparten las 3 líneas
A25: Nomina_Kuajo | B25: Salarios de los 6 integrantes, factor prestacional y gastos generales
A26: Cotizaciones | B26: Precios de referencia de cada suministro, con fuente o marcados como estimación
A27: Precio_Kuajo | B27: Del costo de Kuajo al precio de la oferta
A28: Cronograma | B28: Actividades, ruta crítica (CPM) y Gantt
A29: Curva_S | B29: Valor planificado mensual y acumulado
A30: EDT | B30: Estructura desglosada del trabajo
A31: Beneficios_OPEX | B31: Margen por kg, beneficios anuales y costos de operación de Pomar
A32: Flujo_Pomar | B32: Flujo de caja, VPN, TIR y recuperación de Pomar
... A42: Simulacion | B42: Resultados del simulador de eventos discretos (sim.py, sección 6.9): escenarios actual y propuesto, 10 réplicas
A43: Convención de colores: azul = dato de entrada · negro = fórmula · verde = vínculo a otra hoja. El libro tiene 23 hojas: portada y 22 hojas de cálculo.

Sheet Supuestos
A1: Supuestos del modelo — Proyecto de automatización Kuajo Automation → Lácteos Pomar
A2: Azul = dato de entrada editable · Negro = fórmula · Verde = vínculo a otra hoja · Fondo amarillo = supuesto clave. Valores en COP sin IVA salvo que se indique.
A4: Parámetro | B4: Valor | C4: Unidad | D4: Fuente o justificación
A5: Macroeconomía y tasas
A6: TRM (tasa de cambio) | B6: 3273.49 | C6: COP/USD | D6: TRM del 3–5 oct. 2026 (Noticias Caracol, 5 oct. 2026)
A7: Inflación esperada Colombia (horizonte 2 años) | B7: 0.04 | C7: % anual | D7: Banco de la República, encuesta de expectativas de sept. 2026: 4,0 % a dos años
A8: Inflación esperada EE. UU. | B8: 0.025 | C8: % anual | D8: Supuesto (meta de la Reserva Federal + margen); se usa solo para convertir el costo de capital a COP
A9: Tasa de política monetaria Banco de la República | B9: 0.1225 | C9: % anual | D9: Banco de la República, decisión del 30 sept. 2026 (12,25 %)
A10: Tasa de impuesto de renta (personas jurídicas) | B10: 0.35 | C10: % | D10: Estatuto Tributario art. 240; Damodaran, ctryprem (Colombia 35 %, ene. 2026)
A11: Importación: componentes del costo de nacionalización (sobre el valor FOB de cada equipo importado)
A12: Flete internacional (marítimo desde Europa o EE. UU.; aéreo para instrumentos pequeños) | B12: 0.03 | C12: % del FOB | D12: ≈ 6 contenedores de 40 pies a US$3.000–4.500 cada uno sobre ≈ US$0,97 millones FOB ≈ 2,5 %; se toma 3 % por envíos aéreos. Referencia: 20 pies Port Everglades–Cartagena 1.469 € en 4 días (iContainers, oct. 2026)
A13: Seguro de transporte internacional | B13: 0.005 | C13: % del FOB | D13: Prima habitual de seguro de carga de 0,3–0,5 % del valor CIF; se toma el extremo alto por ser equipo sensible
A14: Agencia de aduanas, gastos portuarios y documentales | B14: 0.015 | C14: % del FOB | D14: Banco Mundial (Doing Business): cumplimiento fronterizo US$545 y documental US$50 por embarque en Colombia, más honorarios de la agencia (obligatoria para importaciones > US$1.000 FOB, trade.gov)
A15: Transporte terrestre Cartagena–Cajicá con seguro | B15: 0.015 | C15: % del FOB | D15: Mundo Marítimo: US$1.330 por contenedor Cartagena–Bogotá (2019), ajustado a ≈ US$1.900 en 2026 × 6 contenedores ≈ 1,2 %; se toma 1,5 % por carga sobredimensionada de la celda
A16: Arancel de importación | B16: 0 | C16: % del FOB | D16: Decreto 272 de 2018: arancel 0 % para bienes de capital no producidos en Colombia; los Decretos 2616 de 2022 y 324 de 2024 solo restablecen subpartidas con producción nacional (bombas, refrigeradores, cables). Los robots (subpartida 8479.50.00.00, a confirmar con la agencia de aduanas) se compran de fabricación sueca con certificado de origen UE (Acuerdo Comercial UE–Colombia, 0 %); E+H, Alfa Laval y Mettler-Toledo también son de origen UE y Rockwell, Cisco y Dell de EE. UU. (TLC, 0 %). Riesgo residual: 5 % ≈ $160 M, cubierto por la contingencia.
A17: Bodegaje en puerto, demoras e imprevistos logísticos | B17: 0.015 | C17: % del FOB | D17: Reserva para almacenamiento en puerto, inspección física de la DIAN y demoras (tiempo de importación en Colombia: 112 h de cumplimiento fronterizo + 64 h documental, Banco Mundial)
A18: Costo total de nacionalización de equipos importados | B18: =B12+B13+B14+B15+B16+B17 -> 0.08 | C18: % del valor FOB | D18: Suma de los componentes anteriores; se aplica a cada ítem importado de la hoja Cotizaciones
A19: Costo de capital de Pomar (WACC) y tasa de oportunidad
A20: Tasa libre de riesgo (bono del Tesoro EE. UU. a 10 años) | B20: 0.0418 | C20: % | D20: Damodaran, Historical Implied ERP, inicio de 2026: 4,18 %
A21: Beta apalancada industria de alimentos procesados | B21: 0.61 | C21: — | D21: Damodaran, Cost of Capital by industry (Food Processing), ene. 2026
A22: Prima de riesgo de mercado madura | B22: 0.0423 | C22: % | D22: Damodaran, prima implícita ene. 2026: 4,23 %
A23: Prima de riesgo país Colombia | B23: 0.0285 | C23: % | D23: Damodaran, ctryprem (Baa3), ene. 2026: 2,85 %
A24: Deuda / (Deuda + Patrimonio) | B24: 0.3043 | C24: % | D24: Damodaran, Food Processing, ene. 2026: 30,43 %
A25: Diferencial de crédito corporativo sobre la tasa BanRep | B25: 0.04 | C25: % | D25: Supuesto: crédito comercial para empresa mediana
A26: Costo del patrimonio en USD (CAPM) | B26: =B20+B21*(B22+B23) -> 0.084988 | C26: % | D26: Ke = Rf + β·(ERP + CRP)
A27: Costo del patrimonio en COP | B27: =(1+B26)*(1+B7)/(1+B8)-1 -> 0.10086587 | C27: % | D27: Ajuste por diferencial de inflación (paridad de Fisher)
A28: Costo de la deuda después de impuestos (COP) | B28: =(B9+B25)*(1-B10) -> 0.105625 | C28: % | D28: Kd = (tasa BanRep + diferencial)·(1 − t)
A29: WACC de Pomar (COP nominal) | B29: =(1-B24)*B27+B24*B28 -> 0.10231408 | C29: % | D29: Promedio ponderado
A30: Prima de riesgo del proyecto (tecnológico, primera implementación) | B30: 0.035 | C30: % | D30: Supuesto conservador por riesgo de ejecución y de adopción
A31: Tasa de oportunidad (TIO) de Pomar para descontar el proyecto | B31: =B29+B30 -> 0.13731408 | C31: % | D31: TIO = WACC + prima de proyecto
A32: Tasa de oportunidad de Kuajo Automation (empresa nueva) | B32: 0.2 | C32: % efectivo anual | D32: Supuesto: costo del patrimonio de una empresa pequeña de servicios recién creada (Ke COP + prima por tamaño y etapa temprana)
A33: Nómina y cargas laborales (Colombia 2026)
A34: Salario mínimo mensual 2026 | B34: 1750905 | C34: COP/mes | D34: Decreto 1469 de 2025 (Holland & Knight, dic. 2025)
A35: Auxilio de transporte 2026 (salarios ≤ 2 SMMLV) | B35: 249095 | C35: COP/mes | D35: Decreto 1470 de 2025
A36: Aporte a pensión (empleador) | B36: 0.12 | C36: % | D36: Ley 100 de 1993; tabla de prestaciones 2026 (calcucolombia.co)
A37: ARL riesgo II (ingenieros que trabajan en planta) | B37: 0.01044 | C37: % | D37: Decreto 1295 de 1994, tabla de cotización ARL
A38: ARL riesgo III (operarios de planta) | B38: 0.02436 | C38: % | D38: Decreto 1295 de 1994
A39: Caja de compensación familiar | B39: 0.04 | C39: % | D39: Ley 21 de 1982
A40: Prima de servicios | B40: 0.0833 | C40: % | D40: Código Sustantivo del Trabajo art. 306
A41: Cesantías | B41: 0.0833 | C41: % | D41: CST art. 249
A42: Intereses sobre cesantías | B42: 0.01 | C42: % | D42: Ley 52 de 1975 (12 % anual sobre cesantías)
A43: Vacaciones | B43: 0.0417 | C43: % | D43: CST art. 186 (15 días hábiles/año)
A44: Factor prestacional ingenieros (salud, SENA e ICBF exonerados por salario < 10 SMMLV) | B44: =1+B36+B37+B39+B40+B41+B42+B43 -> 1.38874 | C44: veces el salario | D44: Art. 114-1 del Estatuto Tributario (Ley 1819 de 2016); coincide con el rango 1,45–1,55 de calcucolombia si se incluye salud
A45: Factor prestacional operarios | B45: =1+B36+B38+B39+B40+B41+B42+B43 -> 1.40266 | C45: veces el salario | D45: Igual que ingenieros, con ARL riesgo III
A46: Horas facturables por ingeniero al mes | B46: 160 | C46: h/mes | D46: Jornada de 42 h/semana (Ley 2101 de 2021, vigente desde jul. 2026) menos reuniones internas y formación
A47: Tarifa de ingeniería de Kuajo | B47: 150000 | C47: COP/h | D47: Supuesto: ≈ 3 veces el costo horario del equipo (ver Nomina_Kuajo); equivale a ≈ US$46/h, por debajo de tarifas de integradores en EE. UU.
A48: Meses de nómina cargados al proyecto | B48: 12 | C48: meses | D48: Duración del proyecto (48 semanas ≈ 11 meses) más cierre; las horas facturables del cronograma (10.160 h) son 88 % de la capacidad de 11.520 h
A49: Estructura de precio de Kuajo
A50: Margen comercial sobre suministros (equipos, software, obras) | B50: 0.1 | C50: % | D50: Supuesto: rango habitual de integradores para equipos de terceros (8–15 %)
A51: Contingencia del proyecto | B51: 0.07 | C51: % de costos directos | D51: Fijada para cubrir el valor esperado de los riesgos que retiene Kuajo (hoja Riesgos, cobertura ≥ 1). Es baja frente a la exactitud de un estimado clase 3 (AACE 18R-97: −20 % a +30 %) porque el riesgo cambiario se transfiere por cláusula y el 70 % de los precios se confirmará con cotizaciones formales
A52: Prima de la póliza de cumplimiento y calidad | B52: 0.012 | C52: % del contrato | D52: Póliza con 3 amparos: cumplimiento (20 % del contrato, 15 meses), buen manejo del anticipo (100 % del anticipo, ≈ 11 meses) y calidad (20 %, 12 meses). Valor asegurado-año ≈ $5.900 M; a una tasa de referencia de ≈ 1,6 % anual da ≈ 1,2 % del contrato. Estimación: cotizar con Sura, Bolívar o Mapfre.
A53: ICA Bogotá — actividades de ingeniería (9,66 por mil) | B53: 0.00966 | C53: % de ingresos | D53: Acuerdo 65 de 2002 de Bogotá, tarifa servicios
A54: Gravamen a los movimientos financieros (4 por mil) | B54: 0.004 | C54: % de pagos | D54: Estatuto Tributario art. 872
A55: IVA (informativo, no incluido en el flujo) | B55: 0.19 | C55: % | D55: Estatuto Tributario art. 468; para Pomar es descontable en bienes de capital (art. 258-1)
A56: Fracción de la contingencia que se espera consumir | B56: 0.5 | C56: % | D56: Supuesto: la mitad de los riesgos identificados se materializa
A57: Operación de la línea de yogures (situación actual: sección 6; con la propuesta: sección 7.4)
A58: Días de producción al año | B58: 312 | C58: días | D58: 6 días por semana × 52 semanas
A59: Producción actual de Y1 fresa | B59: 26400 | C59: kg/día | D59: Informe, sección 6.1: 176.000 vasos de 150 g; la llenadora de vasos limita la producción (OEE 55 %)
A60: Producción actual de Y2 griego | B60: 5900 | C60: kg/día | D60: Informe, sección 6.1: lanzado a baja escala en 2026 (11.800 vasos de 500 g); crece con el contrato de supermercados
A61: Producción actual de Y3 kéfir | B61: 11400 | C61: kg/día | D61: Informe, sección 6.1: ≈ 11.070 botellas de 1 L
A62: Producción actual de la línea de yogures | B62: =B59+B60+B61 -> 43700 | C62: kg/día | D62: Suma de las 3 recetas (situación actual)
A63: Producción con la propuesta de Y1 fresa | B63: 30000 | C63: kg/día | D63: Informe, sección 7.4: 200.000 vasos
A64: Producción con la propuesta de Y2 griego | B64: 10000 | C64: kg/día | D64: Informe, sección 7.4: 20.000 vasos (contrato con cadenas de supermercados)
A65: Producción con la propuesta de Y3 kéfir | B65: 12400 | C65: kg/día | D65: Informe, sección 7.4: 12.000 botellas
A66: Producción con la propuesta | B66: =B63+B64+B65 -> 52400 | C66: kg/día | D66: Suma de las 3 recetas (+20 % frente a la situación actual)
A67: Fracción del volumen adicional atribuible a la automatización | B67: 0.5 | C67: % | D67: Supuesto conservador: parte del aumento podría lograrse con un tercer turno o mejoras de gestión sin esta inversión
A68: Captura de beneficios en el año 1 (curva de aprendizaje) | B68: 0.6 | C68: % | D68: Supuesto: estabilización de 6 meses después de la puesta en marcha
A69: Precio de la leche cruda pagada al productor (Cundinamarca) | B69: 2134 | C69: COP/L | D69: Agronegocios, mayo 2026 (dato de marzo 2026, región Boyacá–Cundinamarca)
A70: Costo de acopio y transporte de leche | B70: 0.05 | C70: % sobre el precio | D70: Supuesto
A71: Rechazo actual (peso o sellado) | B71: 0.03 | C71: % | D71: Informe, problema P4
A72: Rechazo con la propuesta | B72: 0.01 | C72: % | D72: Informe, sección 7.9
A73: Fracción de la reducción de rechazos que se captura | B73: 0.75 | C73: % | D73: Supuesto conservador
A74: Operarios de paletizado manual que se liberan | B74: 6 | C74: personas | D74: Hoy 4 por turno × 2 turnos; queda 1 por turno supervisando la celda
A75: Salario de operario de planta | B75: =1.1*B34 -> 1925995.5 | C75: COP/mes | D75: 1,1 SMMLV (referencia de mercado para operario de alimentos)
A76: Costo de energía, vapor y agua de la línea | B76: 250 | C76: COP/kg | D76: Estimación de la industria láctea (≈ 0,2–0,3 kWh-equivalente por kg)
A77: Ahorro por submedición y control de consumos | B77: 0.03 | C77: % | D77: Supuesto conservador (programas de submedición suelen dar 3–10 %)
A78: Probabilidad anual de un retiro de producto | B78: 0.1 | C78: % | D78: Supuesto
A79: Costo evitado por acotar el retiro (2 h de producción en vez de un día) | B79: 800000000 | C79: COP por evento | D79: Estimación: producto, logística inversa y destrucción de un día de producción
A80: Capital de trabajo sobre ventas incrementales | B80: 30 | C80: días | D80: Supuesto: inventario + cartera netos de proveedores
A81: Días de parada de la línea para el montaje | B81: 12 | C81: días | D81: Informe: parada máxima de 2 semanas (6 días/semana)
A82: Fracción de producción perdida durante la parada | B82: 0.5 | C82: % | D82: Supuesto: la mitad se compensa con inventario fabricado antes de la parada
A83: Costo interno de Pomar (líder de proyecto, TI, calidad) | B83: 150000000 | C83: COP | D83: Estimación: 1 líder a medio tiempo + apoyo de TI y calidad durante 12 meses
A84: Horizonte de evaluación | B84: 7 | C84: años | D84: Vida útil económica conservadora; sin valor residual
A85: Vida útil fiscal de maquinaria y equipo | B85: 10 | C85: años | D85: Estatuto Tributario art. 137 (modificado por la Ley 1819 de 2016): tasa máxima anual de 10 % para maquinaria y equipo
A86: Vida útil fiscal de equipo de cómputo y software | B86: 5 | C86: años | D86: Estatuto Tributario art. 137: tasa máxima anual de 20 % para equipo de cómputo y software
A87: Kuajo: plazo de cobro de cada hito (meses) | B87: 1 | C87: meses | D87: Oferta, punto 5: pago contra hito aprobado y factura a 30 días (también el anticipo, contra la póliza de buen manejo)
A88: Kuajo: retención en la fuente promedio sobre los cobros | B88: 0.04 | C88: % | D88: Estimación: 2,5 % en compras de bienes y 4–11 % en servicios de ingeniería; es un anticipo del impuesto de renta que se descuenta al liquidarlo
A89: Kuajo: tasa del crédito rotativo de capital de trabajo (EA) | B89: =B9+B25 -> 0.1625 | C89: % EA | D89: Tasa de política del BanRep + diferencial de crédito comercial (igual que en el costo de la deuda de Pomar)
A90: Kuajo: cupo del crédito rotativo | B90: 1500000000 | C90: COP | D90: Cupo aprobado antes de la firma; respaldado por el contrato y la póliza (se usa solo en los meses con saldo negativo)
A91: Horas extra del equipo en semanas pico (h) | B91: 305 | C91: h | D91: Hoja Cronograma, histograma de recursos: horas por encima de 42 h/semana por persona (≈ 3 % de las horas)

Sheet Nomina_Kuajo
A1: Nómina y costos de Kuajo Automation durante el proyecto
A2: Salarios mensuales en COP 2026. Referencias de mercado: Indeed Colombia (sept. 2026).
A4: Rol | B4: Integrante | C4: Salario mensual | D4: Factor prestacional | E4: Costo mensual empresa | F4: Meses en el proyecto | G4: Costo total | H4: Referencia de mercado
A5: R1 Gerente de proyecto | B5: Duvan Felipe Pacheco Rodriguez | C5: 7500000 | D5: =Supuestos!$B$44 -> 1.38874 | E5: =C5*D5 -> 10415550 | F5: =Supuestos!$B$48 -> 12 | G5: =E5*F5 -> 124986600 | H5: Indeed: gerente de proyectos, promedio $6.653.365/mes; rango $3,7–11,9 M (11 sept. 2026). Se paga por encima del promedio por ser responsable del contrato y del P&G.
A6: R2 Arquitecta TDI (OT/IT) | B6: Paula Valentina Alvarez Chaparro | C6: 6500000 | D6: =Supuestos!$B$44 -> 1.38874 | E6: =C6*D6 -> 9026810 | F6: =Supuestos!$B$48 -> 12 | G6: =E6*F6 -> 108321720 | H6: Indeed: ingeniero de automatización, máximo $5.590.333/mes; se ubica sobre el máximo por especialidad en MES/ERP e ISA-95.
A7: R3 Ingeniero de procesos | B7: David Felipe Garcia Lopez | C7: 5000000 | D7: =Supuestos!$B$44 -> 1.38874 | E7: =C7*D7 -> 6943700 | F7: =Supuestos!$B$48 -> 12 | G7: =E7*F7 -> 83324400 | H7: Indeed: ingeniero de automatización, promedio $3.267.929 y máximo $5.590.333/mes (17 sept. 2026).
A8: R4 Ingeniero de producción | B8: Juan Angel Vargas Rodriguez | C8: 5000000 | D8: =Supuestos!$B$44 -> 1.38874 | E8: =C8*D8 -> 6943700 | F8: =Supuestos!$B$48 -> 12 | G8: =E8*F8 -> 83324400 | H8: Ídem; incluye simulación con Tecnomatix.
A9: R5 Ingeniero de control y robótica | B9: Jose Luis Pulido Fonseca | C9: 5500000 | D9: =Supuestos!$B$44 -> 1.38874 | E9: =C9*D9 -> 7638070 | F9: =Supuestos!$B$48 -> 12 | G9: =E9*F9 -> 91656840 | H9: Ídem, con prima por robótica y seguridad de máquinas.
A10: R6 Ingeniero de supervisión y comunicaciones | B10: Ian Saonni Rodriguez Pulido | C10: 5000000 | D10: =Supuestos!$B$44 -> 1.38874 | E10: =C10*D10 -> 6943700 | F10: =Supuestos!$B$48 -> 12 | G10: =E10*F10 -> 83324400 | H10: Ídem; SCADA Ignition, gemelo digital y redes.
A11: Total equipo | C11: =SUM(C5:C10) -> 34500000 | E11: =SUM(E5:E10) -> 47911530 | G11: =SUM(G5:G10) -> 574938360
A13: Costo horario del equipo (COP/h) | B13: =E11/(6*Supuestos!$B$46) -> 49907.844 | C13: Tarifa facturada / costo horario | E13: =Supuestos!$B$47/B13 -> 3.0055396
A15: Gastos generales de Kuajo
A16: Concepto | B16: Tipo | C16: Valor unitario | D16: Cantidad | E16: Total | F16: Moneda | G16: Total COP | H16: Justificación
A17: Oficina compartida (coworking, 6 puestos) | B17: Mensual | C17: 4000000 | D17: 12 | E17: =C17*D17 -> 48000000 | F17: COP | G17: =E17*IF(F17="USD",Supuestos!$B$6,1) -> 48000000 | H17: Estimación de coworking en Bogotá
A18: Contador y revisoría externa | B18: Mensual | C18: 1500000 | D18: 12 | E18: =C18*D18 -> 18000000 | F18: COP | G18: =E18*IF(F18="USD",Supuestos!$B$6,1) -> 18000000 | H18: Estimación de honorarios
A19: Transporte y viáticos a Cajicá | B19: Mensual | C19: 3000000 | D19: 12 | E19: =C19*D19 -> 36000000 | F19: COP | G19: =E19*IF(F19="USD",Supuestos!$B$6,1) -> 36000000 | H19: ≈ 3 visitas semanales; 1 vehículo compartido
A20: Telecomunicaciones, nube y GitHub | B20: Mensual | C20: 800000 | D20: 12 | E20: =C20*D20 -> 9600000 | F20: COP | G20: =E20*IF(F20="USD",Supuestos!$B$6,1) -> 9600000 | H20: Estimación
A21: Seguros, dotación, EPP y varios | B21: Mensual | C21: 1200000 | D21: 12 | E21: =C21*D21 -> 14400000 | F21: COP | G21: =E21*IF(F21="USD",Supuestos!$B$6,1) -> 14400000 | H21: Estimación
A22: Computadores portátiles de ingeniería | B22: Único | C22: 6500000 | D22: 6 | E22: =C22*D22 -> 39000000 | F22: COP | G22: =E22*IF(F22="USD",Supuestos!$B$6,1) -> 39000000 | H22: Equipo con capacidad para RobotStudio y Tecnomatix
A23: Studio 5000 Logix Designer + Logix Emulate (licencia de desarrollo) | B23: Único | C23: 12000 | D23: 1 | E23: =C23*D23 -> 12000 | F23: USD | G23: =E23*IF(F23="USD",Supuestos!$B$6,1) -> 39281880 | H23: Estimación; cotizar con distribuidor Rockwell
A24: RobotStudio Premium (suscripción anual) | B24: Único | C24: 4000 | D24: 1 | E24: =C24*D24 -> 4000 | F24: USD | G24: =E24*IF(F24="USD",Supuestos!$B$6,1) -> 13093960 | H24: Estimación; cotizar con ABB
A25: Tecnomatix Plant Simulation (suscripción anual) | B25: Único | C25: 15000 | D25: 1 | E25: =C25*D25 -> 15000 | F25: USD | G25: =E25*IF(F25="USD",Supuestos!$B$6,1) -> 49102350 | H25: Estimación; cotizar con Siemens
A26: Constitución de la S.A.S. y registro mercantil | B26: Único | C26: 2000000 | D26: 1 | E26: =C26*D26 -> 2000000 | F26: COP | G26: =E26*IF(F26="USD",Supuestos!$B$6,1) -> 2000000 | H26: Estimación
A27: Total gastos generales | G27: =SUM(G17:G26) -> 268478190
A28: de los cuales mensuales (COP/mes) | G28: =SUMIFS(C17:C26,B17:B26,"Mensual") -> 10500000
A29: de los cuales únicos (mes 0) | G29: =SUMIFS(G17:G26,B17:B26,"Único") -> 142478190

Sheet VSM_Actual
A1: Estado actual de la línea de yogures: VSM, OEE, cuello de botella, lead time y KPIs base
A2: Situación actual = supuestos del caso calibrados con el problema (OEE 55 %, cambio 90 min, rechazo 3 %); se validan en la visita industrial. Futuro = con la propuesta (informe, sección 7).
A4: Parámetro | B4: Situación actual | C4: Con la propuesta | D4: Cálculo, fuente o justificación
A5: 1. Demanda y tiempo disponible
A6: Demanda de los clientes (kg/día) | B6: =Supuestos!$B$66 -> 52400 | C6: =Supuestos!$B$66 -> 52400 | D6: Contrato con cadenas + lanzamiento del griego: la demanda ya es de 52.400 kg/día
A7: Producción de la línea (kg/día) | B7: =Supuestos!$B$62 -> 43700 | C7: =Supuestos!$B$66 -> 52400 | D7: Supuestos (suma de las 3 recetas)
A8: Cumplimiento de la demanda | B8: =B7/B6 -> 0.83396947 | C8: =C7/C6 -> 1 | D8: Producción / demanda: hoy se dejan de atender ≈ 8.700 kg/día
A9: Turnos por día | B9: 2 | C9: 2 | D9: Informe, sección 3: 2 turnos de 8 h, 6 días a la semana
A10: Pausas y relevo por turno (min) | B10: 60 | C10: 60 | D10: Almuerzo, relevo y alistamiento de turno
A11: Tiempo disponible por día (min) | B11: =B9*(480-B10) -> 840 | C11: =C9*(480-C10) -> 840 | D11: 2 × (480 − 60) = 840 min (igual que en la sección 7.4)
A12: Takt time de la línea (s por kg) | B12: =B11*60/B6 -> 0.96183206 | C12: =C11*60/C6 -> 0.96183206 | D12: Tiempo disponible / demanda: el ritmo al que habría que producir para cumplir
A13: Ritmo real de producción (s por kg) | B13: =B11*60/B7 -> 1.1533181 | C13: =C11*60/C7 -> 0.96183206 | D13: Hoy la línea va 20 % más lenta que el takt
A14: Throughput de la línea (kg/h) | B14: =B7/(B11/60) -> 3121.4286 | C14: =C7/(C11/60) -> 3742.8571 | D14: Producción / horas disponibles (14 h)
A15: Producción por turno (kg/turno) | B15: =B7/B9 -> 21850 | C15: =C7/C9 -> 26200 | D15: Producción / 2 turnos
A17: 2. Producción por receta (kg/día y unidades)
A18: Y1 fresa (vaso 150 g): kg/día | B18: =Supuestos!$B$59 -> 26400 | C18: =Supuestos!$B$63 -> 30000 | D18: Supuestos
A19: Y1 fresa (vaso 150 g): unidades/día | B19: =B18/0.15 -> 176000 | C19: =C18/0.15 -> 200000 | D19: kg/día / 0,15 kg por unidad
A20: Y1 fresa (vaso 150 g): lotes/día | B20: =B18/11364 -> 2.3231257 | C20: =C18/11364 -> 2.6399155 | D20: kg/día / 11.364 kg por lote (sección 7.4)
A21: Y1 fresa (vaso 150 g): cajas/día | B21: =B19/24 -> 7333.3333 | C21: =C19/24 -> 8333.3333 | D21: 24 unidades por caja
A22: Y1 fresa (vaso 150 g): pallets/día | B22: =B21/112 -> 65.47619 | C22: =C21/112 -> 74.404762 | D22: 112 cajas por pallet (patrón P1, sección 7.5)
A23: Y2 griego (vaso 500 g): kg/día | B23: =Supuestos!$B$60 -> 5900 | C23: =Supuestos!$B$64 -> 10000 | D23: Supuestos
A24: Y2 griego (vaso 500 g): unidades/día | B24: =B23/0.5 -> 11800 | C24: =C23/0.5 -> 20000 | D24: kg/día / 0,5 kg por unidad
A25: Y2 griego (vaso 500 g): lotes/día | B25: =B23/3054 -> 1.9318926 | C25: =C23/3054 -> 3.2743942 | D25: kg/día / 3.054 kg por lote (sección 7.4)
A26: Y2 griego (vaso 500 g): cajas/día | B26: =B24/12 -> 983.33333 | C26: =C24/12 -> 1666.6667 | D26: 12 unidades por caja
A27: Y2 griego (vaso 500 g): pallets/día | B27: =B26/77 -> 12.770563 | C27: =C26/77 -> 21.645022 | D27: 77 cajas por pallet (patrón P2: 7 × 11, sección 7.5)
A28: Y3 kéfir (botella 1 L): kg/día | B28: =Supuestos!$B$61 -> 11400 | C28: =Supuestos!$B$65 -> 12400 | D28: Supuestos
A29: Y3 kéfir (botella 1 L): unidades/día | B29: =B28/1.03 -> 11067.961 | C29: =C28/1.03 -> 12038.835 | D29: kg/día / 1,03 kg por unidad
A30: Y3 kéfir (botella 1 L): lotes/día | B30: =B28/9800 -> 1.1632653 | C30: =C28/9800 -> 1.2653061 | D30: kg/día / 9.800 kg por lote (sección 7.4)
A31: Y3 kéfir (botella 1 L): cajas/día | B31: =B29/12 -> 922.3301 | C31: =C29/12 -> 1003.2362 | D31: 12 unidades por caja
A32: Y3 kéfir (botella 1 L): pallets/día | B32: =B31/45 -> 20.496224 | C32: =C31/45 -> 22.294139 | D32: 45 cajas por pallet (patrón P3, sección 7.5)
A33: Leche requerida (kg/día) | B33: =B18*Beneficios_OPEX!$B$8+B23*Beneficios_OPEX!$C$8+B28*Beneficios_OPEX!$D$8 -> 50929.4 | C33: =C18*Beneficios_OPEX!$B$8+C23*Beneficios_OPEX!$C$8+C28*Beneficios_OPEX!$D$8 -> 68098 | D33: kg de leche por kg de producto (hoja Beneficios_OPEX, fila 8: 0,757 / 3,274 / 1,02; sección 7.1); límite 70.000 L/día ≈ 72.100 kg
A35: 3. Llenadora de vasos U-232 (Y1 y Y2): OEE y carga
A36: Velocidad nominal formato 150 g (vasos/h) | B36: 28800 | C36: 28800 | D36: Sección 7.4: 16 vasos por ciclo × 30 ciclos/min
A37: Velocidad nominal formato 500 g (vasos/h) | B37: 7200 | C37: 7200 | D37: Sección 7.4: 6 vasos por ciclo × 20 ciclos/min
A38: Tiempo de llenado a velocidad nominal de las unidades buenas (h/día) | B38: =B19/B36+B24/B37 -> 7.75 | C38: =C19/C36+C24/C37 -> 9.7222222 | D38: Unidades buenas / velocidad nominal
A39: Cambios de formato o receta por día | B39: 2 | C39: 2 | D39: Secuencia diaria Y1 → Y2 → Y1 (sección 7.10)
A40: Duración de cada cambio (min) | B40: 90 | C40: 35 | D40: Hoy: CIP y ajustes manuales (problema P2). Con la propuesta: receta ISA-88 y CIP automático (sección 7.10)
A41: Fallas de la llenadora por día | B41: 2.2 | C41: 1.5 | D41: Hoy: atascos de vasos, falla de sellado y ajustes de peso. Con la propuesta: mantenimiento preventivo y predictivo con datos del historian (sección 6.8)
A42: Tiempo medio de reparación de la llenadora, MTTR (min) | B42: 25 | C42: 20 | D42: Con la propuesta: diagnóstico por alarmas en la HMI y repuestos críticos en sitio
A43: Esperas y microparadas por día (min) | B43: 30 | C43: 15 | D43: Hoy: espera de producto por fermentaciones fuera de tiempo. Con la propuesta: secuenciación por el MES
A44: Paradas no planeadas por día (min) | B44: =B41*B42+B43 -> 85 | C44: =C41*C42+C43 -> 45 | D44: Fallas × MTTR + esperas y microparadas
A45: Disponibilidad | B45: =(B11-B39*B40-B44)/B11 -> 0.68452381 | C45: =(C11-C39*C40-C44)/C11 -> 0.86309524 | D45: (Tiempo disponible − cambios − paradas) / tiempo disponible
A46: Tiempo medio entre fallas de la llenadora, MTBF (h) | B46: =(B11-B39*B40-B44)/60/B41 -> 4.3560606 | C46: =(C11-C39*C40-C44)/60/C41 -> 8.0555556 | D46: Tiempo de operación / número de fallas
A47: Rendimiento (velocidad real / nominal) | B47: 0.835 | C47: 0.913 | D47: Hoy se trabaja más lento para controlar el peso a mano y hay microparadas; con la propuesta, control de peso en lazo cerrado con la pesadora
A48: Calidad (unidades buenas / llenadas) | B48: =1-Supuestos!$B$71 -> 0.97 | C48: =1-Supuestos!$B$72 -> 0.99 | D48: Rechazo por peso o sellado: 3 % → 1 % (Supuestos)
A49: OEE de la llenadora de vasos | B49: =B45*B47*B48 -> 0.55443006 | C49: =C45*C47*C48 -> 0.78012589 | D49: Disponibilidad × rendimiento × calidad: 55 % → 78 % (informe, sección 1)
A50: Tiempo que necesita la llenadora (h/día) | B50: =B38/B49 -> 13.978319 | C50: =C38/C49 -> 12.462376 | D50: Tiempo de llenado nominal / OEE
A51: Ocupación de la llenadora de vasos | B51: =B50*60/B11 -> 0.99845133 | C51: =C50*60/C11 -> 0.89016972 | D51: Hoy está al 100 %: es el cuello de botella. Con la propuesta queda al 89 % aunque produce 20 % más
A53: 4. Llenadora de botellas U-233 (Y3)
A54: Velocidad nominal (botellas/h) | B54: 6000 | C54: 6000 | D54: Sección 7.4
A55: OEE de la llenadora de botellas | B55: 0.55 | C55: 0.8 | D55: Hoy con las mismas prácticas manuales; meta de la sección 7.9: ≥ 80 %
A56: Ocupación de la llenadora de botellas | B56: =B29/B54/B55*60/B11 -> 0.23956626 | C56: =C29/C54/C55*60/C11 -> 0.17914933 | D56: Tiene holgura en las dos situaciones
A58: 5. Fermentadores U-221 a U-224
A59: Ocupación por lote de Y1 (h) | B59: =C59+B62 -> 9.25 | C59: 8
A60: Ocupación por lote de Y2 (h) | B60: =C60+B62 -> 11.75 | C60: 10.5
A61: Ocupación por lote de Y3 (h) | B61: =C61+B62 -> 24.75 | C61: 23.5 | D61: Sección 7.3: llenado + incubación + ruptura + vaciado + CIP
A62: Tiempo adicional por lote en la operación manual (h) | B62: 1.25 | C62: 0 | D62: Hoy: 0,75 h de sobretiempo porque el pH final se detecta con muestreo manual cada 30–60 min, y 0,5 h más de CIP manual
A63: Horas-tanque requeridas por día | B63: =B20*B59+B25*B60+B30*B61 -> 72.979467 | C63: =C20*C59+C25*C60+C30*C61 -> 85.235158 | D63: Σ lotes/día × ocupación por lote
A64: Horas-tanque disponibles por día | B64: 96 | C64: 96 | D64: 4 fermentadores × 24 h (la fermentación sigue fuera de turno)
A65: Ocupación de los fermentadores | B65: =B63/B64 -> 0.76020278 | C65: =C63/C64 -> 0.88786622 | D65: Hoy hay holgura; con la propuesta la fermentación pasa a ser el cuello de botella (≈ 90 %)
A67: 6. Encajonado y paletizado
A68: Cajas por día | B68: =B21+B26+B31 -> 9238.9968 | C68: =C21+C26+C31 -> 11003.236 | D68: Suma de las 3 recetas
A69: Pallets por día | B69: =B22+B27+B32 -> 98.742978 | C69: =C22+C27+C32 -> 118.34392 | D69: Suma de las 3 recetas
A70: Operarios de fin de línea por turno | B70: 4 | C70: 1 | D70: Hoy: 2 encajonan y 2 paletizan a mano (cajas de 12–18 kg, problema P6). Con la propuesta: 1 supervisor de la celda robotizada
A71: Cajas por operario-hora | B71: =B68/(B70*B9*(B11/B9)/60) -> 164.98209 | C71: =C68/(C70*C9*(C11/C9)/60) -> 785.94545 | D71: Productividad de la mano de obra de fin de línea
A73: 7. Tiempo de manufactura (MLT) de un lote de Y1, de la leche en silo al despacho, en horas
A74: Etapa | B74: Actual (h) | C74: Con la propuesta (h) | D74: ¿Agrega valor? / justificación
A75: Espera de la leche cruda en silo | B75: 12 | C75: 12 | D75: No (espera necesaria): la leche se procesa dentro de las 24 h siguientes al acopio
A76: Preparación en U-211 | B76: 1.1666667 | C76: 1.1666667 | D76: Sí: transferencia, polvos e hidratación (sección 7.3)
A77: Tratamiento térmico en U-212 | B77: 1 | C77: 1 | D77: Sí: homogeneización y pasteurización
A78: Fermentación | B78: 4.5 | C78: 4.5 | D78: Sí: incubación hasta pH 4,60
A79: Sobretiempo de fermentación por control manual del pH | B79: 0.75 | C79: 0 | D79: No: desaparece con pH en línea y fin de fase automático
A80: Ruptura del coágulo y enfriamiento | B80: 1.1666667 | C80: 1.1666667 | D80: Sí
A81: Espera en el tanque pulmón U-226 | B81: 4 | C81: 1.5 | D81: No: hoy el producto espera a la llenadora (cuello de botella); con el MES se sincroniza
A82: Llenado del lote (74.200 vasos) | B82: =74200/(B36*B47) -> 3.0854957 | C82: =74200/(C36*C47) -> 2.8218936 | D82: Sí: a la velocidad real (rendimiento)
A83: Encajonado y paletizado | B83: 0.5 | C83: 0.3 | D83: Sí
A84: Liberación de calidad en cámara (2–6 °C) | B84: 24 | C84: 24 | D84: No (necesaria): enfriamiento final y liberación microbiológica
A85: Inventario de producto terminado esperando despacho | B85: 48 | C85: 24 | D85: No: hoy el plan es semanal en Excel; con el MES y SAP el plan es diario
A86: MLT total (h) | B86: =SUM(B75:B85) -> 100.16883 | C86: =SUM(C75:C85) -> 72.455227 | D86: Suma de las etapas
A87: MLT total (días) | B87: =B86/24 -> 4.1737012 | C87: =C86/24 -> 3.0189678
A88: Tiempo que agrega valor (h) | B88: =B76+B77+B78+B80+B82+B83 -> 11.418829 | C88: =C76+C77+C78+C80+C82+C83 -> 10.955227 | D88: Suma de las etapas marcadas "Sí"
A89: Relación de valor agregado | B89: =B88/B86 -> 0.11399583 | C89: =C88/C86 -> 0.15119995 | D89: Tiempo que agrega valor / MLT
A91: 7b. MLT de un lote de Y2 griego, en horas
A92: Etapa | B92: Actual (h) | C92: Con la propuesta (h) | D92: ¿Agrega valor? / justificación
A93: Espera de la leche en silo | B93: 12 | C93: 12 | D93: No (espera necesaria)
A94: Transferencia y precalentamiento en U-211 | B94: 0.5 | C94: 0.5 | D94: Sí: sin polvos (sección 7.3)
A95: Tratamiento térmico a 8.300 L/h (92 °C × 6 min) | B95: 1.2 | C95: 1.2 | D95: Sí
A96: Fermentación hasta pH 4,50 | B96: 6 | C96: 6 | D96: Sí
A97: Sobretiempo por control manual del pH | B97: 0.75 | C97: 0 | D97: No: desaparece con pH en línea
A98: Concentración en el separador U-228 y enfriamiento | B98: 2 | C98: 2 | D98: Sí: el suero ácido sale a su tanque
A99: Espera en el tanque pulmón U-226 | B99: 4 | C99: 3 | D99: No: hoy espera a la llenadora. Con la propuesta, el griego se separa de noche y espera en promedio ≈ 3 h a ≤ 10 °C hasta el llenado de la mañana (máx. 12 h)
A100: Llenado del lote (5.990 vasos de 500 g) | B100: =5990/(B37*B47) -> 0.99634065 | C100: =5990/(C37*C47) -> 0.91122064 | D100: Sí
A101: Encajonado y paletizado | B101: 0.5 | C101: 0.3 | D101: Sí
A102: Liberación de calidad en cámara | B102: 24 | C102: 24 | D102: No (necesaria)
A103: Inventario de producto terminado | B103: 48 | C103: 24 | D103: No: plan semanal hoy, diario con la propuesta
A104: MLT total Y2 (h) | B104: =SUM(B93:B103) -> 99.946341 | C104: =SUM(C93:C103) -> 73.911221 | D104: Suma de las etapas
A105: Tiempo que agrega valor Y2 (h) | B105: =B94+B95+B96+B98+B100+B101 -> 11.196341 | C105: =C94+C95+C96+C98+C100+C101 -> 10.911221 | D105: Etapas marcadas "Sí"
A106: Relación de valor agregado Y2 | B106: =B105/B104 -> 0.11202352 | C106: =C105/C104 -> 0.14762604
A108: 7c. MLT de un lote de Y3 kéfir, en horas
A109: Etapa | B109: Actual (h) | C109: Con la propuesta (h) | D109: ¿Agrega valor? / justificación
...

Sheet Simulacion
A1: Simulación de eventos discretos de la línea 1 (sim.py): resultados que validan los KPIs del VSM y de la propuesta
A2: Paso de 1 minuto, 13 semanas por réplica (1 de calentamiento), 10 réplicas con semillas 1 a 10. Valores en azul = salida de sim.py copiada como dato; para actualizarlos se corre "python3 sim.py 10" y se pegan los valores de sim_results.json. El modelo de Tecnomatix Plant Simulation replica esta misma estructura (anexo D).
A4: Parámetros por escenario
A5: Parámetro | B5: Actual | C5: Actual con demanda objetivo | D5: Propuesta con pausas escalonadas | E5: Propuesta con pausas fijas | F5: Fuente
A6: Demanda o programa Y1 (kg/día) | B6: 26400 | C6: 30000 | D6: 30000 | E6: 30000 | F6: VSM_Actual / Supuestos
A7: Demanda o programa Y2 (kg/día) | B7: 5900 | C7: 10000 | D7: 10000 | E7: 10000 | F7: VSM_Actual / Supuestos
A8: Demanda o programa Y3 (kg/día) | B8: 11400 | C8: 12400 | D8: 12400 | E8: 12400 | F8: VSM_Actual / Supuestos
A9: Cambio de formato de la llenadora (min) | B9: 90 | C9: 90 | D9: 35 | E9: 35 | F9: VSM_Actual (actual) y SMED de la propuesta
A10: MTBF de la llenadora de vasos (h) | B10: 4.356 | C10: 4.356 | D10: 8.056 | E10: 8.056 | F10: VSM_Actual
A11: MTTR de la llenadora de vasos (min) | B11: 25 | C11: 25 | D11: 20 | E11: 20 | F11: VSM_Actual
A12: Rendimiento de velocidad de la llenadora | B12: 0.835 | C12: 0.835 | D12: 0.913 | E12: 0.913 | F12: VSM_Actual
A13: Desperdicio de envasado | B13: 0.03 | C13: 0.03 | D13: 0.01 | E13: 0.01 | F13: VSM_Actual
A14: Horas extra por semana | B14: 75 | C14: 75 | D14: 0 | E14: 0 | F14: VSM_Actual
A15: Pausas de la llenadora | B15: Fijas (almuerzo común) | C15: Fijas | D15: Escalonadas (06:00–22:00 continuo) | E15: Fijas | F15: Sección 6.9
A17: Resultados (media de 10 réplicas; ± = desviación estándar)
A18: Indicador | B18: Actual | C18: Actual con demanda objetivo | D18: Propuesta con pausas escalonadas | E18: Propuesta con pausas fijas | F18: Unidad
A19: Producción vendible total | B19: 41186.202 | C19: 38657.052 | D19: 50874.133 | E19: 48960.413 | F19: kg/día
A20: ± desviación | B20: 201.6581 | C20: 311.7304 | D20: 38.733 | E20: 210.123 | F20: kg/día
A21: Producción vendible Y1 | B21: 24704.727 | C21: 22134.375 | D21: 29077.125 | E21: 27951.189 | F21: kg/día
A22: Producción vendible Y2 | B22: 5506.2776 | C22: 7347.6085 | D22: 9564.3953 | E22: 9311.8122 | F22: kg/día
A23: Producción vendible Y3 | B23: 10975.198 | C23: 9175.0683 | D23: 12232.613 | E23: 11697.412 | F23: kg/día
A24: OEE de la llenadora de vasos | B24: 0.5177 | C24: 0.5118 | D24: 0.5867 | E24: 0.6469 | F24: %
A25: Ocupación de la llenadora de vasos | B25: 0.9519 | C25: 0.9181 | D25: 0.7624 | E25: 0.84 | F25: %
A26: Ocupación de los fermentadores | B26: 0.9811 | C26: 0.9865 | D26: 0.9826 | E26: 0.9821 | F26: %
A27: Ocupación de la llenadora de botellas | B27: 0.1714 | C27: 0.1446 | D27: 0.143 | E27: 0.156 | F27: %
A28: Tiempo de paso (MLT) de Y1 | B28: 116.6644 | C28: 116.7263 | D28: 81.0199 | E28: 82.0115 | F28: h
A29: Lotes atrasados al final | B29: 2.7 | C29: 121.3 | D29: 2 | E29: 21.4 | F29: lotes
A30: Demanda o programa total | B30: =SUM(B6:B8) -> 43700 | C30: =SUM(C6:C8) -> 52400 | D30: =SUM(D6:D8) -> 52400 | E30: =SUM(E6:E8) -> 52400 | F30: kg/día
A31: Cumplimiento de la demanda (vendible / programa) | B31: =B19/B30 -> 0.94247603 | C31: =C19/C30 -> 0.73772999 | D31: =D19/D30 -> 0.9708804 | E31: =E19/E30 -> 0.93435903 | F31: %
A32: Aumento de producción vendible frente al actual | B32: =B19/$B$19-1 -> 0 | C32: =C19/$B$19-1 -> -0.061407716 | D32: =D19/$B$19-1 -> 0.23522273 | E32: =E19/$B$19-1 -> 0.18875765 | F32: %
A34: Lectura
A35: La propuesta solo cumple la demanda objetivo (97 % vendible y atraso estable) si las pausas de la llenadora se escalonan; con pausas fijas el atraso crece semana a semana. Los fermentadores siguen ocupados cerca del 98 %, por lo que la siguiente restricción después de la llenadora es la fermentación.

Sheet Lineas_2_3
A1: Líneas 2 y 3: resultados esperados (referencia ±30 %) y proyecto de planta completa
A2: La línea 1 (yogures) está calculada en detalle en las demás hojas. Las líneas 2 (quesos) y 3 (UHT) son una referencia de ±30 % con un método simplificado: sin capital de trabajo, con todo el precio depreciado a 10 años y con recuperación = inversión / flujo promedio de los años 2 a 7. Fase 2 = línea 3 (UHT) y Fase 3 = línea 2 (quesos), según el orden recomendado.
A4: 1. Datos productivos | B4: Línea 1: yogures | C4: Línea 2: quesos | D4: Línea 3: UHT y bebidas | E4: Cálculo, fuente o justificación
A5: Leche asignada a la línea (L/día) | B5: 70000 | C5: 60000 | D5: 90000 | E5: Informe, sección 3 (cifras supuestas del caso; total del alcance 220.000 L/día)
A6: Crecimiento esperado de la producción | B6: =VSM_Actual!$C$7/VSM_Actual!$B$7-1 -> 0.19908467 | C6: 0 | D6: 0.11 | E6: L1: VSM. L2: sin crecimiento (las tinas usan 38 % y la empacadora tiene holgura; la demanda de quesos no es el detonante). L3: +11 % al subir el OEE de las llenadoras de 68 % a 80 % (capacidad +17 %, limitada por la demanda)
A7: Producción con la propuesta (kg/día) | B7: =VSM_Actual!$C$7 -> 52400 | C7: 7470 | D7: 91250 | E7: L1: VSM. L2 y L3: documento general, secciones 8.4 y 9.4
A8: Producción hoy (kg/día) | B8: =VSM_Actual!$B$7 -> 43700 | C8: =C7/(1+C6) -> 7470 | D8: =D7/(1+D6) -> 82207.207 | E8: Producción con la propuesta / (1 + crecimiento)
A9: Leche usada con la propuesta (L/día) | B9: =VSM_Actual!$C$33/1.03 -> 66114.563 | C9: 60000 | D9: 88400 | E9: L1: kg de leche / 1,03 kg/L. L2 y L3: balances de las secciones 8.4 y 9.4 del documento general
A10: Leche usada hoy (L/día) | B10: =VSM_Actual!$B$33/1.03 -> 49446.019 | C10: =C9/(1+C6) -> 60000 | D10: =D9/(1+D6) -> 79639.64 | E10: Proporcional a la producción
A11: Equipo crítico (define la capacidad) | B11: Llenadora de vasos U-232 | C11: Empacadora Q-332 | D11: Llenadoras asépticas L-431/L-432 | E11: Equipo de la línea con mayor ocupación hoy
A12: OEE del equipo crítico hoy | B12: =VSM_Actual!$B$49 -> 0.55443006 | C12: 0.58 | D12: 0.68 | E12: L1: VSM. L2: empaque y moldeo manuales (supuesto del caso). L3: las llenadoras asépticas ya traen control propio, por eso parten más alto (supuesto del caso)
A13: OEE meta | B13: =VSM_Actual!$C$49 -> 0.78012589 | C13: 0.75 | D13: 0.8 | E13: Metas de las secciones 7.9, 8.9 y 9.9 del documento general
A14: Cuello de botella hoy | B14: Llenadora de vasos (100 %) | C14: Moldeo y empaque manuales | D14: Llenadoras asépticas (OEE 68 %) | E14: Análisis de capacidad de cada línea
A15: Restricción con la propuesta | B15: Fermentadores (89 %) | C15: Tinas y prensado | D15: Tren UHT (≈ 9,3 h/día de producción) | E15: Secciones 7.3, 8.3 y 9.3 del documento general
A16: Operarios de fin de línea liberados | B16: =Supuestos!$B$74 -> 6 | C16: 4 | D16: 4 | E16: L1: 6 (Supuestos). L2: robot de moldes y paletizado, 2 por turno. L3: paletizado robotizado, 2 por turno
A17: Robótica propuesta | B17: 2 robots delta + paletizador | C17: Robot sanitario de moldes + paletizador | D17: Paletizador con 2 estaciones | E17: Sección 4 (alcance de la robotización)
A19: 2. Margen de contribución de la línea 3 por receta (COP/L) | B19: U1 leche entera 1 L | C19: U2 deslactosada 1 L | D19: U3 achocolatada 200 mL | E19: Cálculo, fuente o justificación
A20: Precio al consumidor (COP/L) | B20: 5700 | C20: 6500 | D20: 11500 | E20: Caja de 1 L entre $4.671 y $6.400 en 2022 (El Tiempo), ajustada por inflación; U3: $2.300 por 200 mL (Alpin de Alpina $4.050 en Farmatodo, marca premium). Estimaciones
A21: Margen del canal | B21: 0.25 | C21: 0.25 | D21: 0.3 | E21: Leche UHT es un producto de alta rotación y menor margen de canal que el yogur (40 %)
A22: Precio ex-fábrica (COP/L) | B22: =B20*(1-B21) -> 4275 | C22: =C20*(1-C21) -> 4875 | D22: =D20*(1-D21) -> 8050 | E22: Precio al consumidor × (1 − margen del canal)
A23: Leche por L de producto | B23: 1 | C23: 1 | D23: 0.92 | E23: U3 lleva 8 % de azúcar, cacao y estabilizante (sección 9.1)
A24: Costo de leche (COP/L) | B24: =B23*Supuestos!$B$69*(1+Supuestos!$B$70) -> 2240.7 | C24: =C23*Supuestos!$B$69*(1+Supuestos!$B$70) -> 2240.7 | D24: =D23*Supuestos!$B$69*(1+Supuestos!$B$70) -> 2061.444 | E24: Leche × precio al productor × (1 + acopio)
A25: Otros ingredientes (COP/L) | B25: 0 | C25: 150 | D25: 600 | E25: U2: lactasa; U3: cacao, azúcar y carragenina. Estimaciones
A26: Envase aséptico (COP/L) | B26: 450 | C26: 450 | D26: 900 | E26: Caja aséptica de 1 L ≈ $450; de 200 mL con pitillo ≈ $180 por unidad. Estimaciones
A27: Energía, vapor, agua y CIP (COP/L) | B27: 220 | C27: 240 | D27: 250 | E27: UHT a 140 °C con regeneración. Estimación
A28: Logística y gasto comercial (% del precio ex-fábrica) | B28: 0.1 | C28: 0.1 | D28: 0.1 | E28: Producto a temperatura ambiente: menor costo logístico que el yogur (12 %)
A29: Costo variable (COP/L) | B29: =B24+B25+B26+B27+B28*B22 -> 3338.2 | C29: =C24+C25+C26+C27+C28*C22 -> 3568.2 | D29: =D24+D25+D26+D27+D28*D22 -> 4616.444 | E29: Suma de costos variables
A30: Margen de contribución (COP/L) | B30: =B22-B29 -> 936.8 | C30: =C22-C29 -> 1306.8 | D30: =D22-D29 -> 3433.556 | E30: Precio ex-fábrica − costo variable
A31: Margen de contribución (%) | B31: =B30/B22 -> 0.2191345 | C31: =C30/C22 -> 0.26806154 | D31: =D30/D22 -> 0.4265287 | E31: La leche blanca deja poco margen; la achocolatada, mucho más
A32: Producción con la propuesta (L/día) | B32: 49500 | C32: 24750 | D32: 14140 | E32: Sección 9.4 del documento general (U3: 70.700 envases × 0,2 L)
A33: Volumen adicional (L/día) | B33: =B32-B32/(1+$D$6) -> 4905.4054 | C33: =C32-C32/(1+$D$6) -> 2452.7027 | D33: =D32-D32/(1+$D$6) -> 1401.2613 | E33: Mismo crecimiento en las 3 recetas
A34: Margen del volumen adicional de la línea 3 (COP/día) | D34: =SUMPRODUCT(B30:D30,B33:D33) -> 12611885
A35: Costo variable ponderado de la línea 3 (COP/L) | D35: =SUMPRODUCT(B29:D29,B32:D32)/SUM(B32:D32) -> 3607.0864
A37: 3. Parámetros de los beneficios | B37: Línea 1: yogures | C37: Línea 2: quesos | D37: Línea 3: UHT y bebidas | E37: Cálculo, fuente o justificación
A38: Mejora del rendimiento quesero | B38: — | C38: 0.015 | D38: — | E38: Estandarización de grasa y proteína, y control del corte y del desuerado por receta: ≈ 1–2 % más queso con la misma leche (supuesto conservador)
A39: Costo variable por kg (COP) | B39: — | C39: =60000/7470*Supuestos!$B$69*(1+Supuestos!$B$70)+1000 -> 18997.59 | D39: =D35/1.03 -> 3502.0256 | E39: L2: 8,0 L de leche por kg de queso + $1.000 de empaque, sal y cuajo. L3: costo variable ponderado / 1,03 kg/L
A40: Rechazo hoy | B40: =Supuestos!$B$71 -> 0.03 | C40: 0.03 | D40: 0.02 | E40: L2: peso y sellado al vacío. L3: sellado y peso de cajas asépticas (supuestos del caso)
A41: Rechazo con la propuesta | B41: =Supuestos!$B$72 -> 0.01 | C41: 0.01 | D41: 0.008 | E41: Metas de las secciones 8.9 y 9.9
A42: Energía, vapor y agua (COP/kg) | B42: =Supuestos!$B$76 -> 250 | C42: 350 | D42: 220 | E42: L2: cocción e hilado de Q2 y CIP. L3: tren UHT. Estimaciones
A43: Costo evitado por retiro acotado (COP) | B43: =Supuestos!$B$79 -> 800000000 | C43: 300000000 | D43: 500000000 | E43: Proporcional al valor de un día de producción de cada línea
A44: Días de cuarentena que se reducen | B44: — | C44: — | D44: 2 | E44: Liberación electrónica en el MES: de 7 a 5 días en promedio (sección 9.6 del documento general)
A45: Costo de la parada para Pomar (COP) | B45: =Beneficios_OPEX!$B$49 -> 9.2894539e+08 | C45: 150000000 | D45: 200000000 | E45: L1: margen perdido en 12 días. L2 y L3: integración en paradas de mantenimiento programadas de ≈ 6 días
A46: Costo interno de Pomar (COP) | B46: =Supuestos!$B$83 -> 150000000 | C46: 100000000 | D46: 100000000 | E46: Líder de proyecto y apoyo de TI y calidad; menor en L2 y L3 porque la plataforma ya existe
A48: 4. Beneficios anuales en régimen (COP/año, precios de 2026) | B48: Línea 1: yogures | C48: Línea 2: quesos | D48: Línea 3: UHT y bebidas | E48: Cálculo, fuente o justificación
A49: Margen del volumen adicional (atribuible 50 %) | B49: =Beneficios_OPEX!$B$30 -> 6.5507443e+09 | C49: 0 | D49: =D34*Supuestos!$B$58*Supuestos!$B$67 -> 1.967454e+09 | E49: L2: sin crecimiento de volumen. L3: margen del volumen adicional × 312 días × 50 % atribuible
A50: Rendimiento quesero (menos leche por kg de queso) | B50: 0 | C50: =C9*C38*Supuestos!$B$69*(1+Supuestos!$B$70)*Supuestos!$B$58 -> 629188560 | D50: 0 | E50: Leche ahorrada × precio de la leche × 312 días
A51: Producto no rechazado | B51: =Beneficios_OPEX!$B$31 -> 1.5156827e+09 | C51: =(C40-C41)*Supuestos!$B$73*C7*C39*Supuestos!$B$58 -> 664148160 | D51: =(D40-D41)*Supuestos!$B$73*D7*D39*Supuestos!$B$58 -> 8.9732403e+08 | E51: Puntos de rechazo evitados × 75 % × producción × costo variable × 312 días
A52: Mano de obra liberada | B52: =Beneficios_OPEX!$B$32 -> 2.1244405e+08 | C52: =C16*(Supuestos!$B$75*Supuestos!$B$45+Supuestos!$B$35)*12 -> 1.4162937e+08 | D52: =D16*(Supuestos!$B$75*Supuestos!$B$45+Supuestos!$B$35)*12 -> 1.4162937e+08 | E52: Operarios × (salario × factor prestacional + auxilio de transporte) × 12
A53: Ahorro de energía, vapor y agua (3 %) | B53: =Beneficios_OPEX!$B$33 -> 122616000 | C53: =C7*C42*Supuestos!$B$77*Supuestos!$B$58 -> 24471720 | D53: =D7*D42*Supuestos!$B$77*Supuestos!$B$58 -> 187902000 | E53: Producción × costo de energía por kg × 3 % × 312 días
A54: Retiros de producto acotados | B54: =Beneficios_OPEX!$B$34 -> 80000000 | C54: =Supuestos!$B$78*C43 -> 30000000 | D54: =Supuestos!$B$78*D43 -> 50000000 | E54: Probabilidad anual (10 %) × costo evitado
A55: Inventario en cuarentena liberado (costo de oportunidad) | B55: 0 | C55: 0 | D55: =D44*D7*D39*Supuestos!$B$31 -> 87760128 | E55: 2 días de inventario × costo variable × TIO de Pomar
A56: Total beneficios anuales | B56: =SUM(B49:B55) -> 8.4814871e+09 | C56: =SUM(C49:C55) -> 1.4894378e+09 | D56: =SUM(D49:D55) -> 3.3320695e+09
A58: 5. Evaluación financiera para Pomar | B58: Línea 1: yogures | C58: Línea 2: quesos | D58: Línea 3: UHT y bebidas | E58: Cálculo, fuente o justificación
A59: Precio de Kuajo (sin IVA) | B59: =Oferta!$B$58 -> 8.5259187e+09 | C59: =Oferta!$B$60 -> 3.8499874e+09 | D59: =Oferta!$B$59 -> 3.1499897e+09 | E59: Hoja Oferta: Fase 1 calculada; UHT (Fase 2) = 0,45 y quesos (Fase 3) = 0,55 × la automatización de la línea 1 sin la plataforma (±30 %)
A60: Inversión total de Pomar en el año 0 | B60: =B59+B45+B46 -> 9.6048641e+09 | C60: =C59+C45+C46 -> 4.0999874e+09 | D60: =D59+D45+D46 -> 3.4499897e+09 | E60: Precio + parada + costo interno
A61: OPEX anual | B61: =Beneficios_OPEX!$B$46 -> 5.8824485e+08 | C61: =C59*$B$61/$B$59 -> 2.6562947e+08 | D61: =D59*$B$61/$B$59 -> 2.173332e+08 | E61: L1: hoja Beneficios_OPEX. L2 y L3: misma proporción OPEX / precio de la línea 1 (soporte, mantenimiento, repuestos)
A62: Beneficio neto anual en régimen | B62: =B56-B61 -> 7.8932422e+09 | C62: =C56-C61 -> 1.2238083e+09 | D62: =D56-D61 -> 3.1147363e+09 | E62: Beneficios − OPEX
A64: 6. Flujo de caja libre para Pomar (COP) | B64: Línea 1: yogures | C64: Línea 2: quesos | D64: Línea 3: UHT y bebidas | E64: Cálculo, fuente o justificación
A65: Año 0 | B65: =Flujo_Pomar!B26 -> -9.2272332e+09 | C65: =-C59-(C45+C46)*(1-Supuestos!$B$10) -> -4.0124874e+09 | D65: =-D59-(D45+D46)*(1-Supuestos!$B$10) -> -3.3449897e+09 | E65: L1: flujo detallado (hoja Flujo_Pomar). L2 y L3: (beneficios × captura − OPEX) × inflación × (1 − 35 %) + escudo de la depreciación a 10 años
A66: Año 1 | B66: =Flujo_Pomar!C26 -> 2.5411237e+09 | C66: =((C56*Supuestos!$B$68)-C61)*(1+Supuestos!$B$7)^1*(1-Supuestos!$B$10)+C59/Supuestos!$B$85*Supuestos!$B$10 -> 5.5930001e+08 | D66: =((D56*Supuestos!$B$68)-D61)*(1+Supuestos!$B$7)^1*(1-Supuestos!$B$10)+D59/Supuestos!$B$85*Supuestos!$B$10 -> 1.3148198e+09 | E66: Año 1 al 60 % por curva de aprendizaje
A67: Año 2 | B67: =Flujo_Pomar!D26 -> 5.2733739e+09 | C67: =((C56*1)-C61)*(1+Supuestos!$B$7)^2*(1-Supuestos!$B$10)+C59/Supuestos!$B$85*Supuestos!$B$10 -> 9.9513577e+08 | D67: =((D56*1)-D61)*(1+Supuestos!$B$7)^2*(1-Supuestos!$B$10)+D59/Supuestos!$B$85*Supuestos!$B$10 -> 2.3000339e+09
A68: Año 3 | B68: =Flujo_Pomar!E26 -> 6.0566471e+09 | C68: =((C56*1)-C61)*(1+Supuestos!$B$7)^3*(1-Supuestos!$B$10)+C59/Supuestos!$B$85*Supuestos!$B$10 -> 1.0295512e+09 | D68: =((D56*1)-D61)*(1+Supuestos!$B$7)^3*(1-Supuestos!$B$10)+D59/Supuestos!$B$85*Supuestos!$B$10 -> 2.3876252e+09
A69: Año 4 | B69: =Flujo_Pomar!F26 -> 6.2851521e+09 | C69: =((C56*1)-C61)*(1+Supuestos!$B$7)^4*(1-Supuestos!$B$10)+C59/Supuestos!$B$85*Supuestos!$B$10 -> 1.0653433e+09 | D69: =((D56*1)-D61)*(1+Supuestos!$B$7)^4*(1-Supuestos!$B$10)+D59/Supuestos!$B$85*Supuestos!$B$10 -> 2.4787203e+09
A70: Año 5 | B70: =Flujo_Pomar!G26 -> 6.5227973e+09 | C70: =((C56*1)-C61)*(1+Supuestos!$B$7)^5*(1-Supuestos!$B$10)+C59/Supuestos!$B$85*Supuestos!$B$10 -> 1.102567e+09 | D70: =((D56*1)-D61)*(1+Supuestos!$B$7)^5*(1-Supuestos!$B$10)+D59/Supuestos!$B$85*Supuestos!$B$10 -> 2.5734591e+09
A71: Año 6 | B71: =Flujo_Pomar!H26 -> 6.6787199e+09 | C71: =((C56*1)-C61)*(1+Supuestos!$B$7)^6*(1-Supuestos!$B$10)+C59/Supuestos!$B$85*Supuestos!$B$10 -> 1.1412797e+09 | D71: =((D56*1)-D61)*(1+Supuestos!$B$7)^6*(1-Supuestos!$B$10)+D59/Supuestos!$B$85*Supuestos!$B$10 -> 2.6719875e+09
A72: Año 7 | B72: =Flujo_Pomar!I26 -> 8.718455e+09 | C72: =((C56*1)-C61)*(1+Supuestos!$B$7)^7*(1-Supuestos!$B$10)+C59/Supuestos!$B$85*Supuestos!$B$10 -> 1.1815409e+09 | D72: =((D56*1)-D61)*(1+Supuestos!$B$7)^7*(1-Supuestos!$B$10)+D59/Supuestos!$B$85*Supuestos!$B$10 -> 2.774457e+09
A74: 7. Indicadores para Pomar | B74: Línea 1: yogures | C74: Línea 2: quesos | D74: Línea 3: UHT y bebidas | E74: Cálculo, fuente o justificación
A75: VPN a la TIO | B75: =B65+NPV(Supuestos!$B$31,B66:B72) -> 1.5013918e+10 | C75: =C65+NPV(Supuestos!$B$31,C66:C72) -> 1.7207714e+08 | D75: =D65+NPV(Supuestos!$B$31,D66:D72) -> 6.4081344e+09 | E75: Horizonte de 7 años, sin valor residual (igual que la línea 1)
A76: TIR | B76: =IFERROR(IRR(B65:B72),"n.a.") -> 0.48963311 | C76: =IFERROR(IRR(C65:C72),"n.a.") -> 0.14986061 | D76: =IFERROR(IRR(D65:D72),"n.a.") -> 0.57279785 | E76: Comparar con la TIO de Pomar
A77: Recuperación simple (años) | B77: =Flujo_Pomar!$B$36 -> 2.2332537 | C77: =-C65/AVERAGE(C67:C72) -> 3.6950699 | D77: =-D65/AVERAGE(D67:D72) -> 1.3215833 | E77: L1: cálculo exacto (hoja Flujo_Pomar). L2 y L3: inversión / flujo promedio de los años 2 a 7 (aproximación)
A78: Beneficio neto anual / inversión | B78: =B62/B60 -> 0.82179634 | C78: =C62/C60 -> 0.29849075 | D78: =D62/D60 -> 0.90282482 | E78: Cuántas veces al año se recupera la inversión
A79: Factor de valor presente de 1 peso anual (años 1 a 7) | B79: =Supuestos!$B$68*(1+Supuestos!$B$7)/(1+Supuestos!$B$31)+((1+Supuestos!$B$7)/(1+Supuestos!$B$31))^2+((1+Supuestos!$B$7)/(1+Supuestos!$B$31))^3+((1+Supuestos!$B$7)/(1+Supuestos!$B$31))^4+((1+Supuestos!$B$7)/(1+Supuestos!$B$31))^5+((1+Supuestos!$B$7)/(1+Supuestos!$B$31))^6+((1+Supuestos!$B$7)/(1+Supuestos!$B$31))^7 -> 4.6074309 | E79: Con la captura del 60 % en el año 1, la inflación y la TIO
A80: Rendimiento quesero de equilibrio (VPN = 0 en la línea 2) | C80: =C38+(-C75)/((C50/C38)*(1-Supuestos!$B$10)*$B$79) -> 0.013630187 | E80: Mejora de rendimiento que haría rentable la Fase 2 solo con eficiencia
A81: Lectura | B81: Conviene (calculada en detalle) | C81: =IF(C75>0,"Conviene","No conviene solo por eficiencia") -> Conviene | D81: =IF(D75>0,"Conviene","No conviene") -> Conviene | E81: VPN > 0 → conviene
A83: 8. Proyecto de planta completa (3 líneas, 9 productos) | B83: Valor | E83: Cálculo, fuente o justificación
A84: Precio total de Kuajo (3 fases, sin IVA) | B84: =Oferta!$B$58+Oferta!$B$59+Oferta!$B$60 -> 1.5525896e+10 | E84: Fase 1 + Fase 2 + Fase 3 (hoja Oferta)
A85: Costo total para Kuajo | B85: =Oferta!$C$58+Oferta!$C$59+Oferta!$C$60 -> 1.2907746e+10 | E85: Misma relación costo/precio de la Fase 1
A86: Utilidad antes de impuestos de Kuajo | B86: =B84-B85 -> 2.6181501e+09
A87: Utilidad neta de Kuajo | B87: =B86*(1-Supuestos!$B$10) -> 1.7017976e+09 | E87: Después del impuesto de renta de 35 %
A88: Inversión total de Pomar | B88: =B60+C60+D60 -> 1.7154841e+10 | E88: Suma de las 3 líneas
A89: Beneficios anuales en régimen | B89: =B56+C56+D56 -> 1.3302994e+10 | E89: Suma de las 3 líneas
A90: VPN combinado para Pomar (fases escalonadas) | B90: =B75+D75/(1+Supuestos!$B$31)+C75/(1+Supuestos!$B$31)^2 -> 2.0781397e+10 | E90: Fase 2 (UHT) empieza 1 año después y Fase 3 (quesos) 2 años después de la Fase 1 (orden recomendado)
A91: Duración de la Fase 2: UHT (semanas) | B91: 26 | E91: Integración de máquinas OEM con PackML y paletizado; sin fermentación ni recetas complejas
A92: Duración de la Fase 3: quesos (semanas) | B92: 32 | E92: Sin plataforma ni red troncal; sí con robot sanitario de moldes (importación de 20 semanas)
A93: Duración del programa completo (semanas) | B93: =Cronograma!$G$43+B91+B92 -> 106 | E93: Fases en serie con el mismo equipo de 6 personas (≈ 2 años)
A94: Producción total de la planta hoy (kg/día) | B94: =B8+C8+D8 -> 133377.21 | E94: Suma de las 3 líneas
A95: Producción total con el proyecto completo (kg/día) | B95: =B7+C7+D7 -> 151120 | E95: Suma de las 3 líneas
A96: Leche total de la planta hoy (L/día) | B96: =B10+C10+D10+40000 -> 229085.66 | E96: 3 líneas + ≈ 40.000 L/día de productos fuera del alcance (bolsa, mantequilla)
A97: Leche total con el proyecto completo (L/día) | B97: =B9+C9+D9+40000 -> 254514.56 | E97: Debe ser ≤ al acopio de ≈ 260.000 L/día (Portafolio, 2023)
A98: Acopio de Pomar (L/día) | B98: 260000 | E98: 95 millones de litros en 2023 (Portafolio)
A99: Holgura de leche con el proyecto completo | B99: =1-B97/B98 -> 0.021097834 | E99: Si es negativa, faltaría leche

Sheet Recursos_compartidos
A1: Recursos compartidos de la planta: capacidad, demanda y utilización en 3 escenarios
A2: Hoy · con la línea 1 automatizada (Fase 1) · con la planta completa (Fases 1 a 3). Capacidades y factores de consumo: supuestos del caso por validar en la visita industrial.
A4: Dato de entrada | B4: Hoy | C4: Fase 1 (línea 1) | D4: Planta completa | E4: Fuente o justificación
A5: Leche de la línea 1 (L/día) | B5: =Lineas_2_3!$B$10 -> 49446.019 | C5: =Lineas_2_3!$B$9 -> 66114.563 | D5: =Lineas_2_3!$B$9 -> 66114.563 | E5: Hoja Lineas_2_3
A6: Leche de la línea 2 (L/día) | B6: =Lineas_2_3!$C$10 -> 60000 | C6: =Lineas_2_3!$C$10 -> 60000 | D6: =Lineas_2_3!$C$9 -> 60000 | E6: Hoja Lineas_2_3
A7: Leche de la línea 3 (L/día) | B7: =Lineas_2_3!$D$10 -> 79639.64 | C7: =Lineas_2_3!$D$10 -> 79639.64 | D7: =Lineas_2_3!$D$9 -> 88400 | E7: Hoja Lineas_2_3
A8: Leche de otros productos (L/día) | B8: 40000 | C8: 40000 | D8: 40000 | E8: Leche en bolsa, mantequilla y leche condensada (sección 3)
A9: Leche total (L/día) | B9: =SUM(B5:B8) -> 229085.66 | C9: =SUM(C5:C8) -> 245754.2 | D9: =SUM(D5:D8) -> 254514.56 | E9: Suma
A10: Lotes de Y2 por día | B10: =VSM_Actual!$B$25 -> 1.9318926 | C10: =VSM_Actual!$C$25 -> 3.2743942 | D10: =VSM_Actual!$C$25 -> 3.2743942 | E10: Hoja VSM_Actual
A11: Pallets de yogur por día | B11: =VSM_Actual!$B$69 -> 98.742978 | C11: =VSM_Actual!$C$69 -> 118.34392 | D11: =VSM_Actual!$C$69 -> 118.34392 | E11: Hoja VSM_Actual
A12: Días de yogur en cámara (liberación + stock) | B12: 3 | C12: 2 | D12: 2 | E12: Yogur Y1 y Y2: 24 h de liberación + 48 h de stock hoy; 24 h de stock con el plan diario. El kéfir (Y3) se libera a las 48 h: 1 día más
A13: Pallets de queso por día | B13: 18 | C13: 18 | D13: 18 | E13: ≈ 7.470 kg/día en cajas de 10–12 kg (sección 8.5 del documento general)
A14: Pallets de UHT por día | B14: =102/(1+Lineas_2_3!$D$6) -> 91.891892 | C14: =102/(1+Lineas_2_3!$D$6) -> 91.891892 | D14: 102 | E14: ≈ 102 pallets/día con la propuesta (sección 9.4 del documento general)
A15: Días de UHT en cuarentena | B15: 7 | C15: 7 | D15: 5 | E15: Liberación electrónica en el MES en la Fase 3
A17: Factor de consumo | B17: Yogur | C17: Quesos | D17: UHT | E17: Fuente o justificación
A18: Vapor por 1.000 L procesados (kg) | B18: 120 | C18: 150 | D18: 110 | E18: Calentar de 4 a 90 °C con 90 % de regeneración ≈ 15 kg de vapor por 1.000 L, más camisas, agua caliente y CIP. Otros: 60 kg. Estimación
A19: Frío por 1.000 L/día procesados (kW) | B19: 3.5 | C19: 2 | D19: 1 | E19: El yogur enfría de 43 a 20 °C y madura el kéfir a 9 °C; el UHT sale frío de la regeneración. Otros: 1,5 kW. Estimación
A21: Recurso compartido | B21: Hoy | C21: Fase 1 (línea 1) | D21: Planta completa | E21: Capacidad y cálculo
A22: Acopio de leche | E22: Capacidad: 260000 L/día. 95 millones de litros en 2023 (Portafolio)
A23: Demanda | B23: =B9 -> 229085.66 | C23: =C9 -> 245754.2 | D23: =D9 -> 254514.56
A24: Capacidad | B24: 260000 | C24: 260000 | D24: 260000
A25: Utilización | B25: =B23/B24 -> 0.88109869 | C25: =C23/C24 -> 0.94520847 | D25: =D23/D24 -> 0.97890217
A26: Recepción de leche (R-111, 2 plataformas) | E26: Capacidad: 1000000 L/día. 2 plataformas × 25.000 L/h × 20 h; los carrotanques llegan concentrados en la madrugada
A27: Demanda | B27: =B9 -> 229085.66 | C27: =C9 -> 245754.2 | D27: =D9 -> 254514.56
A28: Capacidad | B28: 1000000 | C28: 1000000 | D28: 1000000
A29: Utilización | B29: =B27/B28 -> 0.22908566 | C29: =C27/C28 -> 0.2457542 | D29: =D27/D28 -> 0.25451456
A30: Silos de leche cruda (R-121 a R-123) | E30: Capacidad: 240000 L. 3 × 80.000 L; demanda = leche de 12 h (residencia promedio)
A31: Demanda | B31: =B9*12/24 -> 114542.83 | C31: =C9*12/24 -> 122877.1 | D31: =D9*12/24 -> 127257.28
A32: Capacidad | B32: 240000 | C32: 240000 | D32: 240000
A33: Utilización | B33: =B31/B32 -> 0.47726179 | C33: =C31/C32 -> 0.51198792 | D33: =D31/D32 -> 0.53023867
A34: Tratamiento inicial (R-131: clarificación, descremado, estandarización) | E34: Capacidad: 400000 L/día. 20.000 L/h × 20 h
A35: Demanda | B35: =B9 -> 229085.66 | C35: =C9 -> 245754.2 | D35: =D9 -> 254514.56
A36: Capacidad | B36: 400000 | C36: 400000 | D36: 400000
A37: Utilización | B37: =B35/B36 -> 0.57271415 | C37: =C35/C36 -> 0.61438551 | D37: =D35/D36 -> 0.63628641
A38: CIP-100 de recepción y silos | E38: Capacidad: 20 h/día. Lavado de cada carrotanque de 25.000 L (45 min) + 1 silo por día (1,5 h)
A39: Demanda | B39: =B9/25000*0.75+1.5 -> 8.3725698 | C39: =C9/25000*0.75+1.5 -> 8.8726261 | D39: =D9/25000*0.75+1.5 -> 9.1354369
A40: Capacidad | B40: 20 | C40: 20 | D40: 20
A41: Utilización | B41: =B39/B40 -> 0.41862849 | C41: =C39/C40 -> 0.4436313 | D41: =D39/D40 -> 0.45677184
A42: Vapor (caldera S-511), demanda pico | E42: Capacidad: 4000 kg/h. Σ leche × vapor por 1.000 L / 16 h × 1,5 (factor de pico por arranques simultáneos)
A43: Demanda | B43: =(B5*$B$18+B6*$C$18+B7*$D$18+B8*60)/1000/16*1.5 -> 2446.3015 | C43: =(C5*$B$18+C6*$C$18+C7*$D$18+C8*60)/1000/16*1.5 -> 2633.8226 | D43: =(D5*$B$18+D6*$C$18+D7*$D$18+D8*60)/1000/16*1.5 -> 2724.1638
A44: Capacidad | B44: 4000 | C44: 4000 | D44: 4000
A45: Utilización | B45: =B43/B44 -> 0.61157538 | C45: =C43/C44 -> 0.65845565 | D45: =D43/D44 -> 0.68104096
A46: Agua helada (S-521) | E46: Capacidad: 700 kW. Σ leche × frío por 1.000 L/día
A47: Demanda | B47: =(B5*$B$19+B6*$C$19+B7*$D$19+B8*1.5)/1000 -> 432.70071 | C47: =(C5*$B$19+C6*$C$19+C7*$D$19+C8*1.5)/1000 -> 491.04061 | D47: =(D5*$B$19+D6*$C$19+D7*$D$19+D8*1.5)/1000 -> 499.80097
A48: Capacidad | B48: 700 | C48: 700 | D48: 700
A49: Utilización | B49: =B47/B48 -> 0.61814387 | C49: =C47/C48 -> 0.70148659 | D49: =D47/D48 -> 0.71400139
A50: Manejo de suero (S-551) | E50: Capacidad: 90000 L/día. Suero dulce de quesos (leche − queso) + suero ácido de Y2 (≈ 6.950 kg por lote)
A51: Demanda | B51: =(B6-7470)+B10*6950 -> 65956.654 | C51: =(C6-7470)+C10*6950 -> 75287.04 | D51: =(D6-7470)+D10*6950 -> 75287.04
A52: Capacidad | B52: 90000 | C52: 90000 | D52: 90000
A53: Utilización | B53: =B51/B52 -> 0.73285171 | C53: =C51/C52 -> 0.83652267 | D53: =D51/D52 -> 0.83652267
A54: Cámara refrigerada A-611 (yogur y quesos) | E54: Capacidad: 420 posiciones de pallet en racks de 4 niveles (≈ 20 × 28 m). Pallets/día × días en cámara (kéfir 1 día más); quesos 2 días
A55: Demanda | B55: =(VSM_Actual!$B$22+VSM_Actual!$B$27)*B12+VSM_Actual!$B$32*(B12+1)+B13*2 -> 352.72516 | C55: =(VSM_Actual!$C$22+VSM_Actual!$C$27)*C12+VSM_Actual!$C$32*(C12+1)+C13*2 -> 294.98198 | D55: =(VSM_Actual!$C$22+VSM_Actual!$C$27)*D12+VSM_Actual!$C$32*(D12+1)+D13*2 -> 294.98198
A56: Capacidad | B56: 420 | C56: 420 | D56: 420
A57: Utilización | B57: =B55/B56 -> 0.8398218 | C57: =C55/C56 -> 0.70233806 | D57: =D55/D56 -> 0.70233806
A58: Bodega de UHT en cuarentena A-621 | E58: Capacidad: 800 posiciones de pallet en racks de 5 niveles (≈ 20 × 29,5 m). Pallets/día × días de cuarentena
A59: Demanda | B59: =B14*B15 -> 643.24324 | C59: =C14*C15 -> 643.24324 | D59: =D14*D15 -> 510
A60: Capacidad | B60: 800 | C60: 800 | D60: 800
A61: Utilización | B61: =B59/B60 -> 0.80405405 | C61: =C59/C60 -> 0.80405405 | D61: =D59/D60 -> 0.6375
A62: Muelles de despacho A-631 | E62: Capacidad: 64 camiones/día. 2 muelles × 16 h × 2 camiones/h; 24 pallets por camión
A63: Demanda | B63: =(B11+B13+B14)/24 -> 8.6931196 | C63: =(C11+C13+C14)/24 -> 9.5098256 | D63: =(D11+D13+D14)/24 -> 9.9309968
A64: Capacidad | B64: 64 | C64: 64 | D64: 64
A65: Utilización | B65: =B63/B64 -> 0.13582999 | C65: =C63/C64 -> 0.14859102 | D65: =D63/D64 -> 0.15517182
A67: Lectura
A68: • Con la línea 1 automatizada ningún recurso compartido se satura, pero el acopio de leche sube de 88 % a 95 %: es el recurso más cargado de la planta, porque el griego (Y2) usa 3,3 kg de leche por kg de producto.
A69: • Entre los equipos compartidos, el más cargado es el manejo de suero (de 73 % a 84 %): el griego genera suero ácido y se suma al suero dulce de quesos.
A70: • La cámara refrigerada se libera (de 84 % a 70 %) aunque se produce 20 % más, porque el yogur pasa 2 días en cámara en vez de 3 (el kéfir, 3 en vez de 4).
A71: • Con la planta completa, la restricción de toda la planta pasa a ser el acopio de leche (≈ 98 %).

Sheet Cotizaciones
A1: Cotizaciones y precios de referencia de suministros (Fase 1: línea de yogures + plataforma de planta)
A2: “Publicado” = precio de lista consultado en línea (fuente en la columna L). “Estimación” = valor de referencia de integrador, a reemplazar por 3 cotizaciones formales antes de la orden de compra.
A4: # | B4: Paquete | C4: Actividad EDT | D4: Descripción | E4: Tag o uso | F4: Cant. | G4: Moneda | H4: Precio unitario | I4: Importado | J4: Total COP | K4: Tipo de precio | L4: Fuente | M4: Grupo de compra | N4: Clase para depreciación
A5: 1 | B5: Instrumentación | C5: 4.2 | D5: Caudalímetro Coriolis higiénico (ref. E+H Promass S 300) | E5: FT-211, FT-231 | F5: 2 | G5: USD | H5: 12405.67 | I5: Sí | J5: =F5*H5*IF(G5="USD",Supuestos!$B$6,1)*IF(I5="Sí",1+Supuestos!$B$18,1) -> 87717247 | K5: Rango publicado | L5: Instrumart, Endress+Hauser Coriolis: precio «desde» de la configuración base (se clasifica como rango) | M5: Instrumentación E+H | N5: Equipo
A6: 2 | B6: Instrumentación | C6: 4.2 | D6: Caudalímetro electromagnético higiénico (ref. E+H Promag H 300) | E6: FT-212, FT-228, FT-201 | F6: 3 | G6: USD | H6: 4869.52 | I6: Sí | J6: =F6*H6*IF(G6="USD",Supuestos!$B$6,1)*IF(I6="Sí",1+Supuestos!$B$18,1) -> 51646653 | K6: Publicado | L6: Instrumart, Endress+Hauser flow meters | M6: Instrumentación E+H | N6: Equipo
A7: 3 | B7: Instrumentación | C7: 4.2 | D7: Termómetro higiénico digital (ref. E+H iTHERM TM411, incluye recargo de 8,4 %) | E7: TT-211 a TT-227, TT-201 | F7: 13 | G7: USD | H7: 522.52 | I7: Sí | J7: =F7*H7*IF(G7="USD",Supuestos!$B$6,1)*IF(I7="Sí",1+Supuestos!$B$18,1) -> 24014914 | K7: Publicado | L7: Instrumart, iTHERM TM411 ($482,03 + 8,4 % de recargo) | M7: Instrumentación E+H | N7: Equipo
A8: 4 | B8: Instrumentación | C8: 4.2 | D8: Sensor de pH digital (ref. E+H Memosens CPS77E) | E8: AT-221 a AT-224, AT-227 | F8: 5 | G8: USD | H8: 1045.59 | I8: Sí | J8: =F8*H8*IF(G8="USD",Supuestos!$B$6,1)*IF(I8="Sí",1+Supuestos!$B$18,1) -> 18482733 | K8: Publicado | L8: Instrumart, sensores de pH E+H | M8: Instrumentación E+H | N8: Equipo
A9: 5 | B9: Instrumentación | C9: 4.2 | D9: Transmisor de pH (ref. E+H Liquiline M CM42, pH/ORP) | E9: AT-221 a AT-224, AT-227 | F9: 5 | G9: USD | H9: 3645.04 | I9: Sí | J9: =F9*H9*IF(G9="USD",Supuestos!$B$6,1)*IF(I9="Sí",1+Supuestos!$B$18,1) -> 64432811 | K9: Publicado | L9: Instrumart, Liquiline M CM42 (variante pH) | M9: Instrumentación E+H | N9: Equipo
A10: 6 | B10: Instrumentación | C10: 4.2 | D10: Transmisor de conductividad del CIP (ref. E+H CM42) | E10: AT-201 | F10: 1 | G10: USD | H10: 2658.12 | I10: Sí | J10: =F10*H10*IF(G10="USD",Supuestos!$B$6,1)*IF(I10="Sí",1+Supuestos!$B$18,1) -> 9397435.6 | K10: Publicado | L10: Instrumart, Liquiline M CM42 | M10: Instrumentación E+H | N10: Equipo
A11: 7 | B11: Instrumentación | C11: 4.2 | D11: Sensor toroidal de conductividad higiénico | E11: AT-201 | F11: 1 | G11: USD | H11: 1200 | I11: Sí | J11: =F11*H11*IF(G11="USD",Supuestos!$B$6,1)*IF(I11="Sí",1+Supuestos!$B$18,1) -> 4242443 | K11: Estimación | L11: Estimación de integrador | M11: Instrumentación E+H | N11: Equipo
A12: 8 | B12: Instrumentación | C12: 4.2 | D12: Radar de nivel higiénico (ref. E+H Micropilot FMR43) | E12: LT-211, LT-226, LT-227 | F12: 3 | G12: USD | H12: 1936.25 | I12: Sí | J12: =F12*H12*IF(G12="USD",Supuestos!$B$6,1)*IF(I12="Sí",1+Supuestos!$B$18,1) -> 20536076 | K12: Publicado | L12: Instrumart, Micropilot FMR43 | M12: Instrumentación E+H | N12: Equipo
A13: 9 | B13: Instrumentación | C13: 4.2 | D13: Juego de celdas de carga higiénicas con indicador EtherNet/IP | E13: WT-211, WT-212, WT-221 a WT-224 | F13: 6 | G13: USD | H13: 6000 | I13: Sí | J13: =F13*H13*IF(G13="USD",Supuestos!$B$6,1)*IF(I13="Sí",1+Supuestos!$B$18,1) -> 1.2727329e+08 | K13: Estimación | L13: Estimación de integrador | M13: Instrumentación E+H | N13: Equipo
A14: 10 | B14: Instrumentación | C14: 4.2 | D14: Transmisores de presión y presión diferencial higiénicos | E14: PT-212, PDT-212 | F14: 2 | G14: USD | H14: 1800 | I14: Sí | J14: =F14*H14*IF(G14="USD",Supuestos!$B$6,1)*IF(I14="Sí",1+Supuestos!$B$18,1) -> 12727329 | K14: Estimación | L14: Estimación de integrador | M14: Instrumentación E+H | N14: Equipo
A15: 11 | B15: Instrumentación | C15: 4.2 | D15: Analizador NIR de proteína en línea | E15: AT-228 | F15: 1 | G15: USD | H15: 45000 | I15: Sí | J15: =F15*H15*IF(G15="USD",Supuestos!$B$6,1)*IF(I15="Sí",1+Supuestos!$B$18,1) -> 159091614 | K15: Estimación | L15: Estimación de integrador (rango de mercado US$40.000–80.000) | M15: Analizador NIR | N15: Equipo
A16: 12 | B16: Instrumentación | C16: 4.2 | D16: Interruptores de nivel vibratorios | E16: LSL-221 a LSL-224 | F16: 4 | G16: USD | H16: 600 | I16: Sí | J16: =F16*H16*IF(G16="USD",Supuestos!$B$6,1)*IF(I16="Sí",1+Supuestos!$B$18,1) -> 8484886.1 | K16: Estimación | L16: Estimación de integrador | M16: Instrumentación E+H | N16: Equipo
... A70: 66 | B70: Robótica | C70: 4.3 | D70: Integración de la celda robotizada por el integrador local: ingeniería mecánica de detalle, ensamble, cableado, programación base de los robots, FAT en taller e instalación en sitio | E70: Celda 240 | F70: 1 | G70: COP | H70: 300000000 | I70: No | J70: =F70*H70*IF(G70="USD",Supuestos!$B$6,1)*IF(I70="Sí",1+Supuestos!$B$18,1) -> 300000000 | K70: Estimación | L70: ≈ 28 % del hardware de la celda (rango habitual de integración 25–50 %); se cotiza dentro del contrato llave en mano de robots | M70: Robots y celda | N70: Equipo
D71: Total suministros (costo para Kuajo) | J71: =SUM(J5:J70) -> 5.7713914e+09
D72: Participación de precios publicados | J72: =SUMIFS(J5:J70,K5:K70,"Publicado")/J71 -> 0.12050121
D73: Participación de rangos publicados | J73: =SUMIFS(J5:J70,K5:K70,"Rango publicado")/J71 -> 0.14690073
D74: Participación de estimaciones | J74: =SUMIFS(J5:J70,K5:K70,"Estimación")/J71 -> 0.73259806
D75: Participación de los suministros cotizados en US$ (exposición cambiaria) | J75: =SUMIFS(J5:J70,G5:G70,"USD")/J71 -> 0.72883489

Sheet Instrumentos
A1: Lista única de instrumentos, funciones de control y actuadores de la línea 1 (fuente de las tablas 12.1 y 12.2, del P&ID 12.1 y de la figura 10.1)
A2: Tags según ISA-5.1: primera letra = variable; siguientes = función. Número = unidad (U-2xx). Los variadores toman el número del motor o la bomba que mueven. X = sin clasificar (lectores de código).
A4: Tag | B4: Tipo | C4: Descripción | D4: Unidad | E4: Variable y rango | F4: Señal | G4: Nuevo o existente | H4: Partida de Cotizaciones (#)
A5: FT-211 | B5: Sensor | C5: Caudalímetro másico Coriolis | D5: U-211 | E5: Caudal de leche, 0–30.000 kg/h | F5: 4–20 mA HART | G5: Nuevo | H5: 1
A6: WT-211 | B6: Sensor | C6: Celdas de carga del tanque de preparación | D6: U-211 | E6: Peso, 0–12.000 kg | F6: EtherNet/IP | G6: Nuevo | H6: 9
A7: WT-212 | B7: Sensor | C7: Celdas de carga de la tolva de polvos | D7: U-211 | E7: Peso, 0–2.000 kg | F7: EtherNet/IP | G7: Nuevo | H7: 9
A8: LT-211 | B8: Sensor | C8: Nivel por radar | D8: U-211 | E8: Nivel, 0–100 % | F8: 4–20 mA | G8: Nuevo | H8: 8
A9: TT-211 | B9: Sensor | C9: Termorresistencia PT100 | D9: U-211 | E9: Temperatura, 0–100 °C | F9: 4–20 mA | G9: Nuevo | H9: 3
A10: XI-211 | B10: Sensor | C10: Lector de código de barras de lotes de polvos, azúcar y kits | D10: U-211 | E10: Código de lote | F10: EtherNet/IP | G10: Nuevo | H10: 62
A11: FT-212 | B11: Sensor | C11: Caudalímetro electromagnético del tren térmico | D11: U-212 | E11: Caudal, 0–12.000 L/h | F11: 4–20 mA HART | G11: Nuevo | H11: 2
A12: TT-212A | B12: Sensor | C12: PT100 de calentamiento | D12: U-212 | E12: Temperatura, 0–150 °C | F12: 4–20 mA | G12: Existente (PLC OEM) → PLC de línea | H12: —
A13: TT-212B | B13: Sensor | C13: PT100 doble a la salida del tubo de retención (PCC 1) | D13: U-212 | E13: Temperatura, 0–150 °C | F13: 4–20 mA | G13: Nuevo | H13: 3
A14: TR-212B | B14: Sensor | C14: Registrador sin papel del PCC 1 | D14: U-212 | E14: Registro continuo de temperatura | F14: 4–20 mA / EtherNet/IP | G14: Nuevo | H14: 61
A15: TSL-212B | B15: Sensor | C15: Relé de temperatura baja del registrador, cableado directo a FDV-212 | D15: U-212 | E15: Límite de pasteurización | F15: Digital cableado | G15: Nuevo | H15: 61
A16: TT-212C | B16: Sensor | C16: PT100 de salida hacia el fermentador | D16: U-212 | E16: Temperatura, 0–100 °C | F16: 4–20 mA | G16: Nuevo | H16: 3
A17: PT-212 | B17: Sensor | C17: Presión de homogeneización | D17: U-212 | E17: Presión, 0–300 bar | F17: 4–20 mA | G17: Nuevo (reemplaza el manómetro local) | H17: 10
A18: PDT-212 | B18: Sensor | C18: Presión diferencial del regenerador | D18: U-212 | E18: ±2 bar | F18: 4–20 mA | G18: Nuevo | H18: 10
A19: TT-221 | B19: Sensor | C19: PT100 de incubación | D19: U-221 | E19: Temperatura, 0–100 °C | F19: 4–20 mA | G19: Nuevo | H19: 3
A20: AT-221 | B20: Sensor | C20: Sensor de pH higiénico en línea | D20: U-221 | E20: pH, 2–12 | F20: 4–20 mA HART | G20: Nuevo | H20: 4 y 5
A21: WT-221 | B21: Sensor | C21: Celdas de carga del fermentador | D21: U-221 | E21: Peso, 0–12.000 kg | F21: EtherNet/IP | G21: Nuevo | H21: 9
A22: LSL-221 | B22: Sensor | C22: Interruptor de nivel bajo vibratorio | D22: U-221 | E22: Nivel mínimo | F22: Digital (IO-Link) | G22: Nuevo | H22: 12
A23: XI-221 | B23: Sensor | C23: Lector de código del lote de cultivo (puerto aséptico) | D23: U-221 | E23: Código de lote | F23: EtherNet/IP | G23: Nuevo | H23: 62
A24: TT-222 | B24: Sensor | C24: PT100 de incubación | D24: U-222 | E24: Temperatura, 0–100 °C | F24: 4–20 mA | G24: Nuevo | H24: 3
A25: AT-222 | B25: Sensor | C25: Sensor de pH higiénico en línea | D25: U-222 | E25: pH, 2–12 | F25: 4–20 mA HART | G25: Nuevo | H25: 4 y 5
A26: WT-222 | B26: Sensor | C26: Celdas de carga del fermentador | D26: U-222 | E26: Peso, 0–12.000 kg | F26: EtherNet/IP | G26: Nuevo | H26: 9
A27: LSL-222 | B27: Sensor | C27: Interruptor de nivel bajo vibratorio | D27: U-222 | E27: Nivel mínimo | F27: Digital (IO-Link) | G27: Nuevo | H27: 12
A28: XI-222 | B28: Sensor | C28: Lector de código del lote de cultivo (puerto aséptico) | D28: U-222 | E28: Código de lote | F28: EtherNet/IP | G28: Nuevo | H28: 62
A29: TT-223 | B29: Sensor | C29: PT100 de incubación | D29: U-223 | E29: Temperatura, 0–100 °C | F29: 4–20 mA | G29: Nuevo | H29: 3
A30: AT-223 | B30: Sensor | C30: Sensor de pH higiénico en línea | D30: U-223 | E30: pH, 2–12 | F30: 4–20 mA HART | G30: Nuevo | H30: 4 y 5
A31: WT-223 | B31: Sensor | C31: Celdas de carga del fermentador | D31: U-223 | E31: Peso, 0–12.000 kg | F31: EtherNet/IP | G31: Nuevo | H31: 9
A32: LSL-223 | B32: Sensor | C32: Interruptor de nivel bajo vibratorio | D32: U-223 | E32: Nivel mínimo | F32: Digital (IO-Link) | G32: Nuevo | H32: 12
A33: XI-223 | B33: Sensor | C33: Lector de código del lote de cultivo (puerto aséptico) | D33: U-223 | E33: Código de lote | F33: EtherNet/IP | G33: Nuevo | H33: 62
A34: TT-224 | B34: Sensor | C34: PT100 de incubación | D34: U-224 | E34: Temperatura, 0–100 °C | F34: 4–20 mA | G34: Nuevo | H34: 3
A35: AT-224 | B35: Sensor | C35: Sensor de pH higiénico en línea | D35: U-224 | E35: pH, 2–12 | F35: 4–20 mA HART | G35: Nuevo | H35: 4 y 5
A36: WT-224 | B36: Sensor | C36: Celdas de carga del fermentador | D36: U-224 | E36: Peso, 0–12.000 kg | F36: EtherNet/IP | G36: Nuevo | H36: 9
A37: LSL-224 | B37: Sensor | C37: Interruptor de nivel bajo vibratorio | D37: U-224 | E37: Nivel mínimo | F37: Digital (IO-Link) | G37: Nuevo | H37: 12
A38: XI-224 | B38: Sensor | C38: Lector de código del lote de cultivo (puerto aséptico) | D38: U-224 | E38: Código de lote | F38: EtherNet/IP | G38: Nuevo | H38: 62
A39: AT-228 | B39: Sensor | C39: Analizador NIR de proteína (AE/AT) | D39: U-228 | E39: Proteína, 0–15 % | F39: 4–20 mA | G39: Nuevo | H39: 11
A40: FT-228 | B40: Sensor | C40: Caudalímetro de suero ácido | D40: U-228 | E40: Caudal, 0–8.000 L/h | F40: 4–20 mA | G40: Nuevo | H40: 2
A41: TT-225 | B41: Sensor | C41: PT100 de salida del enfriador | D41: U-225 | E41: Temperatura, 0–50 °C | F41: 4–20 mA | G41: Nuevo | H41: 3
A42: LT-226 | B42: Sensor | C42: Nivel por radar del pulmón | D42: U-226 | E42: Nivel, 0–100 % | F42: 4–20 mA | G42: Nuevo | H42: 8
A43: TT-226 | B43: Sensor | C43: PT100 del pulmón | D43: U-226 | E43: Temperatura, 0–50 °C | F43: 4–20 mA | G43: Nuevo | H43: 3
A44: TT-227 | B44: Sensor | C44: PT100 de maduración | D44: U-227 | E44: Temperatura, 0–50 °C | F44: 4–20 mA | G44: Nuevo | H44: 3
A45: AT-227 | B45: Sensor | C45: pH de maduración | D45: U-227 | E45: pH, 2–12 | F45: 4–20 mA HART | G45: Nuevo | H45: 4 y 5
A46: LT-227 | B46: Sensor | C46: Nivel por radar del tanque de maduración | D46: U-227 | E46: Nivel, 0–100 % | F46: 4–20 mA | G46: Nuevo | H46: 8
A47: FT-231 | B47: Sensor | C47: Caudalímetro másico Coriolis del preparado de fruta | D47: U-231 | E47: Caudal, 0–2.000 kg/h | F47: 4–20 mA HART | G47: Nuevo | H47: 1
A48: XI-231 | B48: Sensor | C48: Lector de código del contenedor de fruta | D48: U-231 | E48: Código de lote | F48: EtherNet/IP | G48: Nuevo | H48: 62
A49: XI-232 | B49: Sensor | C49: Lector de código de bobina, lámina y vasos | D49: U-232 | E49: Código de lote | F49: EtherNet/IP | G49: Nuevo | H49: 62
A50: XI-232F | B50: Sensor | C50: Lector RFID del juego de formato | D50: U-232 | E50: Pieza de formato | F50: EtherNet/IP | G50: Nuevo | H50: 63
A51: XI-233 | B51: Sensor | C51: Lector de código de botellas y tapas | D51: U-233 | E51: Código de lote | F51: EtherNet/IP | G51: Nuevo | H51: 62
A52: WT-234 | B52: Sensor | C52: Pesadora dinámica con rechazo | D52: U-234 | E52: Peso por envase | F52: EtherNet/IP | G52: Nuevo | H52: 13
A53: MD-234 | B53: Sensor | C53: Detector de metales con rechazo (PCC 2) | D53: U-234 | E53: Contaminante metálico | F53: Digital | G53: Nuevo | H53: 14
A54: VS-234 | B54: Sensor | C54: Visión artificial (sello, lote y vencimiento) | D54: U-234 | E54: Imagen / OCR | F54: EtherNet/IP | G54: Nuevo | H54: 15
A55: AT-201 | B55: Sensor | C55: Conductividad del retorno del CIP | D55: CIP-200 | E55: Concentración de soda o ácido | F55: 4–20 mA | G55: Nuevo | H55: 6 y 7
A56: TT-201 | B56: Sensor | C56: Temperatura del retorno del CIP | D56: CIP-200 | E56: 0–100 °C | F56: 4–20 mA | G56: Nuevo | H56: 3
A57: FT-201 | B57: Sensor | C57: Caudal del retorno del CIP | D57: CIP-200 | E57: 0–30.000 L/h | F57: 4–20 mA | G57: Nuevo | H57: 2
A58: TIC-211 | B58: Función en el PLC | C58: Control de precalentamiento (camisa de agua caliente) | D58: U-211 | E58: — | F58: Lógica del PLC de línea | G58: Nuevo | H58: 20
A59: TIC-212 | B59: Función en el PLC | C59: Control de la temperatura de pasteurización | D59: U-212 | E59: — | F59: Lógica del PLC de línea | G59: Nuevo | H59: 20
A60: FIC-212 | B60: Función en el PLC | C60: Control de caudal del tren (velocidad de P-212 con SC-212) | D60: U-212 | E60: — | F60: Lógica del PLC de línea | G60: Nuevo | H60: 20
A61: TIC-212C | B61: Función en el PLC | C61: Control de la temperatura de inoculación | D61: U-212 | E61: — | F61: Lógica del PLC de línea | G61: Nuevo | H61: 20
A62: TIC-221 | B62: Función en el PLC | C62: Control de incubación en rango dividido (U-222 a U-224: TIC-222 a TIC-224) | D62: U-221 a U-224 | E62: — | F62: Lógica del PLC de línea | G62: Nuevo | H62: 20
A63: AI-221 | B63: Función en el PLC | C63: Indicación de pH y condición de fin de fase (U-222 a U-224: AI-222 a AI-224) | D63: U-221 a U-224 | E63: — | F63: Lógica del PLC de línea | G63: Nuevo | H63: 20
A64: AIC-228 | B64: Función en el PLC | C64: Control de la proteína del griego (ajuste del separador) | D64: U-228 | E64: — | F64: Lógica del PLC de línea | G64: Nuevo | H64: 20
A65: TIC-225 | B65: Función en el PLC | C65: Control de la salida del enfriador | D65: U-225 | E65: — | F65: Lógica del PLC de línea | G65: Nuevo | H65: 20
A66: TIC-227 | B66: Función en el PLC | C66: Control de la maduración | D66: U-227 | E66: — | F66: Lógica del PLC de línea | G66: Nuevo | H66: 20
A67: FFIC-231 | B67: Función en el PLC | C67: Control de razón fruta : base 12 : 88 | D67: U-231 | E67: — | F67: Lógica del PLC de línea | G67: Nuevo | H67: 20
A68: XV-211A/B | B68: Actuador | C68: Válvulas de entrada de leche y descarga de U-211 | D68: U-211 | E68: — | F68: 4–20 mA / IO-Link / EtherNet/IP | G68: Nuevo | H68: 16
A69: XV-214 | B69: Actuador | C69: Bypass del homogeneizador (Y2) | D69: U-212 | E69: — | F69: 4–20 mA / IO-Link / EtherNet/IP | G69: Nuevo | H69: 16
A70: XV-221A/B a XV-224A/B | B70: Actuador | C70: Válvulas de llenado y descarga de los fermentadores | D70: U-221 a U-224 | E70: — | F70: 4–20 mA / IO-Link / EtherNet/IP | G70: Nuevo | H70: 16
A71: XV-226A/B | B71: Actuador | C71: Entrada y salida del pulmón | D71: U-226 | E71: — | F71: 4–20 mA / IO-Link / EtherNet/IP | G71: Nuevo | H71: 16
A72: XV-227A/B | B72: Actuador | C72: Entrada y salida del tanque de maduración | D72: U-227 | E72: — | F72: 4–20 mA / IO-Link / EtherNet/IP | G72: Nuevo | H72: 16
A73: XV-228A/B/C | B73: Actuador | C73: Alimentación del separador, salida de suero y bypass del separador (Y1 y Y3) | D73: U-228 | E73: — | F73: 4–20 mA / IO-Link / EtherNet/IP | G73: Nuevo | H73: 16
A74: TCV-211 | B74: Actuador | C74: Válvula de control de agua caliente de la camisa | D74: U-211 | E74: — | F74: 4–20 mA / IO-Link / EtherNet/IP | G74: Nuevo | H74: 17
A75: TCV-212 | B75: Actuador | C75: Válvula de control del agua caliente de E-212B | D75: U-212 | E75: — | F75: 4–20 mA / IO-Link / EtherNet/IP | G75: Nuevo | H75: 17
A76: TCV-212C | B76: Actuador | C76: Válvula de control del agua helada de E-212C | D76: U-212 | E76: — | F76: 4–20 mA / IO-Link / EtherNet/IP | G76: Nuevo | H76: 17
A77: TCV-221A/B a TCV-224A/B | B77: Actuador | C77: Agua caliente (A) y agua helada (B) de las camisas, rango dividido | D77: U-221 a U-224 | E77: — | F77: 4–20 mA / IO-Link / EtherNet/IP | G77: Nuevo | H77: 17
A78: TCV-225 | B78: Actuador | C78: Agua helada del enfriador | D78: U-225 | E78: — | F78: 4–20 mA / IO-Link / EtherNet/IP | G78: Nuevo | H78: 17
A79: TCV-227 | B79: Actuador | C79: Agua helada de la camisa de maduración | D79: U-227 | E79: — | F79: 4–20 mA / IO-Link / EtherNet/IP | G79: Nuevo | H79: 17
... A86: SC-231 | B86: Actuador | C86: Variador de la bomba de fruta P-231 | D86: U-231 | E86: — | F86: 4–20 mA / IO-Link / EtherNet/IP | G86: Nuevo | H86: 19
A87: M-212 | B87: Actuador | C87: Válvula rotativa de polvos (arranque directo; dosifica por diferencia de peso WT-212) | D87: U-211 | E87: — | F87: 4–20 mA / IO-Link / EtherNet/IP | G87: Existente | H87: —
A88: M-214 | B88: Actuador | C88: Homogeneizador (equipo existente, controlador propio) | D88: U-212 | E88: — | F88: 4–20 mA / IO-Link / EtherNet/IP | G88: Existente | H88: —
A89: M-228 | B89: Actuador | C89: Separador centrífugo (equipo existente, controlador propio) | D89: U-228 | E89: — | F89: 4–20 mA / IO-Link / EtherNet/IP | G89: Existente | H89: —
A90: MX-231 | B90: Actuador | C90: Mezclador estático de fruta en línea | D90: U-231 | E90: — | F90: 4–20 mA / IO-Link / EtherNet/IP | G90: Existente | H90: —
A92: Instrumentos de campo (sensores) | C92: =COUNTIF(B5:B90,"Sensor") -> 53
A93: Funciones de control en el PLC | C93: =COUNTIF(B5:B90,"Función en el PLC") -> 10

Sheet Cronograma
A1: Cronograma del proyecto con ruta crítica (método CPM) y diagrama de Gantt
A2: Duraciones en semanas. ES/EF = inicio/fin más temprano; LS/LF = inicio/fin más tardío. La ruta crítica tiene holgura 0.
A3: Fecha de inicio (firma del contrato) | C3: 46398
R4: Semanas del proyecto →
A5: Código | B5: Actividad | C5: Responsable | D5: Duración (sem) | E5: Predecesoras | F5: ES | G5: EF | H5: LS | I5: LF | J5: Holgura | K5: Crítica | L5: Horas Kuajo | M5: Suministros (COP, costo) | N5: Valor planificado (COP, precio) | O5: Inicio | P5: Fin | Q5: Desfase por nivelación (sem) | R5: 1 | S5: 2 | T5: 3 | U5: 4 | V5: 5 | W5: 6 | X5: 7 | Y5: 8 | Z5: 9 | AA5: 10 | AB5: 11 | AC5: 12 | AD5: 13 | AE5: 14 | AF5: 15 | AG5: 16 | AH5: 17 | AI5: 18 | AJ5: 19 | AK5: 20 | AL5: 21 | AM5: 22 | AN5: 23 | AO5: 24 | AP5: 25 | AQ5: 26 | AR5: 27 | AS5: 28 | AT5: 29 | AU5: 30 | AV5: 31 | AW5: 32 | AX5: 33 | AY5: 34 | AZ5: 35 | BA5: 36 | BB5: 37 | BC5: 38 | BD5: 39 | BE5: 40 | BF5: 41 | BG5: 42 | BH5: 43 | BI5: 44 | BJ5: 45 | BK5: 46 | BL5: 47 | BM5: 48 | BN5: 49 | BO5: 50 | BQ5: Horas R1 | BR5: Horas R2 | BS5: Horas R3 | BT5: Horas R4 | BU5: Horas R5 | BV5: Horas R6 | BW5: Control (debe ser 0) | BX5: h/sem R1 | BY5: h/sem R2 | BZ5: h/sem R3 | CA5: h/sem R4 | CB5: h/sem R5 | CC5: h/sem R6
A6: 1.1 | B6: Acta de constitución y reunión de arranque | C6: R1 Duvan | D6: 1 | E6: — | F6: =0+Q6 -> 0 | G6: =F6+D6 -> 1 | H6: =I6-D6 -> 0 | I6: =MIN(H7,H9) -> 1 | J6: =H6-F6 -> 0 | K6: =IF(J6=0,"Sí","") -> Sí | L6: =SUM(BQ6:BV6) -> 80 | M6: =SUMIFS(Cotizaciones!$J$5:$J$70,Cotizaciones!$C$5:$C$70,A6) -> 0 | N6: =(L6*Supuestos!$B$47+M6*(1+Supuestos!$B$50))*(1+Supuestos!$B$51)/(1-Supuestos!$B$52) -> 12995951 | O6: =$C$3+F6*7 -> 46398 | P6: =$C$3+G6*7-IF(D6>0,1,0) -> 46404 | Q6: 0 | R6: =IF(AND(R$5>$F6,R$5<=$G6),IF($K6="Sí",2,1),IF(AND($D6=0,R$5=$G6),3,"")) -> 2 | S6: =IF(AND(S$5>$F6,S$5<=$G6),IF($K6="Sí",2,1),IF(AND($D6=0,S$5=$G6),3,"")) | T6: =IF(AND(T$5>$F6,T$5<=$G6),IF($K6="Sí",2,1),IF(AND($D6=0,T$5=$G6),3,"")) | U6: =IF(AND(U$5>$F6,U$5<=$G6),IF($K6="Sí",2,1),IF(AND($D6=0,U$5=$G6),3,"")) | V6: =IF(AND(V$5>$F6,V$5<=$G6),IF($K6="Sí",2,1),IF(AND($D6=0,V$5=$G6),3,"")) | W6: =IF(AND(W$5>$F6,W$5<=$G6),IF($K6="Sí",2,1),IF(AND($D6=0,W$5=$G6),3,"")) | X6: =IF(AND(X$5>$F6,X$5<=$G6),IF($K6="Sí",2,1),IF(AND($D6=0,X$5=$G6),3,"")) | Y6: =IF(AND(Y$5>$F6,Y$5<=$G6),IF($K6="Sí",2,1),IF(AND($D6=0,Y$5=$G6),3,"")) | ... BO6: =IF(AND(BO$5>$F6,BO$5<=$G6),IF($K6="Sí",2,1),IF(AND($D6=0,BO$5=$G6),3,"")) | BQ6: 44 | BR6: 0 | BS6: 0 | BT6: 0 | BU6: 36 | BV6: 0 | BW6: =L6-80 -> 0 | BX6: =IF($D6=0,0,BQ6/$D6) -> 44 | BY6: =IF($D6=0,0,BR6/$D6) -> 0 | BZ6: =IF($D6=0,0,BS6/$D6) -> 0 | CA6: =IF($D6=0,0,BT6/$D6) -> 0 | CB6: =IF($D6=0,0,BU6/$D6) -> 36 | CC6: =IF($D6=0,0,BV6/$D6) -> 0
A7: 1.2 | B7: Plan de proyecto PM4R (alcance, cronograma, costos, riesgos) | C7: R1 Duvan | D7: 2 | E7: 1.1 | F7: =MAX(G6)+Q7 -> 1 | G7: =F7+D7 -> 3 | H7: =I7-D7 -> 2 | I7: =MIN(H8) -> 4 | J7: =H7-F7 -> 1 | K7: =IF(J7=0,"Sí","") | L7: =SUM(BQ7:BV7) -> 160 | M7: =SUMIFS(Cotizaciones!$J$5:$J$70,Cotizaciones!$C$5:$C$70,A7) -> 0 | N7: =(L7*Supuestos!$B$47+M7*(1+Supuestos!$B$50))*(1+Supuestos!$B$51)/(1-Supuestos!$B$52) -> 25991903 | O7: =$C$3+F7*7 -> 46405 | P7: =$C$3+G7*7-IF(D7>0,1,0) -> 46418 | Q7: 0 | R7: =IF(AND(R$5>$F7,R$5<=$G7),IF($K7="Sí",2,1),IF(AND($D7=0,R$5=$G7),3,"")) | S7: =IF(AND(S$5>$F7,S$5<=$G7),IF($K7="Sí",2,1),IF(AND($D7=0,S$5=$G7),3,"")) -> 1 | T7: =IF(AND(T$5>$F7,T$5<=$G7),IF($K7="Sí",2,1),IF(AND($D7=0,T$5=$G7),3,"")) -> 1 | U7: =IF(AND(U$5>$F7,U$5<=$G7),IF($K7="Sí",2,1),IF(AND($D7=0,U$5=$G7),3,"")) | V7: =IF(AND(V$5>$F7,V$5<=$G7),IF($K7="Sí",2,1),IF(AND($D7=0,V$5=$G7),3,"")) | W7: =IF(AND(W$5>$F7,W$5<=$G7),IF($K7="Sí",2,1),IF(AND($D7=0,W$5=$G7),3,"")) | X7: =IF(AND(X$5>$F7,X$5<=$G7),IF($K7="Sí",2,1),IF(AND($D7=0,X$5=$G7),3,"")) | Y7: =IF(AND(Y$5>$F7,Y$5<=$G7),IF($K7="Sí",2,1),IF(AND($D7=0,Y$5=$G7),3,"")) | ... BO7: =IF(AND(BO$5>$F7,BO$5<=$G7),IF($K7="Sí",2,1),IF(AND($D7=0,BO$5=$G7),3,"")) | BQ7: 87 | BR7: 73 | BS7: 0 | BT7: 0 | BU7: 0 | BV7: 0 | BW7: =L7-160 -> 0 | BX7: =IF($D7=0,0,BQ7/$D7) -> 43.5 | BY7: =IF($D7=0,0,BR7/$D7) -> 36.5 | BZ7: =IF($D7=0,0,BS7/$D7) -> 0 | CA7: =IF($D7=0,0,BT7/$D7) -> 0 | CB7: =IF($D7=0,0,BU7/$D7) -> 0 | CC7: =IF($D7=0,0,BV7/$D7) -> 0
A8: 1.3 | B8: Seguimiento, control de cambios e informes (nivel de esfuerzo) | C8: R1 Duvan | D8: 44 | E8: 1.2 | F8: =MAX(G7)+Q8 -> 3 | G8: =F8+D8 -> 47 | H8: =I8-D8 -> 4 | I8: =MAX($G$6:$G$43) -> 48 | J8: =H8-F8 -> 1 | K8: =IF(J8=0,"Sí","") | L8: =SUM(BQ8:BV8) -> 1100 | M8: =SUMIFS(Cotizaciones!$J$5:$J$70,Cotizaciones!$C$5:$C$70,A8) -> 0 | N8: =(L8*Supuestos!$B$47+M8*(1+Supuestos!$B$50))*(1+Supuestos!$B$51)/(1-Supuestos!$B$52) -> 1.7869433e+08 | O8: =$C$3+F8*7 -> 46419 | P8: =$C$3+G8*7-IF(D8>0,1,0) -> 46726 | Q8: 0 | R8: =IF(AND(R$5>$F8,R$5<=$G8),IF($K8="Sí",2,1),IF(AND($D8=0,R$5=$G8),3,"")) | S8: =IF(AND(S$5>$F8,S$5<=$G8),IF($K8="Sí",2,1),IF(AND($D8=0,S$5=$G8),3,"")) | T8: =IF(AND(T$5>$F8,T$5<=$G8),IF($K8="Sí",2,1),IF(AND($D8=0,T$5=$G8),3,"")) | U8: =IF(AND(U$5>$F8,U$5<=$G8),IF($K8="Sí",2,1),IF(AND($D8=0,U$5=$G8),3,"")) -> 1 | V8: =IF(AND(V$5>$F8,V$5<=$G8),IF($K8="Sí",2,1),IF(AND($D8=0,V$5=$G8),3,"")) -> 1 | W8: =IF(AND(W$5>$F8,W$5<=$G8),IF($K8="Sí",2,1),IF(AND($D8=0,W$5=$G8),3,"")) -> 1 | X8: =IF(AND(X$5>$F8,X$5<=$G8),IF($K8="Sí",2,1),IF(AND($D8=0,X$5=$G8),3,"")) -> 1 | Y8: =IF(AND(Y$5>$F8,Y$5<=$G8),IF($K8="Sí",2,1),IF(AND($D8=0,Y$5=$G8),3,"")) -> 1 | ... BO8: =IF(AND(BO$5>$F8,BO$5<=$G8),IF($K8="Sí",2,1),IF(AND($D8=0,BO$5=$G8),3,"")) | BQ8: 1100 | BR8: 0 | BS8: 0 | BT8: 0 | BU8: 0 | BV8: 0 | BW8: =L8-1100 -> 0 | BX8: =IF($D8=0,0,BQ8/$D8) -> 25 | BY8: =IF($D8=0,0,BR8/$D8) -> 0 | BZ8: =IF($D8=0,0,BS8/$D8) -> 0 | CA8: =IF($D8=0,0,BT8/$D8) -> 0 | CB8: =IF($D8=0,0,BU8/$D8) -> 0 | CC8: =IF($D8=0,0,BV8/$D8) -> 0
A9: 2.1 | B9: Levantamiento en planta y diagnóstico de la situación actual | C9: R3 David Felipe | D9: 3 | E9: 1.1 | F9: =MAX(G6)+Q9 -> 1 | G9: =F9+D9 -> 4 | H9: =I9-D9 -> 1 | I9: =MIN(H10,H11) -> 4 | J9: =H9-F9 -> 0 | K9: =IF(J9=0,"Sí","") -> Sí | L9: =SUM(BQ9:BV9) -> 480 | M9: =SUMIFS(Cotizaciones!$J$5:$J$70,Cotizaciones!$C$5:$C$70,A9) -> 0 | N9: =(L9*Supuestos!$B$47+M9*(1+Supuestos!$B$50))*(1+Supuestos!$B$51)/(1-Supuestos!$B$52) -> 77975709 | O9: =$C$3+F9*7 -> 46405 | P9: =$C$3+G9*7-IF(D9>0,1,0) -> 46425 | Q9: 0 | R9: =IF(AND(R$5>$F9,R$5<=$G9),IF($K9="Sí",2,1),IF(AND($D9=0,R$5=$G9),3,"")) | S9: =IF(AND(S$5>$F9,S$5<=$G9),IF($K9="Sí",2,1),IF(AND($D9=0,S$5=$G9),3,"")) -> 2 | T9: =IF(AND(T$5>$F9,T$5<=$G9),IF($K9="Sí",2,1),IF(AND($D9=0,T$5=$G9),3,"")) -> 2 | U9: =IF(AND(U$5>$F9,U$5<=$G9),IF($K9="Sí",2,1),IF(AND($D9=0,U$5=$G9),3,"")) -> 2 | V9: =IF(AND(V$5>$F9,V$5<=$G9),IF($K9="Sí",2,1),IF(AND($D9=0,V$5=$G9),3,"")) | W9: =IF(AND(W$5>$F9,W$5<=$G9),IF($K9="Sí",2,1),IF(AND($D9=0,W$5=$G9),3,"")) | X9: =IF(AND(X$5>$F9,X$5<=$G9),IF($K9="Sí",2,1),IF(AND($D9=0,X$5=$G9),3,"")) | Y9: =IF(AND(Y$5>$F9,Y$5<=$G9),IF($K9="Sí",2,1),IF(AND($D9=0,Y$5=$G9),3,"")) | ... BO9: =IF(AND(BO$5>$F9,BO$5<=$G9),IF($K9="Sí",2,1),IF(AND($D9=0,BO$5=$G9),3,"")) | BQ9: 0 | BR9: 21 | BS9: 131 | BT9: 131 | BU9: 66 | BV9: 131 | BW9: =L9-480 -> 0 | BX9: =IF($D9=0,0,BQ9/$D9) -> 0 | BY9: =IF($D9=0,0,BR9/$D9) -> 7 | BZ9: =IF($D9=0,0,BS9/$D9) -> 43.666667 | CA9: =IF($D9=0,0,BT9/$D9) -> 43.666667 | CB9: =IF($D9=0,0,BU9/$D9) -> 22 | CC9: =IF($D9=0,0,BV9/$D9) -> 43.666667
A10: 2.2 | B10: VSM actual y línea base de KPIs | C10: R4 Juan | D10: 3 | E10: 2.1 | F10: =MAX(G9)+Q10 -> 4 | G10: =F10+D10 -> 7 | H10: =I10-D10 -> 4 | I10: =MIN(H12) -> 7 | J10: =H10-F10 -> 0 | K10: =IF(J10=0,"Sí","") -> Sí | L10: =SUM(BQ10:BV10) -> 300 | M10: =SUMIFS(Cotizaciones!$J$5:$J$70,Cotizaciones!$C$5:$C$70,A10) -> 0 | N10: =(L10*Supuestos!$B$47+M10*(1+Supuestos!$B$50))*(1+Supuestos!$B$51)/(1-Supuestos!$B$52) -> 48734818 | O10: =$C$3+F10*7 -> 46426 | P10: =$C$3+G10*7-IF(D10>0,1,0) -> 46446 | Q10: 0 | R10: =IF(AND(R$5>$F10,R$5<=$G10),IF($K10="Sí",2,1),IF(AND($D10=0,R$5=$G10),3,"")) | S10: =IF(AND(S$5>$F10,S$5<=$G10),IF($K10="Sí",2,1),IF(AND($D10=0,S$5=$G10),3,"")) | T10: =IF(AND(T$5>$F10,T$5<=$G10),IF($K10="Sí",2,1),IF(AND($D10=0,T$5=$G10),3,"")) | U10: =IF(AND(U$5>$F10,U$5<=$G10),IF($K10="Sí",2,1),IF(AND($D10=0,U$5=$G10),3,"")) | V10: =IF(AND(V$5>$F10,V$5<=$G10),IF($K10="Sí",2,1),IF(AND($D10=0,V$5=$G10),3,"")) -> 2 | W10: =IF(AND(W$5>$F10,W$5<=$G10),IF($K10="Sí",2,1),IF(AND($D10=0,W$5=$G10),3,"")) -> 2 | X10: =IF(AND(X$5>$F10,X$5<=$G10),IF($K10="Sí",2,1),IF(AND($D10=0,X$5=$G10),3,"")) -> 2 | Y10: =IF(AND(Y$5>$F10,Y$5<=$G10),IF($K10="Sí",2,1),IF(AND($D10=0,Y$5=$G10),3,"")) | ... BO10: =IF(AND(BO$5>$F10,BO$5<=$G10),IF($K10="Sí",2,1),IF(AND($D10=0,BO$5=$G10),3,"")) | BQ10: 0 | BR10: 0 | BS10: 38 | BT10: 131 | BU10: 0 | BV10: 131 | BW10: =L10-300 -> 0 | BX10: =IF($D10=0,0,BQ10/$D10) -> 0 | BY10: =IF($D10=0,0,BR10/$D10) -> 0 | BZ10: =IF($D10=0,0,BS10/$D10) -> 12.666667 | CA10: =IF($D10=0,0,BT10/$D10) -> 43.666667 | CB10: =IF($D10=0,0,BU10/$D10) -> 0 | CC10: =IF($D10=0,0,BV10/$D10) -> 43.666667
A11: 2.3 | B11: Arquitectura ISA-95 / ISA-88 y requerimientos | C11: R2 Paula | D11: 3 | E11: 2.1 | F11: =MAX(G9)+Q11 -> 4 | G11: =F11+D11 -> 7 | H11: =I11-D11 -> 4 | I11: =MIN(H12) -> 7 | J11: =H11-F11 -> 0 | K11: =IF(J11=0,"Sí","") -> Sí | L11: =SUM(BQ11:BV11) -> 360 | M11: =SUMIFS(Cotizaciones!$J$5:$J$70,Cotizaciones!$C$5:$C$70,A11) -> 0 | N11: =(L11*Supuestos!$B$47+M11*(1+Supuestos!$B$50))*(1+Supuestos!$B$51)/(1-Supuestos!$B$52) -> 58481781 | O11: =$C$3+F11*7 -> 46426 | P11: =$C$3+G11*7-IF(D11>0,1,0) -> 46446 | Q11: 0 | R11: =IF(AND(R$5>$F11,R$5<=$G11),IF($K11="Sí",2,1),IF(AND($D11=0,R$5=$G11),3,"")) | S11: =IF(AND(S$5>$F11,S$5<=$G11),IF($K11="Sí",2,1),IF(AND($D11=0,S$5=$G11),3,"")) | T11: =IF(AND(T$5>$F11,T$5<=$G11),IF($K11="Sí",2,1),IF(AND($D11=0,T$5=$G11),3,"")) | U11: =IF(AND(U$5>$F11,U$5<=$G11),IF($K11="Sí",2,1),IF(AND($D11=0,U$5=$G11),3,"")) | V11: =IF(AND(V$5>$F11,V$5<=$G11),IF($K11="Sí",2,1),IF(AND($D11=0,V$5=$G11),3,"")) -> 2 | W11: =IF(AND(W$5>$F11,W$5<=$G11),IF($K11="Sí",2,1),IF(AND($D11=0,W$5=$G11),3,"")) -> 2 | X11: =IF(AND(X$5>$F11,X$5<=$G11),IF($K11="Sí",2,1),IF(AND($D11=0,X$5=$G11),3,"")) -> 2 | Y11: =IF(AND(Y$5>$F11,Y$5<=$G11),IF($K11="Sí",2,1),IF(AND($D11=0,Y$5=$G11),3,"")) | ... BO11: =IF(AND(BO$5>$F11,BO$5<=$G11),IF($K11="Sí",2,1),IF(AND($D11=0,BO$5=$G11),3,"")) | BQ11: 0 | BR11: 131 | BS11: 98 | BT11: 0 | BU11: 131 | BV11: 0 | BW11: =L11-360 -> 0 | BX11: =IF($D11=0,0,BQ11/$D11) -> 0 | BY11: =IF($D11=0,0,BR11/$D11) -> 43.666667 | BZ11: =IF($D11=0,0,BS11/$D11) -> 32.666667 | CA11: =IF($D11=0,0,BT11/$D11) -> 0 | CB11: =IF($D11=0,0,BU11/$D11) -> 43.666667 | CC11: =IF($D11=0,0,BV11/$D11) -> 0
A12: 2.4 | B12: Hito: aprobación de la ingeniería conceptual | C12: R1 Duvan | D12: 0 | E12: 2.2, 2.3 | F12: =MAX(G10,G11)+Q12 -> 7 | G12: =F12+D12 -> 7 | H12: =I12-D12 -> 7 | I12: =MIN(H13,H14,H16,H17) -> 7 | J12: =H12-F12 -> 0 | K12: =IF(J12=0,"Sí","") -> Sí | L12: =SUM(BQ12:BV12) -> 0 | M12: =SUMIFS(Cotizaciones!$J$5:$J$70,Cotizaciones!$C$5:$C$70,A12) -> 0 | N12: =(L12*Supuestos!$B$47+M12*(1+Supuestos!$B$50))*(1+Supuestos!$B$51)/(1-Supuestos!$B$52) -> 0 | O12: =$C$3+F12*7 -> 46447 | P12: =$C$3+G12*7-IF(D12>0,1,0) -> 46447 | Q12: 0 | R12: =IF(AND(R$5>$F12,R$5<=$G12),IF($K12="Sí",2,1),IF(AND($D12=0,R$5=$G12),3,"")) | S12: =IF(AND(S$5>$F12,S$5<=$G12),IF($K12="Sí",2,1),IF(AND($D12=0,S$5=$G12),3,"")) | T12: =IF(AND(T$5>$F12,T$5<=$G12),IF($K12="Sí",2,1),IF(AND($D12=0,T$5=$G12),3,"")) | U12: =IF(AND(U$5>$F12,U$5<=$G12),IF($K12="Sí",2,1),IF(AND($D12=0,U$5=$G12),3,"")) | V12: =IF(AND(V$5>$F12,V$5<=$G12),IF($K12="Sí",2,1),IF(AND($D12=0,V$5=$G12),3,"")) | W12: =IF(AND(W$5>$F12,W$5<=$G12),IF($K12="Sí",2,1),IF(AND($D12=0,W$5=$G12),3,"")) | X12: =IF(AND(X$5>$F12,X$5<=$G12),IF($K12="Sí",2,1),IF(AND($D12=0,X$5=$G12),3,"")) -> 3 | Y12: =IF(AND(Y$5>$F12,Y$5<=$G12),IF($K12="Sí",2,1),IF(AND($D12=0,Y$5=$G12),3,"")) | ... BO12: =IF(AND(BO$5>$F12,BO$5<=$G12),IF($K12="Sí",2,1),IF(AND($D12=0,BO$5=$G12),3,"")) | BQ12: 0 | BR12: 0 | BS12: 0 | BT12: 0 | BU12: 0 | BV12: 0 | BW12: =L12-0 -> 0 | BX12: =IF($D12=0,0,BQ12/$D12) -> 0 | BY12: =IF($D12=0,0,BR12/$D12) -> 0 | BZ12: =IF($D12=0,0,BS12/$D12) -> 0 | CA12: =IF($D12=0,0,BT12/$D12) -> 0 | CB12: =IF($D12=0,0,BU12/$D12) -> 0 | CC12: =IF($D12=0,0,BV12/$D12) -> 0
A13: 3.1 | B13: P&ID, lista de instrumentos y hojas de datos | C13: R5 Jose Luis | D13: 5 | E13: 2.4 | F13: =MAX(G12)+Q13 -> 7 | G13: =F13+D13 -> 12 | H13: =I13-D13 -> 8 | I13: =MIN(H15,H22) -> 13 | J13: =H13-F13 -> 1 | K13: =IF(J13=0,"Sí","") | L13: =SUM(BQ13:BV13) -> 400 | M13: =SUMIFS(Cotizaciones!$J$5:$J$70,Cotizaciones!$C$5:$C$70,A13) -> 0 | N13: =(L13*Supuestos!$B$47+M13*(1+Supuestos!$B$50))*(1+Supuestos!$B$51)/(1-Supuestos!$B$52) -> 64979757 | O13: =$C$3+F13*7 -> 46447 | P13: =$C$3+G13*7-IF(D13>0,1,0) -> 46481 | Q13: 0 | R13: =IF(AND(R$5>$F13,R$5<=$G13),IF($K13="Sí",2,1),IF(AND($D13=0,R$5=$G13),3,"")) | S13: =IF(AND(S$5>$F13,S$5<=$G13),IF($K13="Sí",2,1),IF(AND($D13=0,S$5=$G13),3,"")) | T13: =IF(AND(T$5>$F13,T$5<=$G13),IF($K13="Sí",2,1),IF(AND($D13=0,T$5=$G13),3,"")) | U13: =IF(AND(U$5>$F13,U$5<=$G13),IF($K13="Sí",2,1),IF(AND($D13=0,U$5=$G13),3,"")) | V13: =IF(AND(V$5>$F13,V$5<=$G13),IF($K13="Sí",2,1),IF(AND($D13=0,V$5=$G13),3,"")) | W13: =IF(AND(W$5>$F13,W$5<=$G13),IF($K13="Sí",2,1),IF(AND($D13=0,W$5=$G13),3,"")) | X13: =IF(AND(X$5>$F13,X$5<=$G13),IF($K13="Sí",2,1),IF(AND($D13=0,X$5=$G13),3,"")) | Y13: =IF(AND(Y$5>$F13,Y$5<=$G13),IF($K13="Sí",2,1),IF(AND($D13=0,Y$5=$G13),3,"")) -> 1 | ... BO13: =IF(AND(BO$5>$F13,BO$5<=$G13),IF($K13="Sí",2,1),IF(AND($D13=0,BO$5=$G13),3,"")) | BQ13: 56 | BR13: 0 | BS13: 218 | BT13: 59 | BU13: 67 | BV13: 0 | BW13: =L13-400 -> 0 | BX13: =IF($D13=0,0,BQ13/$D13) -> 11.2 | BY13: =IF($D13=0,0,BR13/$D13) -> 0 | BZ13: =IF($D13=0,0,BS13/$D13) -> 43.6 | CA13: =IF($D13=0,0,BT13/$D13) -> 11.8 | CB13: =IF($D13=0,0,BU13/$D13) -> 13.4 | CC13: =IF($D13=0,0,BV13/$D13) -> 0
A14: 3.2 | B14: Especificación funcional (FDS) y recetas ISA-88 | C14: R2 Paula | D14: 7 | E14: 2.4 | F14: =MAX(G12)+Q14 -> 7 | G14: =F14+D14 -> 14 | H14: =I14-D14 -> 8 | I14: =MIN(H18,H19,H20,H27,H28) -> 15 | J14: =H14-F14 -> 1 | K14: =IF(J14=0,"Sí","") | L14: =SUM(BQ14:BV14) -> 480 | M14: =SUMIFS(Cotizaciones!$J$5:$J$70,Cotizaciones!$C$5:$C$70,A14) -> 0 | N14: =(L14*Supuestos!$B$47+M14*(1+Supuestos!$B$50))*(1+Supuestos!$B$51)/(1-Supuestos!$B$52) -> 77975709 | O14: =$C$3+F14*7 -> 46447 | P14: =$C$3+G14*7-IF(D14>0,1,0) -> 46495 | Q14: 0 | R14: =IF(AND(R$5>$F14,R$5<=$G14),IF($K14="Sí",2,1),IF(AND($D14=0,R$5=$G14),3,"")) | S14: =IF(AND(S$5>$F14,S$5<=$G14),IF($K14="Sí",2,1),IF(AND($D14=0,S$5=$G14),3,"")) | T14: =IF(AND(T$5>$F14,T$5<=$G14),IF($K14="Sí",2,1),IF(AND($D14=0,T$5=$G14),3,"")) | U14: =IF(AND(U$5>$F14,U$5<=$G14),IF($K14="Sí",2,1),IF(AND($D14=0,U$5=$G14),3,"")) | V14: =IF(AND(V$5>$F14,V$5<=$G14),IF($K14="Sí",2,1),IF(AND($D14=0,V$5=$G14),3,"")) | W14: =IF(AND(W$5>$F14,W$5<=$G14),IF($K14="Sí",2,1),IF(AND($D14=0,W$5=$G14),3,"")) | X14: =IF(AND(X$5>$F14,X$5<=$G14),IF($K14="Sí",2,1),IF(AND($D14=0,X$5=$G14),3,"")) | Y14: =IF(AND(Y$5>$F14,Y$5<=$G14),IF($K14="Sí",2,1),IF(AND($D14=0,Y$5=$G14),3,"")) -> 1 | ... BO14: =IF(AND(BO$5>$F14,BO$5<=$G14),IF($K14="Sí",2,1),IF(AND($D14=0,BO$5=$G14),3,"")) | BQ14: 0 | BR14: 301 | BS14: 0 | BT14: 0 | BU14: 179 | BV14: 0 | BW14: =L14-480 -> 0 | BX14: =IF($D14=0,0,BQ14/$D14) -> 0 | BY14: =IF($D14=0,0,BR14/$D14) -> 43 | BZ14: =IF($D14=0,0,BS14/$D14) -> 0 | CA14: =IF($D14=0,0,BT14/$D14) -> 0 | CB14: =IF($D14=0,0,BU14/$D14) -> 25.571429 | CC14: =IF($D14=0,0,BV14/$D14) -> 0
A15: 3.3 | B15: Ingeniería eléctrica y diseño de tableros | C15: R5 Jose Luis | D15: 4 | E15: 3.1 | F15: =MAX(G13)+Q15 -> 12 | G15: =F15+D15 -> 16 | H15: =I15-D15 -> 13 | I15: =MIN(H25) -> 17 | J15: =H15-F15 -> 1 | K15: =IF(J15=0,"Sí","") | L15: =SUM(BQ15:BV15) -> 240 | M15: =SUMIFS(Cotizaciones!$J$5:$J$70,Cotizaciones!$C$5:$C$70,A15) -> 0 | N15: =(L15*Supuestos!$B$47+M15*(1+Supuestos!$B$50))*(1+Supuestos!$B$51)/(1-Supuestos!$B$52) -> 38987854 | O15: =$C$3+F15*7 -> 46482 | P15: =$C$3+G15*7-IF(D15>0,1,0) -> 46509 | Q15: 0 | R15: =IF(AND(R$5>$F15,R$5<=$G15),IF($K15="Sí",2,1),IF(AND($D15=0,R$5=$G15),3,"")) | S15: =IF(AND(S$5>$F15,S$5<=$G15),IF($K15="Sí",2,1),IF(AND($D15=0,S$5=$G15),3,"")) | T15: =IF(AND(T$5>$F15,T$5<=$G15),IF($K15="Sí",2,1),IF(AND($D15=0,T$5=$G15),3,"")) | U15: =IF(AND(U$5>$F15,U$5<=$G15),IF($K15="Sí",2,1),IF(AND($D15=0,U$5=$G15),3,"")) | V15: =IF(AND(V$5>$F15,V$5<=$G15),IF($K15="Sí",2,1),IF(AND($D15=0,V$5=$G15),3,"")) | W15: =IF(AND(W$5>$F15,W$5<=$G15),IF($K15="Sí",2,1),IF(AND($D15=0,W$5=$G15),3,"")) | X15: =IF(AND(X$5>$F15,X$5<=$G15),IF($K15="Sí",2,1),IF(AND($D15=0,X$5=$G15),3,"")) | Y15: =IF(AND(Y$5>$F15,Y$5<=$G15),IF($K15="Sí",2,1),IF(AND($D15=0,Y$5=$G15),3,"")) | ... BO15: =IF(AND(BO$5>$F15,BO$5<=$G15),IF($K15="Sí",2,1),IF(AND($D15=0,BO$5=$G15),3,"")) | BQ15: 0 | BR15: 0 | BS15: 30 | BT15: 174 | BU15: 19 | BV15: 17 | BW15: =L15-240 -> 0 | BX15: =IF($D15=0,0,BQ15/$D15) -> 0 | BY15: =IF($D15=0,0,BR15/$D15) -> 0 | BZ15: =IF($D15=0,0,BS15/$D15) -> 7.5 | CA15: =IF($D15=0,0,BT15/$D15) -> 43.5 | CB15: =IF($D15=0,0,BU15/$D15) -> 4.75 | CC15: =IF($D15=0,0,BV15/$D15) -> 4.25
A16: 3.4 | B16: Diseño de la celda robotizada, layout y solicitud de 3 ofertas (RFQ desde la semana 9, en paralelo) | C16: R5 Jose Luis | D16: 4 | E16: 2.4 | F16: =MAX(G12)+Q16 -> 7 | G16: =F16+D16 -> 11 | H16: =I16-D16 -> 7 | I16: =MIN(H21,H24,H32) -> 11 | J16: =H16-F16 -> 0 | K16: =IF(J16=0,"Sí","") -> Sí | L16: =SUM(BQ16:BV16) -> 320 | M16: =SUMIFS(Cotizaciones!$J$5:$J$70,Cotizaciones!$C$5:$C$70,A16) -> 0 | N16: =(L16*Supuestos!$B$47+M16*(1+Supuestos!$B$50))*(1+Supuestos!$B$51)/(1-Supuestos!$B$52) -> 51983806 | O16: =$C$3+F16*7 -> 46447 | P16: =$C$3+G16*7-IF(D16>0,1,0) -> 46474 | Q16: 0 | R16: =IF(AND(R$5>$F16,R$5<=$G16),IF($K16="Sí",2,1),IF(AND($D16=0,R$5=$G16),3,"")) | S16: =IF(AND(S$5>$F16,S$5<=$G16),IF($K16="Sí",2,1),IF(AND($D16=0,S$5=$G16),3,"")) | T16: =IF(AND(T$5>$F16,T$5<=$G16),IF($K16="Sí",2,1),IF(AND($D16=0,T$5=$G16),3,"")) | U16: =IF(AND(U$5>$F16,U$5<=$G16),IF($K16="Sí",2,1),IF(AND($D16=0,U$5=$G16),3,"")) | V16: =IF(AND(V$5>$F16,V$5<=$G16),IF($K16="Sí",2,1),IF(AND($D16=0,V$5=$G16),3,"")) | W16: =IF(AND(W$5>$F16,W$5<=$G16),IF($K16="Sí",2,1),IF(AND($D16=0,W$5=$G16),3,"")) | X16: =IF(AND(X$5>$F16,X$5<=$G16),IF($K16="Sí",2,1),IF(AND($D16=0,X$5=$G16),3,"")) | Y16: =IF(AND(Y$5>$F16,Y$5<=$G16),IF($K16="Sí",2,1),IF(AND($D16=0,Y$5=$G16),3,"")) -> 2 | ... BO16: =IF(AND(BO$5>$F16,BO$5<=$G16),IF($K16="Sí",2,1),IF(AND($D16=0,BO$5=$G16),3,"")) | BQ16: 0 | BR16: 0 | BS16: 0 | BT16: 127 | BU16: 19 | BV16: 174 | BW16: =L16-320 -> 0 | BX16: =IF($D16=0,0,BQ16/$D16) -> 0 | BY16: =IF($D16=0,0,BR16/$D16) -> 0 | BZ16: =IF($D16=0,0,BS16/$D16) -> 0 | CA16: =IF($D16=0,0,BT16/$D16) -> 31.75 | CB16: =IF($D16=0,0,BU16/$D16) -> 4.75 | CC16: =IF($D16=0,0,BV16/$D16) -> 43.5
A17: 3.5 | B17: Diseño de red OT/IT y ciberseguridad (ISA/IEC 62443) | C17: R6 Ian | D17: 4 | E17: 2.4 | F17: =MAX(G12)+Q17 -> 11 | G17: =F17+D17 -> 15 | H17: =I17-D17 -> 13 | I17: =MIN(H25) -> 17 | J17: =H17-F17 -> 2 | K17: =IF(J17=0,"Sí","") | L17: =SUM(BQ17:BV17) -> 160 | M17: =SUMIFS(Cotizaciones!$J$5:$J$70,Cotizaciones!$C$5:$C$70,A17) -> 0 | N17: =(L17*Supuestos!$B$47+M17*(1+Supuestos!$B$50))*(1+Supuestos!$B$51)/(1-Supuestos!$B$52) -> 25991903 | O17: =$C$3+F17*7 -> 46475 | P17: =$C$3+G17*7-IF(D17>0,1,0) -> 46502 | Q17: 4 | R17: =IF(AND(R$5>$F17,R$5<=$G17),IF($K17="Sí",2,1),IF(AND($D17=0,R$5=$G17),3,"")) | S17: =IF(AND(S$5>$F17,S$5<=$G17),IF($K17="Sí",2,1),IF(AND($D17=0,S$5=$G17),3,"")) | T17: =IF(AND(T$5>$F17,T$5<=$G17),IF($K17="Sí",2,1),IF(AND($D17=0,T$5=$G17),3,"")) | U17: =IF(AND(U$5>$F17,U$5<=$G17),IF($K17="Sí",2,1),IF(AND($D17=0,U$5=$G17),3,"")) | V17: =IF(AND(V$5>$F17,V$5<=$G17),IF($K17="Sí",2,1),IF(AND($D17=0,V$5=$G17),3,"")) | W17: =IF(AND(W$5>$F17,W$5<=$G17),IF($K17="Sí",2,1),IF(AND($D17=0,W$5=$G17),3,"")) | X17: =IF(AND(X$5>$F17,X$5<=$G17),IF($K17="Sí",2,1),IF(AND($D17=0,X$5=$G17),3,"")) | Y17: =IF(AND(Y$5>$F17,Y$5<=$G17),IF($K17="Sí",2,1),IF(AND($D17=0,Y$5=$G17),3,"")) | ... BO17: =IF(AND(BO$5>$F17,BO$5<=$G17),IF($K17="Sí",2,1),IF(AND($D17=0,BO$5=$G17),3,"")) | BQ17: 0 | BR17: 0 | BS17: 0 | BT17: 0 | BU17: 0 | BV17: 160 | BW17: =L17-160 -> 0 | BX17: =IF($D17=0,0,BQ17/$D17) -> 0 | BY17: =IF($D17=0,0,BR17/$D17) -> 0 | BZ17: =IF($D17=0,0,BS17/$D17) -> 0 | CA17: =IF($D17=0,0,BT17/$D17) -> 0 | CB17: =IF($D17=0,0,BU17/$D17) -> 0 | CC17: =IF($D17=0,0,BV17/$D17) -> 40
A18: 3.6 | B18: Programación del PLC (fases ISA-88, Grafcet y Ladder) | C18: R5 Jose Luis | D18: 12 | E18: 3.2 | F18: =MAX(G14)+Q18 -> 14 | G18: =F18+D18 -> 26 | H18: =I18-D18 -> 15 | I18: =MIN(H29) -> 27 | J18: =H18-F18 -> 1 | K18: =IF(J18=0,"Sí","") | L18: =SUM(BQ18:BV18) -> 560 | M18: =SUMIFS(Cotizaciones!$J$5:$J$70,Cotizaciones!$C$5:$C$70,A18) -> 0 | N18: =(L18*Supuestos!$B$47+M18*(1+Supuestos!$B$50))*(1+Supuestos!$B$51)/(1-Supuestos!$B$52) -> 90971660 | O18: =$C$3+F18*7 -> 46496 | P18: =$C$3+G18*7-IF(D18>0,1,0) -> 46579 | Q18: 0 | R18: =IF(AND(R$5>$F18,R$5<=$G18),IF($K18="Sí",2,1),IF(AND($D18=0,R$5=$G18),3,"")) | S18: =IF(AND(S$5>$F18,S$5<=$G18),IF($K18="Sí",2,1),IF(AND($D18=0,S$5=$G18),3,"")) | T18: =IF(AND(T$5>$F18,T$5<=$G18),IF($K18="Sí",2,1),IF(AND($D18=0,T$5=$G18),3,"")) | U18: =IF(AND(U$5>$F18,U$5<=$G18),IF($K18="Sí",2,1),IF(AND($D18=0,U$5=$G18),3,"")) | V18: =IF(AND(V$5>$F18,V$5<=$G18),IF($K18="Sí",2,1),IF(AND($D18=0,V$5=$G18),3,"")) | W18: =IF(AND(W$5>$F18,W$5<=$G18),IF($K18="Sí",2,1),IF(AND($D18=0,W$5=$G18),3,"")) | X18: =IF(AND(X$5>$F18,X$5<=$G18),IF($K18="Sí",2,1),IF(AND($D18=0,X$5=$G18),3,"")) | Y18: =IF(AND(Y$5>$F18,Y$5<=$G18),IF($K18="Sí",2,1),IF(AND($D18=0,Y$5=$G18),3,"")) | ... BO18: =IF(AND(BO$5>$F18,BO$5<=$G18),IF($K18="Sí",2,1),IF(AND($D18=0,BO$5=$G18),3,"")) | BQ18: 0 | BR18: 148 | BS18: 0 | BT18: 0 | BU18: 412 | BV18: 0 | BW18: =L18-560 -> 0 | BX18: =IF($D18=0,0,BQ18/$D18) -> 0 | BY18: =IF($D18=0,0,BR18/$D18) -> 12.333333 | BZ18: =IF($D18=0,0,BS18/$D18) -> 0 | CA18: =IF($D18=0,0,BT18/$D18) -> 0 | CB18: =IF($D18=0,0,BU18/$D18) -> 34.333333 | CC18: =IF($D18=0,0,BV18/$D18) -> 0
A19: 3.7 | B19: Configuración del SCADA Ignition (HMI ISA-101) | C19: R6 Ian | D19: 10 | E19: 3.2 | F19: =MAX(G14)+Q19 -> 16 | G19: =F19+D19 -> 26 | H19: =I19-D19 -> 17 | I19: =MIN(H29) -> 27 | J19: =H19-F19 -> 1 | K19: =IF(J19=0,"Sí","") | L19: =SUM(BQ19:BV19) -> 400 | M19: =SUMIFS(Cotizaciones!$J$5:$J$70,Cotizaciones!$C$5:$C$70,A19) -> 0 | N19: =(L19*Supuestos!$B$47+M19*(1+Supuestos!$B$50))*(1+Supuestos!$B$51)/(1-Supuestos!$B$52) -> 64979757 | O19: =$C$3+F19*7 -> 46510 | P19: =$C$3+G19*7-IF(D19>0,1,0) -> 46579 | Q19: 2 | R19: =IF(AND(R$5>$F19,R$5<=$G19),IF($K19="Sí",2,1),IF(AND($D19=0,R$5=$G19),3,"")) | S19: =IF(AND(S$5>$F19,S$5<=$G19),IF($K19="Sí",2,1),IF(AND($D19=0,S$5=$G19),3,"")) | T19: =IF(AND(T$5>$F19,T$5<=$G19),IF($K19="Sí",2,1),IF(AND($D19=0,T$5=$G19),3,"")) | U19: =IF(AND(U$5>$F19,U$5<=$G19),IF($K19="Sí",2,1),IF(AND($D19=0,U$5=$G19),3,"")) | V19: =IF(AND(V$5>$F19,V$5<=$G19),IF($K19="Sí",2,1),IF(AND($D19=0,V$5=$G19),3,"")) | W19: =IF(AND(W$5>$F19,W$5<=$G19),IF($K19="Sí",2,1),IF(AND($D19=0,W$5=$G19),3,"")) | X19: =IF(AND(X$5>$F19,X$5<=$G19),IF($K19="Sí",2,1),IF(AND($D19=0,X$5=$G19),3,"")) | Y19: =IF(AND(Y$5>$F19,Y$5<=$G19),IF($K19="Sí",2,1),IF(AND($D19=0,Y$5=$G19),3,"")) | ... BO19: =IF(AND(BO$5>$F19,BO$5<=$G19),IF($K19="Sí",2,1),IF(AND($D19=0,BO$5=$G19),3,"")) | BQ19: 0 | BR19: 0 | BS19: 75 | BT19: 169 | BU19: 0 | BV19: 156 | BW19: =L19-400 -> 0 | BX19: =IF($D19=0,0,BQ19/$D19) -> 0 | BY19: =IF($D19=0,0,BR19/$D19) -> 0 | BZ19: =IF($D19=0,0,BS19/$D19) -> 7.5 | CA19: =IF($D19=0,0,BT19/$D19) -> 16.9 | CB19: =IF($D19=0,0,BU19/$D19) -> 0 | CC19: =IF($D19=0,0,BV19/$D19) -> 15.6
A20: 3.8 | B20: Configuración del MES e interfaz con SAP | C20: R2 Paula | D20: 14 | E20: 3.2 | F20: =MAX(G14)+Q20 -> 17 | G20: =F20+D20 -> 31 | H20: =I20-D20 -> 19 | I20: =MIN(H31,H39) -> 33 | J20: =H20-F20 -> 2 | K20: =IF(J20=0,"Sí","") | L20: =SUM(BQ20:BV20) -> 400 | M20: =SUMIFS(Cotizaciones!$J$5:$J$70,Cotizaciones!$C$5:$C$70,A20) -> 0 | N20: =(L20*Supuestos!$B$47+M20*(1+Supuestos!$B$50))*(1+Supuestos!$B$51)/(1-Supuestos!$B$52) -> 64979757 | O20: =$C$3+F20*7 -> 46517 | P20: =$C$3+G20*7-IF(D20>0,1,0) -> 46614 | Q20: 3 | R20: =IF(AND(R$5>$F20,R$5<=$G20),IF($K20="Sí",2,1),IF(AND($D20=0,R$5=$G20),3,"")) | S20: =IF(AND(S$5>$F20,S$5<=$G20),IF($K20="Sí",2,1),IF(AND($D20=0,S$5=$G20),3,"")) | T20: =IF(AND(T$5>$F20,T$5<=$G20),IF($K20="Sí",2,1),IF(AND($D20=0,T$5=$G20),3,"")) | U20: =IF(AND(U$5>$F20,U$5<=$G20),IF($K20="Sí",2,1),IF(AND($D20=0,U$5=$G20),3,"")) | V20: =IF(AND(V$5>$F20,V$5<=$G20),IF($K20="Sí",2,1),IF(AND($D20=0,V$5=$G20),3,"")) | W20: =IF(AND(W$5>$F20,W$5<=$G20),IF($K20="Sí",2,1),IF(AND($D20=0,W$5=$G20),3,"")) | X20: =IF(AND(X$5>$F20,X$5<=$G20),IF($K20="Sí",2,1),IF(AND($D20=0,X$5=$G20),3,"")) | Y20: =IF(AND(Y$5>$F20,Y$5<=$G20),IF($K20="Sí",2,1),IF(AND($D20=0,Y$5=$G20),3,"")) | ... BO20: =IF(AND(BO$5>$F20,BO$5<=$G20),IF($K20="Sí",2,1),IF(AND($D20=0,BO$5=$G20),3,"")) | BQ20: 0 | BR20: 400 | BS20: 0 | BT20: 0 | BU20: 0 | BV20: 0 | BW20: =L20-400 -> 0 | BX20: =IF($D20=0,0,BQ20/$D20) -> 0 | BY20: =IF($D20=0,0,BR20/$D20) -> 28.571429 | BZ20: =IF($D20=0,0,BS20/$D20) -> 0 | CA20: =IF($D20=0,0,BT20/$D20) -> 0 | CB20: =IF($D20=0,0,BU20/$D20) -> 0 | CC20: =IF($D20=0,0,BV20/$D20) -> 0
A21: 3.9 | B21: Programación de robots en RobotStudio | C21: R5 Jose Luis | D21: 4 | E21: 3.4 | F21: =MAX(G16)+Q21 -> 16 | G21: =F21+D21 -> 20 | H21: =I21-D21 -> 27 | I21: =MIN(H30) -> 31 | J21: =H21-F21 -> 11 | K21: =IF(J21=0,"Sí","") | L21: =SUM(BQ21:BV21) -> 80 | M21: =SUMIFS(Cotizaciones!$J$5:$J$70,Cotizaciones!$C$5:$C$70,A21) -> 0 | N21: =(L21*Supuestos!$B$47+M21*(1+Supuestos!$B$50))*(1+Supuestos!$B$51)/(1-Supuestos!$B$52) -> 12995951 | O21: =$C$3+F21*7 -> 46510 | P21: =$C$3+G21*7-IF(D21>0,1,0) -> 46537 | Q21: 5 | R21: =IF(AND(R$5>$F21,R$5<=$G21),IF($K21="Sí",2,1),IF(AND($D21=0,R$5=$G21),3,"")) | S21: =IF(AND(S$5>$F21,S$5<=$G21),IF($K21="Sí",2,1),IF(AND($D21=0,S$5=$G21),3,"")) | T21: =IF(AND(T$5>$F21,T$5<=$G21),IF($K21="Sí",2,1),IF(AND($D21=0,T$5=$G21),3,"")) | U21: =IF(AND(U$5>$F21,U$5<=$G21),IF($K21="Sí",2,1),IF(AND($D21=0,U$5=$G21),3,"")) | V21: =IF(AND(V$5>$F21,V$5<=$G21),IF($K21="Sí",2,1),IF(AND($D21=0,V$5=$G21),3,"")) | W21: =IF(AND(W$5>$F21,W$5<=$G21),IF($K21="Sí",2,1),IF(AND($D21=0,W$5=$G21),3,"")) | X21: =IF(AND(X$5>$F21,X$5<=$G21),IF($K21="Sí",2,1),IF(AND($D21=0,X$5=$G21),3,"")) | Y21: =IF(AND(Y$5>$F21,Y$5<=$G21),IF($K21="Sí",2,1),IF(AND($D21=0,Y$5=$G21),3,"")) | ... BO21: =IF(AND(BO$5>$F21,BO$5<=$G21),IF($K21="Sí",2,1),IF(AND($D21=0,BO$5=$G21),3,"")) | BQ21: 0 | BR21: 0 | BS21: 0 | BT21: 61 | BU21: 19 | BV21: 0 | BW21: =L21-80 -> 0 | BX21: =IF($D21=0,0,BQ21/$D21) -> 0 | BY21: =IF($D21=0,0,BR21/$D21) -> 0 | BZ21: =IF($D21=0,0,BS21/$D21) -> 0 | CA21: =IF($D21=0,0,BT21/$D21) -> 15.25 | CB21: =IF($D21=0,0,BU21/$D21) -> 4.75 | CC21: =IF($D21=0,0,BV21/$D21) -> 0
A22: 4.1 | B22: Solicitud de cotizaciones y órdenes de instrumentación y válvulas | C22: R1 Duvan | D22: 3 | E22: 3.1 | F22: =MAX(G13)+Q22 -> 12 | G22: =F22+D22 -> 15 | H22: =I22-D22 -> 18 | I22: =MIN(H23) -> 21 | J22: =H22-F22 -> 6 | K22: =IF(J22=0,"Sí","") | L22: =SUM(BQ22:BV22) -> 160 | M22: =SUMIFS(Cotizaciones!$J$5:$J$70,Cotizaciones!$C$5:$C$70,A22) -> 0 | N22: =(L22*Supuestos!$B$47+M22*(1+Supuestos!$B$50))*(1+Supuestos!$B$51)/(1-Supuestos!$B$52) -> 25991903 | O22: =$C$3+F22*7 -> 46482 | P22: =$C$3+G22*7-IF(D22>0,1,0) -> 46502 | Q22: 0 | R22: =IF(AND(R$5>$F22,R$5<=$G22),IF($K22="Sí",2,1),IF(AND($D22=0,R$5=$G22),3,"")) | S22: =IF(AND(S$5>$F22,S$5<=$G22),IF($K22="Sí",2,1),IF(AND($D22=0,S$5=$G22),3,"")) | T22: =IF(AND(T$5>$F22,T$5<=$G22),IF($K22="Sí",2,1),IF(AND($D22=0,T$5=$G22),3,"")) | U22: =IF(AND(U$5>$F22,U$5<=$G22),IF($K22="Sí",2,1),IF(AND($D22=0,U$5=$G22),3,"")) | V22: =IF(AND(V$5>$F22,V$5<=$G22),IF($K22="Sí",2,1),IF(AND($D22=0,V$5=$G22),3,"")) | W22: =IF(AND(W$5>$F22,W$5<=$G22),IF($K22="Sí",2,1),IF(AND($D22=0,W$5=$G22),3,"")) | X22: =IF(AND(X$5>$F22,X$5<=$G22),IF($K22="Sí",2,1),IF(AND($D22=0,X$5=$G22),3,"")) | Y22: =IF(AND(Y$5>$F22,Y$5<=$G22),IF($K22="Sí",2,1),IF(AND($D22=0,Y$5=$G22),3,"")) | ... BO22: =IF(AND(BO$5>$F22,BO$5<=$G22),IF($K22="Sí",2,1),IF(AND($D22=0,BO$5=$G22),3,"")) | BQ22: 52 | BR22: 0 | BS22: 108 | BT22: 0 | BU22: 0 | BV22: 0 | BW22: =L22-160 -> 0 | BX22: =IF($D22=0,0,BQ22/$D22) -> 17.333333 | BY22: =IF($D22=0,0,BR22/$D22) -> 0 | BZ22: =IF($D22=0,0,BS22/$D22) -> 36 | CA22: =IF($D22=0,0,BT22/$D22) -> 0 | CB22: =IF($D22=0,0,BU22/$D22) -> 0 | CC22: =IF($D22=0,0,BV22/$D22) -> 0
A23: 4.2 | B23: Fabricación y entrega de instrumentación, válvulas e inspección | C23: R1 Duvan | D23: 12 | E23: 4.1 | F23: =MAX(G22)+Q23 -> 15 | G23: =F23+D23 -> 27 | H23: =I23-D23 -> 21 | I23: =MIN(H33) -> 33 | J23: =H23-F23 -> 6 | K23: =IF(J23=0,"Sí","") | L23: =SUM(BQ23:BV23) -> 80 | M23: =SUMIFS(Cotizaciones!$J$5:$J$70,Cotizaciones!$C$5:$C$70,A23) -> 1.7264363e+09 | N23: =(L23*Supuestos!$B$47+M23*(1+Supuestos!$B$50))*(1+Supuestos!$B$51)/(1-Supuestos!$B$52) -> 2.0696918e+09 | O23: =$C$3+F23*7 -> 46503 | P23: =$C$3+G23*7-IF(D23>0,1,0) -> 46586 | Q23: 0 | R23: =IF(AND(R$5>$F23,R$5<=$G23),IF($K23="Sí",2,1),IF(AND($D23=0,R$5=$G23),3,"")) | S23: =IF(AND(S$5>$F23,S$5<=$G23),IF($K23="Sí",2,1),IF(AND($D23=0,S$5=$G23),3,"")) | T23: =IF(AND(T$5>$F23,T$5<=$G23),IF($K23="Sí",2,1),IF(AND($D23=0,T$5=$G23),3,"")) | U23: =IF(AND(U$5>$F23,U$5<=$G23),IF($K23="Sí",2,1),IF(AND($D23=0,U$5=$G23),3,"")) | V23: =IF(AND(V$5>$F23,V$5<=$G23),IF($K23="Sí",2,1),IF(AND($D23=0,V$5=$G23),3,"")) | W23: =IF(AND(W$5>$F23,W$5<=$G23),IF($K23="Sí",2,1),IF(AND($D23=0,W$5=$G23),3,"")) | X23: =IF(AND(X$5>$F23,X$5<=$G23),IF($K23="Sí",2,1),IF(AND($D23=0,X$5=$G23),3,"")) | Y23: =IF(AND(Y$5>$F23,Y$5<=$G23),IF($K23="Sí",2,1),IF(AND($D23=0,Y$5=$G23),3,"")) | ... BO23: =IF(AND(BO$5>$F23,BO$5<=$G23),IF($K23="Sí",2,1),IF(AND($D23=0,BO$5=$G23),3,"")) | BQ23: 80 | BR23: 0 | BS23: 0 | BT23: 0 | BU23: 0 | BV23: 0 | BW23: =L23-80 -> 0 | BX23: =IF($D23=0,0,BQ23/$D23) -> 6.6666667 | BY23: =IF($D23=0,0,BR23/$D23) -> 0 | BZ23: =IF($D23=0,0,BS23/$D23) -> 0 | CA23: =IF($D23=0,0,BT23/$D23) -> 0 | CB23: =IF($D23=0,0,BU23/$D23) -> 0 | CC23: =IF($D23=0,0,BV23/$D23) -> 0
A24: 4.3 | B24: Orden, fabricación, importación, ensamble e integración de robots y celda | C24: R5 Jose Luis | D24: 20 | E24: 3.4 | F24: =MAX(G16)+Q24 -> 11 | G24: =F24+D24 -> 31 | H24: =I24-D24 -> 11 | I24: =MIN(H30) -> 31 | J24: =H24-F24 -> 0 | K24: =IF(J24=0,"Sí","") -> Sí | L24: =SUM(BQ24:BV24) -> 120 | M24: =SUMIFS(Cotizaciones!$J$5:$J$70,Cotizaciones!$C$5:$C$70,A24) -> 1466671836 | N24: =(L24*Supuestos!$B$47+M24*(1+Supuestos!$B$50))*(1+Supuestos!$B$51)/(1-Supuestos!$B$52) -> 1.7667336e+09 | O24: =$C$3+F24*7 -> 46475 | P24: =$C$3+G24*7-IF(D24>0,1,0) -> 46614 | Q24: 0 | R24: =IF(AND(R$5>$F24,R$5<=$G24),IF($K24="Sí",2,1),IF(AND($D24=0,R$5=$G24),3,"")) | S24: =IF(AND(S$5>$F24,S$5<=$G24),IF($K24="Sí",2,1),IF(AND($D24=0,S$5=$G24),3,"")) | T24: =IF(AND(T$5>$F24,T$5<=$G24),IF($K24="Sí",2,1),IF(AND($D24=0,T$5=$G24),3,"")) | U24: =IF(AND(U$5>$F24,U$5<=$G24),IF($K24="Sí",2,1),IF(AND($D24=0,U$5=$G24),3,"")) | V24: =IF(AND(V$5>$F24,V$5<=$G24),IF($K24="Sí",2,1),IF(AND($D24=0,V$5=$G24),3,"")) | W24: =IF(AND(W$5>$F24,W$5<=$G24),IF($K24="Sí",2,1),IF(AND($D24=0,W$5=$G24),3,"")) | X24: =IF(AND(X$5>$F24,X$5<=$G24),IF($K24="Sí",2,1),IF(AND($D24=0,X$5=$G24),3,"")) | Y24: =IF(AND(Y$5>$F24,Y$5<=$G24),IF($K24="Sí",2,1),IF(AND($D24=0,Y$5=$G24),3,"")) | ... BO24: =IF(AND(BO$5>$F24,BO$5<=$G24),IF($K24="Sí",2,1),IF(AND($D24=0,BO$5=$G24),3,"")) | BQ24: 28 | BR24: 0 | BS24: 0 | BT24: 0 | BU24: 92 | BV24: 0 | BW24: =L24-120 -> 0 | BX24: =IF($D24=0,0,BQ24/$D24) -> 1.4 | BY24: =IF($D24=0,0,BR24/$D24) -> 0 | BZ24: =IF($D24=0,0,BS24/$D24) -> 0 | CA24: =IF($D24=0,0,BT24/$D24) -> 0 | CB24: =IF($D24=0,0,BU24/$D24) -> 4.6 | CC24: =IF($D24=0,0,BV24/$D24) -> 0
A25: 4.4 | B25: Compra y entrega de PLC, E/S, red y servidores | C25: R6 Ian | D25: 10 | E25: 3.5, 3.3 | F25: =MAX(G17,G15)+Q25 -> 16 | G25: =F25+D25 -> 26 | H25: =I25-D25 -> 17 | I25: =MIN(H26,H36) -> 27 | J25: =H25-F25 -> 1 | K25: =IF(J25=0,"Sí","") | L25: =SUM(BQ25:BV25) -> 80 | M25: =SUMIFS(Cotizaciones!$J$5:$J$70,Cotizaciones!$C$5:$C$70,A25) -> 7.6383616e+08 | N25: =(L25*Supuestos!$B$47+M25*(1+Supuestos!$B$50))*(1+Supuestos!$B$51)/(1-Supuestos!$B$52) -> 9.2295056e+08 | O25: =$C$3+F25*7 -> 46510 | P25: =$C$3+G25*7-IF(D25>0,1,0) -> 46579 | Q25: 0 | R25: =IF(AND(R$5>$F25,R$5<=$G25),IF($K25="Sí",2,1),IF(AND($D25=0,R$5=$G25),3,"")) | S25: =IF(AND(S$5>$F25,S$5<=$G25),IF($K25="Sí",2,1),IF(AND($D25=0,S$5=$G25),3,"")) | T25: =IF(AND(T$5>$F25,T$5<=$G25),IF($K25="Sí",2,1),IF(AND($D25=0,T$5=$G25),3,"")) | U25: =IF(AND(U$5>$F25,U$5<=$G25),IF($K25="Sí",2,1),IF(AND($D25=0,U$5=$G25),3,"")) | V25: =IF(AND(V$5>$F25,V$5<=$G25),IF($K25="Sí",2,1),IF(AND($D25=0,V$5=$G25),3,"")) | W25: =IF(AND(W$5>$F25,W$5<=$G25),IF($K25="Sí",2,1),IF(AND($D25=0,W$5=$G25),3,"")) | X25: =IF(AND(X$5>$F25,X$5<=$G25),IF($K25="Sí",2,1),IF(AND($D25=0,X$5=$G25),3,"")) | Y25: =IF(AND(Y$5>$F25,Y$5<=$G25),IF($K25="Sí",2,1),IF(AND($D25=0,Y$5=$G25),3,"")) | ... BO25: =IF(AND(BO$5>$F25,BO$5<=$G25),IF($K25="Sí",2,1),IF(AND($D25=0,BO$5=$G25),3,"")) | BQ25: 80 | BR25: 0 | BS25: 0 | BT25: 0 | BU25: 0 | BV25: 0 | BW25: =L25-80 -> 0 | BX25: =IF($D25=0,0,BQ25/$D25) -> 8 | BY25: =IF($D25=0,0,BR25/$D25) -> 0 | BZ25: =IF($D25=0,0,BS25/$D25) -> 0 | CA25: =IF($D25=0,0,BT25/$D25) -> 0 | CB25: =IF($D25=0,0,BU25/$D25) -> 0 | CC25: =IF($D25=0,0,BV25/$D25) -> 0
A26: 4.5 | B26: Fabricación de tableros eléctricos y de control | C26: R5 Jose Luis | D26: 6 | E26: 4.4 | F26: =MAX(G25)+Q26 -> 26 | G26: =F26+D26 -> 32 | H26: =I26-D26 -> 27 | I26: =MIN(H34) -> 33 | J26: =H26-F26 -> 1 | K26: =IF(J26=0,"Sí","") | L26: =SUM(BQ26:BV26) -> 120 | M26: =SUMIFS(Cotizaciones!$J$5:$J$70,Cotizaciones!$C$5:$C$70,A26) -> 225000000 | N26: =(L26*Supuestos!$B$47+M26*(1+Supuestos!$B$50))*(1+Supuestos!$B$51)/(1-Supuestos!$B$52) -> 2.8753543e+08 | O26: =$C$3+F26*7 -> 46580 | P26: =$C$3+G26*7-IF(D26>0,1,0) -> 46621 | Q26: 0 | R26: =IF(AND(R$5>$F26,R$5<=$G26),IF($K26="Sí",2,1),IF(AND($D26=0,R$5=$G26),3,"")) | S26: =IF(AND(S$5>$F26,S$5<=$G26),IF($K26="Sí",2,1),IF(AND($D26=0,S$5=$G26),3,"")) | T26: =IF(AND(T$5>$F26,T$5<=$G26),IF($K26="Sí",2,1),IF(AND($D26=0,T$5=$G26),3,"")) | U26: =IF(AND(U$5>$F26,U$5<=$G26),IF($K26="Sí",2,1),IF(AND($D26=0,U$5=$G26),3,"")) | V26: =IF(AND(V$5>$F26,V$5<=$G26),IF($K26="Sí",2,1),IF(AND($D26=0,V$5=$G26),3,"")) | W26: =IF(AND(W$5>$F26,W$5<=$G26),IF($K26="Sí",2,1),IF(AND($D26=0,W$5=$G26),3,"")) | X26: =IF(AND(X$5>$F26,X$5<=$G26),IF($K26="Sí",2,1),IF(AND($D26=0,X$5=$G26),3,"")) | Y26: =IF(AND(Y$5>$F26,Y$5<=$G26),IF($K26="Sí",2,1),IF(AND($D26=0,Y$5=$G26),3,"")) | ... BO26: =IF(AND(BO$5>$F26,BO$5<=$G26),IF($K26="Sí",2,1),IF(AND($D26=0,BO$5=$G26),3,"")) | BQ26: 0 | BR26: 0 | BS26: 33 | BT26: 0 | BU26: 87 | BV26: 0 | BW26: =L26-120 -> 0 | BX26: =IF($D26=0,0,BQ26/$D26) -> 0 | BY26: =IF($D26=0,0,BR26/$D26) -> 0 | BZ26: =IF($D26=0,0,BS26/$D26) -> 5.5 | CA26: =IF($D26=0,0,BT26/$D26) -> 0 | CB26: =IF($D26=0,0,BU26/$D26) -> 14.5 | CC26: =IF($D26=0,0,BV26/$D26) -> 0
A27: 4.6 | B27: Compra de licencias de software (Ignition y Sepasoft) | C27: R6 Ian | D27: 1 | E27: 3.2 | F27: =MAX(G14)+Q27 -> 15 | G27: =F27+D27 -> 16 | H27: =I27-D27 -> 26 | I27: =MIN(H29) -> 27 | J27: =H27-F27 -> 11 | K27: =IF(J27=0,"Sí","") | L27: =SUM(BQ27:BV27) -> 40 | M27: =SUMIFS(Cotizaciones!$J$5:$J$70,Cotizaciones!$C$5:$C$70,A27) -> 5.4944711e+08 | N27: =(L27*Supuestos!$B$47+M27*(1+Supuestos!$B$50))*(1+Supuestos!$B$51)/(1-Supuestos!$B$52) -> 6.6105187e+08 | O27: =$C$3+F27*7 -> 46503 | P27: =$C$3+G27*7-IF(D27>0,1,0) -> 46509 | Q27: 1 | R27: =IF(AND(R$5>$F27,R$5<=$G27),IF($K27="Sí",2,1),IF(AND($D27=0,R$5=$G27),3,"")) | S27: =IF(AND(S$5>$F27,S$5<=$G27),IF($K27="Sí",2,1),IF(AND($D27=0,S$5=$G27),3,"")) | T27: =IF(AND(T$5>$F27,T$5<=$G27),IF($K27="Sí",2,1),IF(AND($D27=0,T$5=$G27),3,"")) | U27: =IF(AND(U$5>$F27,U$5<=$G27),IF($K27="Sí",2,1),IF(AND($D27=0,U$5=$G27),3,"")) | V27: =IF(AND(V$5>$F27,V$5<=$G27),IF($K27="Sí",2,1),IF(AND($D27=0,V$5=$G27),3,"")) | W27: =IF(AND(W$5>$F27,W$5<=$G27),IF($K27="Sí",2,1),IF(AND($D27=0,W$5=$G27),3,"")) | X27: =IF(AND(X$5>$F27,X$5<=$G27),IF($K27="Sí",2,1),IF(AND($D27=0,X$5=$G27),3,"")) | Y27: =IF(AND(Y$5>$F27,Y$5<=$G27),IF($K27="Sí",2,1),IF(AND($D27=0,Y$5=$G27),3,"")) | ... BO27: =IF(AND(BO$5>$F27,BO$5<=$G27),IF($K27="Sí",2,1),IF(AND($D27=0,BO$5=$G27),3,"")) | BQ27: 0 | BR27: 29 | BS27: 0 | BT27: 0 | BU27: 0 | BV27: 11 | BW27: =L27-40 -> 0 | BX27: =IF($D27=0,0,BQ27/$D27) -> 0 | BY27: =IF($D27=0,0,BR27/$D27) -> 29 | BZ27: =IF($D27=0,0,BS27/$D27) -> 0 | CA27: =IF($D27=0,0,BT27/$D27) -> 0 | CB27: =IF($D27=0,0,BU27/$D27) -> 0 | CC27: =IF($D27=0,0,BV27/$D27) -> 11
A28: 5.1 | B28: Gemelo digital de la línea de yogures | C28: R6 Ian | D28: 12 | E28: 3.2 | F28: =MAX(G14)+Q28 -> 15 | G28: =F28+D28 -> 27 | H28: =I28-D28 -> 15 | I28: =MIN(H29) -> 27 | J28: =H28-F28 -> 0 | K28: =IF(J28=0,"Sí","") -> Sí | L28: =SUM(BQ28:BV28) -> 800 | M28: =SUMIFS(Cotizaciones!$J$5:$J$70,Cotizaciones!$C$5:$C$70,A28) -> 0 | N28: =(L28*Supuestos!$B$47+M28*(1+Supuestos!$B$50))*(1+Supuestos!$B$51)/(1-Supuestos!$B$52) -> 1.2995951e+08 | O28: =$C$3+F28*7 -> 46503 | P28: =$C$3+G28*7-IF(D28>0,1,0) -> 46586 | Q28: 1 | R28: =IF(AND(R$5>$F28,R$5<=$G28),IF($K28="Sí",2,1),IF(AND($D28=0,R$5=$G28),3,"")) | S28: =IF(AND(S$5>$F28,S$5<=$G28),IF($K28="Sí",2,1),IF(AND($D28=0,S$5=$G28),3,"")) | T28: =IF(AND(T$5>$F28,T$5<=$G28),IF($K28="Sí",2,1),IF(AND($D28=0,T$5=$G28),3,"")) | U28: =IF(AND(U$5>$F28,U$5<=$G28),IF($K28="Sí",2,1),IF(AND($D28=0,U$5=$G28),3,"")) | V28: =IF(AND(V$5>$F28,V$5<=$G28),IF($K28="Sí",2,1),IF(AND($D28=0,V$5=$G28),3,"")) | W28: =IF(AND(W$5>$F28,W$5<=$G28),IF($K28="Sí",2,1),IF(AND($D28=0,W$5=$G28),3,"")) | X28: =IF(AND(X$5>$F28,X$5<=$G28),IF($K28="Sí",2,1),IF(AND($D28=0,X$5=$G28),3,"")) | Y28: =IF(AND(Y$5>$F28,Y$5<=$G28),IF($K28="Sí",2,1),IF(AND($D28=0,Y$5=$G28),3,"")) | ... BO28: =IF(AND(BO$5>$F28,BO$5<=$G28),IF($K28="Sí",2,1),IF(AND($D28=0,BO$5=$G28),3,"")) | BQ28: 0 | BR28: 32 | BS28: 433 | BT28: 0 | BU28: 0 | BV28: 335 | BW28: =L28-800 -> 0 | BX28: =IF($D28=0,0,BQ28/$D28) -> 0 | BY28: =IF($D28=0,0,BR28/$D28) -> 2.6666667 | BZ28: =IF($D28=0,0,BS28/$D28) -> 36.083333 | CA28: =IF($D28=0,0,BT28/$D28) -> 0 | CB28: =IF($D28=0,0,BU28/$D28) -> 0 | CC28: =IF($D28=0,0,BV28/$D28) -> 27.916667
A29: 5.2 | B29: FAT virtual con Logix Emulate, Ignition y el gemelo | C29: R4 Juan | D29: 6 | E29: 3.6, 3.7, 5.1, 4.6 | F29: =MAX(G18,G19,G28,G27)+Q29 -> 27 | G29: =F29+D29 -> 33 | H29: =I29-D29 -> 27 | I29: =MIN(H31) -> 33 | J29: =H29-F29 -> 0 | K29: =IF(J29=0,"Sí","") -> Sí | L29: =SUM(BQ29:BV29) -> 640 | M29: =SUMIFS(Cotizaciones!$J$5:$J$70,Cotizaciones!$C$5:$C$70,A29) -> 0 | N29: =(L29*Supuestos!$B$47+M29*(1+Supuestos!$B$50))*(1+Supuestos!$B$51)/(1-Supuestos!$B$52) -> 1.0396761e+08 | O29: =$C$3+F29*7 -> 46587 | P29: =$C$3+G29*7-IF(D29>0,1,0) -> 46628 | Q29: 0 | R29: =IF(AND(R$5>$F29,R$5<=$G29),IF($K29="Sí",2,1),IF(AND($D29=0,R$5=$G29),3,"")) | S29: =IF(AND(S$5>$F29,S$5<=$G29),IF($K29="Sí",2,1),IF(AND($D29=0,S$5=$G29),3,"")) | T29: =IF(AND(T$5>$F29,T$5<=$G29),IF($K29="Sí",2,1),IF(AND($D29=0,T$5=$G29),3,"")) | U29: =IF(AND(U$5>$F29,U$5<=$G29),IF($K29="Sí",2,1),IF(AND($D29=0,U$5=$G29),3,"")) | V29: =IF(AND(V$5>$F29,V$5<=$G29),IF($K29="Sí",2,1),IF(AND($D29=0,V$5=$G29),3,"")) | W29: =IF(AND(W$5>$F29,W$5<=$G29),IF($K29="Sí",2,1),IF(AND($D29=0,W$5=$G29),3,"")) | X29: =IF(AND(X$5>$F29,X$5<=$G29),IF($K29="Sí",2,1),IF(AND($D29=0,X$5=$G29),3,"")) | Y29: =IF(AND(Y$5>$F29,Y$5<=$G29),IF($K29="Sí",2,1),IF(AND($D29=0,Y$5=$G29),3,"")) | ... BO29: =IF(AND(BO$5>$F29,BO$5<=$G29),IF($K29="Sí",2,1),IF(AND($D29=0,BO$5=$G29),3,"")) | BQ29: 103 | BR29: 90 | BS29: 229 | BT29: 102 | BU29: 0 | BV29: 116 | BW29: =L29-640 -> 0 | BX29: =IF($D29=0,0,BQ29/$D29) -> 17.166667 | BY29: =IF($D29=0,0,BR29/$D29) -> 15 | BZ29: =IF($D29=0,0,BS29/$D29) -> 38.166667 | CA29: =IF($D29=0,0,BT29/$D29) -> 17 | CB29: =IF($D29=0,0,BU29/$D29) -> 0 | CC29: =IF($D29=0,0,BV29/$D29) -> 19.333333
A30: 5.3 | B30: FAT de la celda robotizada en el taller del integrador (Bogotá) | C30: R5 Jose Luis | D30: 2 | E30: 4.3, 3.9 | F30: =MAX(G24,G21)+Q30 -> 31 | G30: =F30+D30 -> 33 | H30: =I30-D30 -> 31 | I30: =MIN(H31,H35) -> 33 | J30: =H30-F30 -> 0 | K30: =IF(J30=0,"Sí","") -> Sí | L30: =SUM(BQ30:BV30) -> 160 | M30: =SUMIFS(Cotizaciones!$J$5:$J$70,Cotizaciones!$C$5:$C$70,A30) -> 0 | N30: =(L30*Supuestos!$B$47+M30*(1+Supuestos!$B$50))*(1+Supuestos!$B$51)/(1-Supuestos!$B$52) -> 25991903 | O30: =$C$3+F30*7 -> 46615 | P30: =$C$3+G30*7-IF(D30>0,1,0) -> 46628 | Q30: 0 | R30: =IF(AND(R$5>$F30,R$5<=$G30),IF($K30="Sí",2,1),IF(AND($D30=0,R$5=$G30),3,"")) | S30: =IF(AND(S$5>$F30,S$5<=$G30),IF($K30="Sí",2,1),IF(AND($D30=0,S$5=$G30),3,"")) | T30: =IF(AND(T$5>$F30,T$5<=$G30),IF($K30="Sí",2,1),IF(AND($D30=0,T$5=$G30),3,"")) | U30: =IF(AND(U$5>$F30,U$5<=$G30),IF($K30="Sí",2,1),IF(AND($D30=0,U$5=$G30),3,"")) | V30: =IF(AND(V$5>$F30,V$5<=$G30),IF($K30="Sí",2,1),IF(AND($D30=0,V$5=$G30),3,"")) | W30: =IF(AND(W$5>$F30,W$5<=$G30),IF($K30="Sí",2,1),IF(AND($D30=0,W$5=$G30),3,"")) | X30: =IF(AND(X$5>$F30,X$5<=$G30),IF($K30="Sí",2,1),IF(AND($D30=0,X$5=$G30),3,"")) | Y30: =IF(AND(Y$5>$F30,Y$5<=$G30),IF($K30="Sí",2,1),IF(AND($D30=0,Y$5=$G30),3,"")) | ... BO30: =IF(AND(BO$5>$F30,BO$5<=$G30),IF($K30="Sí",2,1),IF(AND($D30=0,BO$5=$G30),3,"")) | BQ30: 0 | BR30: 0 | BS30: 0 | BT30: 53 | BU30: 58 | BV30: 49 | BW30: =L30-160 -> 0 | BX30: =IF($D30=0,0,BQ30/$D30) -> 0 | BY30: =IF($D30=0,0,BR30/$D30) -> 0 | BZ30: =IF($D30=0,0,BS30/$D30) -> 0 | CA30: =IF($D30=0,0,BT30/$D30) -> 26.5 | CB30: =IF($D30=0,0,BU30/$D30) -> 29 | CC30: =IF($D30=0,0,BV30/$D30) -> 24.5
A31: 5.4 | B31: Hito: aprobación de las pruebas FAT | C31: R1 Duvan | D31: 0 | E31: 5.2, 5.3, 3.8 | F31: =MAX(G29,G30,G20)+Q31 -> 33 | G31: =F31+D31 -> 33 | H31: =I31-D31 -> 33 | I31: =MIN(H33,H34) -> 33 | J31: =H31-F31 -> 0 | K31: =IF(J31=0,"Sí","") -> Sí | L31: =SUM(BQ31:BV31) -> 0 | M31: =SUMIFS(Cotizaciones!$J$5:$J$70,Cotizaciones!$C$5:$C$70,A31) -> 0 | N31: =(L31*Supuestos!$B$47+M31*(1+Supuestos!$B$50))*(1+Supuestos!$B$51)/(1-Supuestos!$B$52) -> 0 | O31: =$C$3+F31*7 -> 46629 | P31: =$C$3+G31*7-IF(D31>0,1,0) -> 46629 | Q31: 0 | R31: =IF(AND(R$5>$F31,R$5<=$G31),IF($K31="Sí",2,1),IF(AND($D31=0,R$5=$G31),3,"")) | S31: =IF(AND(S$5>$F31,S$5<=$G31),IF($K31="Sí",2,1),IF(AND($D31=0,S$5=$G31),3,"")) | T31: =IF(AND(T$5>$F31,T$5<=$G31),IF($K31="Sí",2,1),IF(AND($D31=0,T$5=$G31),3,"")) | U31: =IF(AND(U$5>$F31,U$5<=$G31),IF($K31="Sí",2,1),IF(AND($D31=0,U$5=$G31),3,"")) | V31: =IF(AND(V$5>$F31,V$5<=$G31),IF($K31="Sí",2,1),IF(AND($D31=0,V$5=$G31),3,"")) | W31: =IF(AND(W$5>$F31,W$5<=$G31),IF($K31="Sí",2,1),IF(AND($D31=0,W$5=$G31),3,"")) | X31: =IF(AND(X$5>$F31,X$5<=$G31),IF($K31="Sí",2,1),IF(AND($D31=0,X$5=$G31),3,"")) | Y31: =IF(AND(Y$5>$F31,Y$5<=$G31),IF($K31="Sí",2,1),IF(AND($D31=0,Y$5=$G31),3,"")) | ... BO31: =IF(AND(BO$5>$F31,BO$5<=$G31),IF($K31="Sí",2,1),IF(AND($D31=0,BO$5=$G31),3,"")) | BQ31: 0 | BR31: 0 | BS31: 0 | BT31: 0 | BU31: 0 | BV31: 0 | BW31: =L31-0 -> 0 | BX31: =IF($D31=0,0,BQ31/$D31) -> 0 | BY31: =IF($D31=0,0,BR31/$D31) -> 0 | BZ31: =IF($D31=0,0,BS31/$D31) -> 0 | CA31: =IF($D31=0,0,BT31/$D31) -> 0 | CB31: =IF($D31=0,0,BU31/$D31) -> 0 | CC31: =IF($D31=0,0,BV31/$D31) -> 0
A32: 6.1 | B32: Obras civiles menores y preparación del sitio | C32: R3 David Felipe | D32: 6 | E32: 3.4 | F32: =MAX(G16)+Q32 -> 25 | G32: =F32+D32 -> 31 | H32: =I32-D32 -> 27 | I32: =MIN(H33,H34,H35) -> 33 | J32: =H32-F32 -> 2 | K32: =IF(J32=0,"Sí","") | L32: =SUM(BQ32:BV32) -> 160 | M32: =SUMIFS(Cotizaciones!$J$5:$J$70,Cotizaciones!$C$5:$C$70,A32) -> 120000000 | N32: =(L32*Supuestos!$B$47+M32*(1+Supuestos!$B$50))*(1+Supuestos!$B$51)/(1-Supuestos!$B$52) -> 1.6894737e+08 | O32: =$C$3+F32*7 -> 46573 | P32: =$C$3+G32*7-IF(D32>0,1,0) -> 46614 | Q32: 14 | R32: =IF(AND(R$5>$F32,R$5<=$G32),IF($K32="Sí",2,1),IF(AND($D32=0,R$5=$G32),3,"")) | S32: =IF(AND(S$5>$F32,S$5<=$G32),IF($K32="Sí",2,1),IF(AND($D32=0,S$5=$G32),3,"")) | T32: =IF(AND(T$5>$F32,T$5<=$G32),IF($K32="Sí",2,1),IF(AND($D32=0,T$5=$G32),3,"")) | U32: =IF(AND(U$5>$F32,U$5<=$G32),IF($K32="Sí",2,1),IF(AND($D32=0,U$5=$G32),3,"")) | V32: =IF(AND(V$5>$F32,V$5<=$G32),IF($K32="Sí",2,1),IF(AND($D32=0,V$5=$G32),3,"")) | W32: =IF(AND(W$5>$F32,W$5<=$G32),IF($K32="Sí",2,1),IF(AND($D32=0,W$5=$G32),3,"")) | X32: =IF(AND(X$5>$F32,X$5<=$G32),IF($K32="Sí",2,1),IF(AND($D32=0,X$5=$G32),3,"")) | Y32: =IF(AND(Y$5>$F32,Y$5<=$G32),IF($K32="Sí",2,1),IF(AND($D32=0,Y$5=$G32),3,"")) | ... BO32: =IF(AND(BO$5>$F32,BO$5<=$G32),IF($K32="Sí",2,1),IF(AND($D32=0,BO$5=$G32),3,"")) | BQ32: 0 | BR32: 0 | BS32: 0 | BT32: 160 | BU32: 0 | BV32: 0 | BW32: =L32-160 -> 0 | BX32: =IF($D32=0,0,BQ32/$D32) -> 0 | BY32: =IF($D32=0,0,BR32/$D32) -> 0 | BZ32: =IF($D32=0,0,BS32/$D32) -> 0 | CA32: =IF($D32=0,0,BT32/$D32) -> 26.666667 | CB32: =IF($D32=0,0,BU32/$D32) -> 0 | CC32: =IF($D32=0,0,BV32/$D32) -> 0
A33: 6.2 | B33: Montaje mecánico, válvulas e instrumentación (parada) | C33: R3 David Felipe | D33: 2 | E33: 4.2, 5.4, 6.1 | F33: =MAX(G23,G31,G32)+Q33 -> 33 | G33: =F33+D33 -> 35 | H33: =I33-D33 -> 33 | I33: =MIN(H37) -> 35 | J33: =H33-F33 -> 0 | K33: =IF(J33=0,"Sí","") -> Sí | L33: =SUM(BQ33:BV33) -> 180 | M33: =SUMIFS(Cotizaciones!$J$5:$J$70,Cotizaciones!$C$5:$C$70,A33) -> 392000000 | N33: =(L33*Supuestos!$B$47+M33*(1+Supuestos!$B$50))*(1+Supuestos!$B$51)/(1-Supuestos!$B$52) -> 4.9622874e+08 | O33: =$C$3+F33*7 -> 46629 | P33: =$C$3+G33*7-IF(D33>0,1,0) -> 46642 | Q33: 0 | R33: =IF(AND(R$5>$F33,R$5<=$G33),IF($K33="Sí",2,1),IF(AND($D33=0,R$5=$G33),3,"")) | S33: =IF(AND(S$5>$F33,S$5<=$G33),IF($K33="Sí",2,1),IF(AND($D33=0,S$5=$G33),3,"")) | T33: =IF(AND(T$5>$F33,T$5<=$G33),IF($K33="Sí",2,1),IF(AND($D33=0,T$5=$G33),3,"")) | U33: =IF(AND(U$5>$F33,U$5<=$G33),IF($K33="Sí",2,1),IF(AND($D33=0,U$5=$G33),3,"")) | V33: =IF(AND(V$5>$F33,V$5<=$G33),IF($K33="Sí",2,1),IF(AND($D33=0,V$5=$G33),3,"")) | W33: =IF(AND(W$5>$F33,W$5<=$G33),IF($K33="Sí",2,1),IF(AND($D33=0,W$5=$G33),3,"")) | X33: =IF(AND(X$5>$F33,X$5<=$G33),IF($K33="Sí",2,1),IF(AND($D33=0,X$5=$G33),3,"")) | Y33: =IF(AND(Y$5>$F33,Y$5<=$G33),IF($K33="Sí",2,1),IF(AND($D33=0,Y$5=$G33),3,"")) | ... BO33: =IF(AND(BO$5>$F33,BO$5<=$G33),IF($K33="Sí",2,1),IF(AND($D33=0,BO$5=$G33),3,"")) | BQ33: 0 | BR33: 0 | BS33: 93 | BT33: 87 | BU33: 0 | BV33: 0 | BW33: =L33-180 -> 0 | BX33: =IF($D33=0,0,BQ33/$D33) -> 0 | BY33: =IF($D33=0,0,BR33/$D33) -> 0 | BZ33: =IF($D33=0,0,BS33/$D33) -> 46.5 | CA33: =IF($D33=0,0,BT33/$D33) -> 43.5 | CB33: =IF($D33=0,0,BU33/$D33) -> 0 | CC33: =IF($D33=0,0,BV33/$D33) -> 0
A34: 6.3 | B34: Montaje eléctrico y tableros (parada) | C34: R5 Jose Luis | D34: 2 | E34: 4.5, 5.4, 6.1 | F34: =MAX(G26,G31,G32)+Q34 -> 33 | G34: =F34+D34 -> 35 | H34: =I34-D34 -> 33 | I34: =MIN(H37) -> 35 | J34: =H34-F34 -> 0 | K34: =IF(J34=0,"Sí","") -> Sí | L34: =SUM(BQ34:BV34) -> 180 | M34: =SUMIFS(Cotizaciones!$J$5:$J$70,Cotizaciones!$C$5:$C$70,A34) -> 450000000 | N34: =(L34*Supuestos!$B$47+M34*(1+Supuestos!$B$50))*(1+Supuestos!$B$51)/(1-Supuestos!$B$52) -> 5.6532389e+08 | O34: =$C$3+F34*7 -> 46629 | P34: =$C$3+G34*7-IF(D34>0,1,0) -> 46642 | Q34: 0 | R34: =IF(AND(R$5>$F34,R$5<=$G34),IF($K34="Sí",2,1),IF(AND($D34=0,R$5=$G34),3,"")) | S34: =IF(AND(S$5>$F34,S$5<=$G34),IF($K34="Sí",2,1),IF(AND($D34=0,S$5=$G34),3,"")) | T34: =IF(AND(T$5>$F34,T$5<=$G34),IF($K34="Sí",2,1),IF(AND($D34=0,T$5=$G34),3,"")) | U34: =IF(AND(U$5>$F34,U$5<=$G34),IF($K34="Sí",2,1),IF(AND($D34=0,U$5=$G34),3,"")) | V34: =IF(AND(V$5>$F34,V$5<=$G34),IF($K34="Sí",2,1),IF(AND($D34=0,V$5=$G34),3,"")) | W34: =IF(AND(W$5>$F34,W$5<=$G34),IF($K34="Sí",2,1),IF(AND($D34=0,W$5=$G34),3,"")) | X34: =IF(AND(X$5>$F34,X$5<=$G34),IF($K34="Sí",2,1),IF(AND($D34=0,X$5=$G34),3,"")) | Y34: =IF(AND(Y$5>$F34,Y$5<=$G34),IF($K34="Sí",2,1),IF(AND($D34=0,Y$5=$G34),3,"")) | ... BO34: =IF(AND(BO$5>$F34,BO$5<=$G34),IF($K34="Sí",2,1),IF(AND($D34=0,BO$5=$G34),3,"")) | BQ34: 0 | BR34: 87 | BS34: 0 | BT34: 0 | BU34: 0 | BV34: 93 | BW34: =L34-180 -> 0 | BX34: =IF($D34=0,0,BQ34/$D34) -> 0 | BY34: =IF($D34=0,0,BR34/$D34) -> 43.5 | BZ34: =IF($D34=0,0,BS34/$D34) -> 0 | CA34: =IF($D34=0,0,BT34/$D34) -> 0 | CB34: =IF($D34=0,0,BU34/$D34) -> 0 | CC34: =IF($D34=0,0,BV34/$D34) -> 46.5
A35: 6.4 | B35: Instalación de la celda robotizada | C35: R5 Jose Luis | D35: 2 | E35: 5.3, 6.1 | F35: =MAX(G30,G32)+Q35 -> 33 | G35: =F35+D35 -> 35 | H35: =I35-D35 -> 33 | I35: =MIN(H37) -> 35 | J35: =H35-F35 -> 0 | K35: =IF(J35=0,"Sí","") -> Sí | L35: =SUM(BQ35:BV35) -> 80 | M35: =SUMIFS(Cotizaciones!$J$5:$J$70,Cotizaciones!$C$5:$C$70,A35) -> 18000000 | N35: =(L35*Supuestos!$B$47+M35*(1+Supuestos!$B$50))*(1+Supuestos!$B$51)/(1-Supuestos!$B$52) -> 34439271 | O35: =$C$3+F35*7 -> 46629 | P35: =$C$3+G35*7-IF(D35>0,1,0) -> 46642 | Q35: 0 | R35: =IF(AND(R$5>$F35,R$5<=$G35),IF($K35="Sí",2,1),IF(AND($D35=0,R$5=$G35),3,"")) | S35: =IF(AND(S$5>$F35,S$5<=$G35),IF($K35="Sí",2,1),IF(AND($D35=0,S$5=$G35),3,"")) | T35: =IF(AND(T$5>$F35,T$5<=$G35),IF($K35="Sí",2,1),IF(AND($D35=0,T$5=$G35),3,"")) | U35: =IF(AND(U$5>$F35,U$5<=$G35),IF($K35="Sí",2,1),IF(AND($D35=0,U$5=$G35),3,"")) | V35: =IF(AND(V$5>$F35,V$5<=$G35),IF($K35="Sí",2,1),IF(AND($D35=0,V$5=$G35),3,"")) | W35: =IF(AND(W$5>$F35,W$5<=$G35),IF($K35="Sí",2,1),IF(AND($D35=0,W$5=$G35),3,"")) | X35: =IF(AND(X$5>$F35,X$5<=$G35),IF($K35="Sí",2,1),IF(AND($D35=0,X$5=$G35),3,"")) | Y35: =IF(AND(Y$5>$F35,Y$5<=$G35),IF($K35="Sí",2,1),IF(AND($D35=0,Y$5=$G35),3,"")) | ... BO35: =IF(AND(BO$5>$F35,BO$5<=$G35),IF($K35="Sí",2,1),IF(AND($D35=0,BO$5=$G35),3,"")) | BQ35: 0 | BR35: 0 | BS35: 0 | BT35: 0 | BU35: 80 | BV35: 0 | BW35: =L35-80 -> 0 | BX35: =IF($D35=0,0,BQ35/$D35) -> 0 | BY35: =IF($D35=0,0,BR35/$D35) -> 0 | BZ35: =IF($D35=0,0,BS35/$D35) -> 0 | CA35: =IF($D35=0,0,BT35/$D35) -> 0 | CB35: =IF($D35=0,0,BU35/$D35) -> 40 | CC35: =IF($D35=0,0,BV35/$D35) -> 0
A36: 6.5 | B36: Instalación de servidores, red y cableado | C36: R6 Ian | D36: 4 | E36: 4.4 | F36: =MAX(G25)+Q36 -> 26 | G36: =F36+D36 -> 30 | H36: =I36-D36 -> 31 | I36: =MIN(H37) -> 35 | J36: =H36-F36 -> 5 | K36: =IF(J36=0,"Sí","") | L36: =SUM(BQ36:BV36) -> 160 | M36: =SUMIFS(Cotizaciones!$J$5:$J$70,Cotizaciones!$C$5:$C$70,A36) -> 60000000 | N36: =(L36*Supuestos!$B$47+M36*(1+Supuestos!$B$50))*(1+Supuestos!$B$51)/(1-Supuestos!$B$52) -> 97469636 | O36: =$C$3+F36*7 -> 46580 | P36: =$C$3+G36*7-IF(D36>0,1,0) -> 46607 | Q36: 0 | R36: =IF(AND(R$5>$F36,R$5<=$G36),IF($K36="Sí",2,1),IF(AND($D36=0,R$5=$G36),3,"")) | S36: =IF(AND(S$5>$F36,S$5<=$G36),IF($K36="Sí",2,1),IF(AND($D36=0,S$5=$G36),3,"")) | T36: =IF(AND(T$5>$F36,T$5<=$G36),IF($K36="Sí",2,1),IF(AND($D36=0,T$5=$G36),3,"")) | U36: =IF(AND(U$5>$F36,U$5<=$G36),IF($K36="Sí",2,1),IF(AND($D36=0,U$5=$G36),3,"")) | V36: =IF(AND(V$5>$F36,V$5<=$G36),IF($K36="Sí",2,1),IF(AND($D36=0,V$5=$G36),3,"")) | W36: =IF(AND(W$5>$F36,W$5<=$G36),IF($K36="Sí",2,1),IF(AND($D36=0,W$5=$G36),3,"")) | X36: =IF(AND(X$5>$F36,X$5<=$G36),IF($K36="Sí",2,1),IF(AND($D36=0,X$5=$G36),3,"")) | Y36: =IF(AND(Y$5>$F36,Y$5<=$G36),IF($K36="Sí",2,1),IF(AND($D36=0,Y$5=$G36),3,"")) | ... BO36: =IF(AND(BO$5>$F36,BO$5<=$G36),IF($K36="Sí",2,1),IF(AND($D36=0,BO$5=$G36),3,"")) | BQ36: 0 | BR36: 0 | BS36: 0 | BT36: 0 | BU36: 98 | BV36: 62 | BW36: =L36-160 -> 0 | BX36: =IF($D36=0,0,BQ36/$D36) -> 0 | BY36: =IF($D36=0,0,BR36/$D36) -> 0 | BZ36: =IF($D36=0,0,BS36/$D36) -> 0 | CA36: =IF($D36=0,0,BT36/$D36) -> 0 | CB36: =IF($D36=0,0,BU36/$D36) -> 24.5 | CC36: =IF($D36=0,0,BV36/$D36) -> 15.5
A37: 7.1 | B37: Pruebas en sitio (SAT): lazos, enclavamientos y secuencias | C37: R4 Juan | D37: 2 | E37: 6.2, 6.3, 6.4, 6.5 | F37: =MAX(G33,G34,G35,G36)+Q37 -> 35 | G37: =F37+D37 -> 37 | H37: =I37-D37 -> 35 | I37: =MIN(H38,H39,H41) -> 37 | J37: =H37-F37 -> 0 | K37: =IF(J37=0,"Sí","") -> Sí | L37: =SUM(BQ37:BV37) -> 440 | M37: =SUMIFS(Cotizaciones!$J$5:$J$70,Cotizaciones!$C$5:$C$70,A37) -> 0 | N37: =(L37*Supuestos!$B$47+M37*(1+Supuestos!$B$50))*(1+Supuestos!$B$51)/(1-Supuestos!$B$52) -> 71477733 | O37: =$C$3+F37*7 -> 46643 | P37: =$C$3+G37*7-IF(D37>0,1,0) -> 46656 | Q37: 0 | R37: =IF(AND(R$5>$F37,R$5<=$G37),IF($K37="Sí",2,1),IF(AND($D37=0,R$5=$G37),3,"")) | S37: =IF(AND(S$5>$F37,S$5<=$G37),IF($K37="Sí",2,1),IF(AND($D37=0,S$5=$G37),3,"")) | T37: =IF(AND(T$5>$F37,T$5<=$G37),IF($K37="Sí",2,1),IF(AND($D37=0,T$5=$G37),3,"")) | U37: =IF(AND(U$5>$F37,U$5<=$G37),IF($K37="Sí",2,1),IF(AND($D37=0,U$5=$G37),3,"")) | V37: =IF(AND(V$5>$F37,V$5<=$G37),IF($K37="Sí",2,1),IF(AND($D37=0,V$5=$G37),3,"")) | W37: =IF(AND(W$5>$F37,W$5<=$G37),IF($K37="Sí",2,1),IF(AND($D37=0,W$5=$G37),3,"")) | X37: =IF(AND(X$5>$F37,X$5<=$G37),IF($K37="Sí",2,1),IF(AND($D37=0,X$5=$G37),3,"")) | Y37: =IF(AND(Y$5>$F37,Y$5<=$G37),IF($K37="Sí",2,1),IF(AND($D37=0,Y$5=$G37),3,"")) | ... BO37: =IF(AND(BO$5>$F37,BO$5<=$G37),IF($K37="Sí",2,1),IF(AND($D37=0,BO$5=$G37),3,"")) | BQ37: 38 | BR37: 87 | BS37: 87 | BT37: 87 | BU37: 54 | BV37: 87 | BW37: =L37-440 -> 0 | BX37: =IF($D37=0,0,BQ37/$D37) -> 19 | BY37: =IF($D37=0,0,BR37/$D37) -> 43.5 | BZ37: =IF($D37=0,0,BS37/$D37) -> 43.5 | CA37: =IF($D37=0,0,BT37/$D37) -> 43.5 | CB37: =IF($D37=0,0,BU37/$D37) -> 27 | CC37: =IF($D37=0,0,BV37/$D37) -> 43.5
A38: 7.2 | B38: Lotes de prueba Y1, Y2 y Y3 | C38: R3 David Felipe | D38: 2 | E38: 7.1 | F38: =MAX(G37)+Q38 -> 37 | G38: =F38+D38 -> 39 | H38: =I38-D38 -> 37 | I38: =MIN(H40) -> 39 | J38: =H38-F38 -> 0 | K38: =IF(J38=0,"Sí","") -> Sí | L38: =SUM(BQ38:BV38) -> 280 | M38: =SUMIFS(Cotizaciones!$J$5:$J$70,Cotizaciones!$C$5:$C$70,A38) -> 0 | N38: =(L38*Supuestos!$B$47+M38*(1+Supuestos!$B$50))*(1+Supuestos!$B$51)/(1-Supuestos!$B$52) -> 45485830 | O38: =$C$3+F38*7 -> 46657 | P38: =$C$3+G38*7-IF(D38>0,1,0) -> 46670 | Q38: 0 | R38: =IF(AND(R$5>$F38,R$5<=$G38),IF($K38="Sí",2,1),IF(AND($D38=0,R$5=$G38),3,"")) | S38: =IF(AND(S$5>$F38,S$5<=$G38),IF($K38="Sí",2,1),IF(AND($D38=0,S$5=$G38),3,"")) | T38: =IF(AND(T$5>$F38,T$5<=$G38),IF($K38="Sí",2,1),IF(AND($D38=0,T$5=$G38),3,"")) | U38: =IF(AND(U$5>$F38,U$5<=$G38),IF($K38="Sí",2,1),IF(AND($D38=0,U$5=$G38),3,"")) | V38: =IF(AND(V$5>$F38,V$5<=$G38),IF($K38="Sí",2,1),IF(AND($D38=0,V$5=$G38),3,"")) | W38: =IF(AND(W$5>$F38,W$5<=$G38),IF($K38="Sí",2,1),IF(AND($D38=0,W$5=$G38),3,"")) | X38: =IF(AND(X$5>$F38,X$5<=$G38),IF($K38="Sí",2,1),IF(AND($D38=0,X$5=$G38),3,"")) | Y38: =IF(AND(Y$5>$F38,Y$5<=$G38),IF($K38="Sí",2,1),IF(AND($D38=0,Y$5=$G38),3,"")) | ... BO38: =IF(AND(BO$5>$F38,BO$5<=$G38),IF($K38="Sí",2,1),IF(AND($D38=0,BO$5=$G38),3,"")) | BQ38: 37 | BR38: 0 | BS38: 87 | BT38: 69 | BU38: 87 | BV38: 0 | BW38: =L38-280 -> 0 | BX38: =IF($D38=0,0,BQ38/$D38) -> 18.5 | BY38: =IF($D38=0,0,BR38/$D38) -> 0 | BZ38: =IF($D38=0,0,BS38/$D38) -> 43.5 | CA38: =IF($D38=0,0,BT38/$D38) -> 34.5 | CB38: =IF($D38=0,0,BU38/$D38) -> 43.5 | CC38: =IF($D38=0,0,BV38/$D38) -> 0
A39: 7.3 | B39: Integración MES–SAP en productivo | C39: R2 Paula | D39: 2 | E39: 7.1, 3.8 | F39: =MAX(G37,G20)+Q39 -> 37 | G39: =F39+D39 -> 39 | H39: =I39-D39 -> 37 | I39: =MIN(H40) -> 39 | J39: =H39-F39 -> 0 | K39: =IF(J39=0,"Sí","") -> Sí | L39: =SUM(BQ39:BV39) -> 160 | M39: =SUMIFS(Cotizaciones!$J$5:$J$70,Cotizaciones!$C$5:$C$70,A39) -> 0 | N39: =(L39*Supuestos!$B$47+M39*(1+Supuestos!$B$50))*(1+Supuestos!$B$51)/(1-Supuestos!$B$52) -> 25991903 | O39: =$C$3+F39*7 -> 46657 | P39: =$C$3+G39*7-IF(D39>0,1,0) -> 46670 | Q39: 0 | R39: =IF(AND(R$5>$F39,R$5<=$G39),IF($K39="Sí",2,1),IF(AND($D39=0,R$5=$G39),3,"")) | S39: =IF(AND(S$5>$F39,S$5<=$G39),IF($K39="Sí",2,1),IF(AND($D39=0,S$5=$G39),3,"")) | T39: =IF(AND(T$5>$F39,T$5<=$G39),IF($K39="Sí",2,1),IF(AND($D39=0,T$5=$G39),3,"")) | U39: =IF(AND(U$5>$F39,U$5<=$G39),IF($K39="Sí",2,1),IF(AND($D39=0,U$5=$G39),3,"")) | V39: =IF(AND(V$5>$F39,V$5<=$G39),IF($K39="Sí",2,1),IF(AND($D39=0,V$5=$G39),3,"")) | W39: =IF(AND(W$5>$F39,W$5<=$G39),IF($K39="Sí",2,1),IF(AND($D39=0,W$5=$G39),3,"")) | X39: =IF(AND(X$5>$F39,X$5<=$G39),IF($K39="Sí",2,1),IF(AND($D39=0,X$5=$G39),3,"")) | Y39: =IF(AND(Y$5>$F39,Y$5<=$G39),IF($K39="Sí",2,1),IF(AND($D39=0,Y$5=$G39),3,"")) | ... BO39: =IF(AND(BO$5>$F39,BO$5<=$G39),IF($K39="Sí",2,1),IF(AND($D39=0,BO$5=$G39),3,"")) | BQ39: 0 | BR39: 87 | BS39: 0 | BT39: 19 | BU39: 0 | BV39: 54 | BW39: =L39-160 -> 0 | BX39: =IF($D39=0,0,BQ39/$D39) -> 0 | BY39: =IF($D39=0,0,BR39/$D39) -> 43.5 | BZ39: =IF($D39=0,0,BS39/$D39) -> 0 | CA39: =IF($D39=0,0,BT39/$D39) -> 9.5 | CB39: =IF($D39=0,0,BU39/$D39) -> 0 | CC39: =IF($D39=0,0,BV39/$D39) -> 27
A40: 7.4 | B40: Estabilización y medición de KPIs | C40: R4 Juan | D40: 6 | E40: 7.2, 7.3 | F40: =MAX(G38,G39)+Q40 -> 39 | G40: =F40+D40 -> 45 | H40: =I40-D40 -> 39 | I40: =MIN(H42) -> 45 | J40: =H40-F40 -> 0 | K40: =IF(J40=0,"Sí","") -> Sí | L40: =SUM(BQ40:BV40) -> 320 | M40: =SUMIFS(Cotizaciones!$J$5:$J$70,Cotizaciones!$C$5:$C$70,A40) -> 0 | N40: =(L40*Supuestos!$B$47+M40*(1+Supuestos!$B$50))*(1+Supuestos!$B$51)/(1-Supuestos!$B$52) -> 51983806 | O40: =$C$3+F40*7 -> 46671 | P40: =$C$3+G40*7-IF(D40>0,1,0) -> 46712 | Q40: 0 | R40: =IF(AND(R$5>$F40,R$5<=$G40),IF($K40="Sí",2,1),IF(AND($D40=0,R$5=$G40),3,"")) | S40: =IF(AND(S$5>$F40,S$5<=$G40),IF($K40="Sí",2,1),IF(AND($D40=0,S$5=$G40),3,"")) | T40: =IF(AND(T$5>$F40,T$5<=$G40),IF($K40="Sí",2,1),IF(AND($D40=0,T$5=$G40),3,"")) | U40: =IF(AND(U$5>$F40,U$5<=$G40),IF($K40="Sí",2,1),IF(AND($D40=0,U$5=$G40),3,"")) | V40: =IF(AND(V$5>$F40,V$5<=$G40),IF($K40="Sí",2,1),IF(AND($D40=0,V$5=$G40),3,"")) | W40: =IF(AND(W$5>$F40,W$5<=$G40),IF($K40="Sí",2,1),IF(AND($D40=0,W$5=$G40),3,"")) | X40: =IF(AND(X$5>$F40,X$5<=$G40),IF($K40="Sí",2,1),IF(AND($D40=0,X$5=$G40),3,"")) | Y40: =IF(AND(Y$5>$F40,Y$5<=$G40),IF($K40="Sí",2,1),IF(AND($D40=0,Y$5=$G40),3,"")) | ... BO40: =IF(AND(BO$5>$F40,BO$5<=$G40),IF($K40="Sí",2,1),IF(AND($D40=0,BO$5=$G40),3,"")) | BQ40: 0 | BR40: 0 | BS40: 0 | BT40: 262 | BU40: 58 | BV40: 0 | BW40: =L40-320 -> 0 | BX40: =IF($D40=0,0,BQ40/$D40) -> 0 | BY40: =IF($D40=0,0,BR40/$D40) -> 0 | BZ40: =IF($D40=0,0,BS40/$D40) -> 0 | CA40: =IF($D40=0,0,BT40/$D40) -> 43.666667 | CB40: =IF($D40=0,0,BU40/$D40) -> 9.6666667 | CC40: =IF($D40=0,0,BV40/$D40) -> 0
A41: 8.1 | B41: Capacitación de operadores, mantenimiento y TI | C41: R3 David Felipe | D41: 3 | E41: 7.1 | F41: =MAX(G37)+Q41 -> 39 | G41: =F41+D41 -> 42 | H41: =I41-D41 -> 44 | I41: =MIN(H43) -> 47 | J41: =H41-F41 -> 5 | K41: =IF(J41=0,"Sí","") | L41: =SUM(BQ41:BV41) -> 240 | M41: =SUMIFS(Cotizaciones!$J$5:$J$70,Cotizaciones!$C$5:$C$70,A41) -> 0 | N41: =(L41*Supuestos!$B$47+M41*(1+Supuestos!$B$50))*(1+Supuestos!$B$51)/(1-Supuestos!$B$52) -> 38987854 | O41: =$C$3+F41*7 -> 46671 | P41: =$C$3+G41*7-IF(D41>0,1,0) -> 46691 | Q41: 2 | R41: =IF(AND(R$5>$F41,R$5<=$G41),IF($K41="Sí",2,1),IF(AND($D41=0,R$5=$G41),3,"")) | S41: =IF(AND(S$5>$F41,S$5<=$G41),IF($K41="Sí",2,1),IF(AND($D41=0,S$5=$G41),3,"")) | T41: =IF(AND(T$5>$F41,T$5<=$G41),IF($K41="Sí",2,1),IF(AND($D41=0,T$5=$G41),3,"")) | U41: =IF(AND(U$5>$F41,U$5<=$G41),IF($K41="Sí",2,1),IF(AND($D41=0,U$5=$G41),3,"")) | V41: =IF(AND(V$5>$F41,V$5<=$G41),IF($K41="Sí",2,1),IF(AND($D41=0,V$5=$G41),3,"")) | W41: =IF(AND(W$5>$F41,W$5<=$G41),IF($K41="Sí",2,1),IF(AND($D41=0,W$5=$G41),3,"")) | X41: =IF(AND(X$5>$F41,X$5<=$G41),IF($K41="Sí",2,1),IF(AND($D41=0,X$5=$G41),3,"")) | Y41: =IF(AND(Y$5>$F41,Y$5<=$G41),IF($K41="Sí",2,1),IF(AND($D41=0,Y$5=$G41),3,"")) | ... BO41: =IF(AND(BO$5>$F41,BO$5<=$G41),IF($K41="Sí",2,1),IF(AND($D41=0,BO$5=$G41),3,"")) | BQ41: 0 | BR41: 0 | BS41: 139 | BT41: 0 | BU41: 101 | BV41: 0 | BW41: =L41-240 -> 0 | BX41: =IF($D41=0,0,BQ41/$D41) -> 0 | BY41: =IF($D41=0,0,BR41/$D41) -> 0 | BZ41: =IF($D41=0,0,BS41/$D41) -> 46.333333 | CA41: =IF($D41=0,0,BT41/$D41) -> 0 | CB41: =IF($D41=0,0,BU41/$D41) -> 33.666667 | CC41: =IF($D41=0,0,BV41/$D41) -> 0
A42: 8.2 | B42: Entrega de documentación, manuales y respaldo | C42: R6 Ian | D42: 2 | E42: 7.4 | F42: =MAX(G40)+Q42 -> 45 | G42: =F42+D42 -> 47 | H42: =I42-D42 -> 45 | I42: =MIN(H43) -> 47 | J42: =H42-F42 -> 0 | K42: =IF(J42=0,"Sí","") -> Sí | L42: =SUM(BQ42:BV42) -> 160 | M42: =SUMIFS(Cotizaciones!$J$5:$J$70,Cotizaciones!$C$5:$C$70,A42) -> 0 | N42: =(L42*Supuestos!$B$47+M42*(1+Supuestos!$B$50))*(1+Supuestos!$B$51)/(1-Supuestos!$B$52) -> 25991903 | O42: =$C$3+F42*7 -> 46713 | P42: =$C$3+G42*7-IF(D42>0,1,0) -> 46726 | Q42: 0 | R42: =IF(AND(R$5>$F42,R$5<=$G42),IF($K42="Sí",2,1),IF(AND($D42=0,R$5=$G42),3,"")) | S42: =IF(AND(S$5>$F42,S$5<=$G42),IF($K42="Sí",2,1),IF(AND($D42=0,S$5=$G42),3,"")) | T42: =IF(AND(T$5>$F42,T$5<=$G42),IF($K42="Sí",2,1),IF(AND($D42=0,T$5=$G42),3,"")) | U42: =IF(AND(U$5>$F42,U$5<=$G42),IF($K42="Sí",2,1),IF(AND($D42=0,U$5=$G42),3,"")) | V42: =IF(AND(V$5>$F42,V$5<=$G42),IF($K42="Sí",2,1),IF(AND($D42=0,V$5=$G42),3,"")) | W42: =IF(AND(W$5>$F42,W$5<=$G42),IF($K42="Sí",2,1),IF(AND($D42=0,W$5=$G42),3,"")) | X42: =IF(AND(X$5>$F42,X$5<=$G42),IF($K42="Sí",2,1),IF(AND($D42=0,X$5=$G42),3,"")) | Y42: =IF(AND(Y$5>$F42,Y$5<=$G42),IF($K42="Sí",2,1),IF(AND($D42=0,Y$5=$G42),3,"")) | ... BO42: =IF(AND(BO$5>$F42,BO$5<=$G42),IF($K42="Sí",2,1),IF(AND($D42=0,BO$5=$G42),3,"")) | BQ42: 0 | BR42: 0 | BS42: 0 | BT42: 0 | BU42: 73 | BV42: 87 | BW42: =L42-160 -> 0 | BX42: =IF($D42=0,0,BQ42/$D42) -> 0 | BY42: =IF($D42=0,0,BR42/$D42) -> 0 | BZ42: =IF($D42=0,0,BS42/$D42) -> 0 | CA42: =IF($D42=0,0,BT42/$D42) -> 0 | CB42: =IF($D42=0,0,BU42/$D42) -> 36.5 | CC42: =IF($D42=0,0,BV42/$D42) -> 43.5
A43: 8.3 | B43: Acta de entrega y cierre (lecciones aprendidas) | C43: R1 Duvan | D43: 1 | E43: 8.2, 8.1 | F43: =MAX(G42,G41)+Q43 -> 47 | G43: =F43+D43 -> 48 | H43: =I43-D43 -> 47 | I43: =MAX($G$6:$G$43) -> 48 | J43: =H43-F43 -> 0 | K43: =IF(J43=0,"Sí","") -> Sí | L43: =SUM(BQ43:BV43) -> 80 | M43: =SUMIFS(Cotizaciones!$J$5:$J$70,Cotizaciones!$C$5:$C$70,A43) -> 0 | N43: =(L43*Supuestos!$B$47+M43*(1+Supuestos!$B$50))*(1+Supuestos!$B$51)/(1-Supuestos!$B$52) -> 12995951 | O43: =$C$3+F43*7 -> 46727 | P43: =$C$3+G43*7-IF(D43>0,1,0) -> 46733 | Q43: 0 | R43: =IF(AND(R$5>$F43,R$5<=$G43),IF($K43="Sí",2,1),IF(AND($D43=0,R$5=$G43),3,"")) | S43: =IF(AND(S$5>$F43,S$5<=$G43),IF($K43="Sí",2,1),IF(AND($D43=0,S$5=$G43),3,"")) | T43: =IF(AND(T$5>$F43,T$5<=$G43),IF($K43="Sí",2,1),IF(AND($D43=0,T$5=$G43),3,"")) | U43: =IF(AND(U$5>$F43,U$5<=$G43),IF($K43="Sí",2,1),IF(AND($D43=0,U$5=$G43),3,"")) | V43: =IF(AND(V$5>$F43,V$5<=$G43),IF($K43="Sí",2,1),IF(AND($D43=0,V$5=$G43),3,"")) | W43: =IF(AND(W$5>$F43,W$5<=$G43),IF($K43="Sí",2,1),IF(AND($D43=0,W$5=$G43),3,"")) | X43: =IF(AND(X$5>$F43,X$5<=$G43),IF($K43="Sí",2,1),IF(AND($D43=0,X$5=$G43),3,"")) | Y43: =IF(AND(Y$5>$F43,Y$5<=$G43),IF($K43="Sí",2,1),IF(AND($D43=0,Y$5=$G43),3,"")) | ... BO43: =IF(AND(BO$5>$F43,BO$5<=$G43),IF($K43="Sí",2,1),IF(AND($D43=0,BO$5=$G43),3,"")) | BQ43: 44 | BR43: 0 | BS43: 0 | BT43: 0 | BU43: 36 | BV43: 0 | BW43: =L43-80 -> 0 | BX43: =IF($D43=0,0,BQ43/$D43) -> 44 | BY43: =IF($D43=0,0,BR43/$D43) -> 0 | BZ43: =IF($D43=0,0,BS43/$D43) -> 0 | CA43: =IF($D43=0,0,BT43/$D43) -> 0 | CB43: =IF($D43=0,0,BU43/$D43) -> 36 | CC43: =IF($D43=0,0,BV43/$D43) -> 0
B44: Total del proyecto | G44: =MAX(G6:G43) -> 48 | L44: =SUM(L6:L43) -> 10160 | M44: =SUM(M6:M43) -> 5.7713914e+09 | N44: =SUM(N6:N43) -> 8.5259187e+09 | BQ44: =SUM(BQ6:BQ43) -> 1749 | BR44: =SUM(BR6:BR43) -> 1486 | BS44: =SUM(BS6:BS43) -> 1799 | BT44: =SUM(BT6:BT43) -> 1691 | BU44: =SUM(BU6:BU43) -> 1772 | BV44: =SUM(BV6:BV43) -> 1663 | BW44: =SUM(BW6:BW43) -> 0
B45: Duración total en meses | G45: =G44*7/30.4 -> 11.052632
B47: Leyenda del Gantt: rojo = actividad crítica · azul = actividad con holgura · amarillo = hito
A49: Histograma de recursos: horas por semana de cada integrante (según el desfase de nivelación y el reparto de horas de las columnas BQ a BV)
A50: Integrante | B50: Total (h) | C50: Máx. h/sem | D50: % de 1.920 h | R50: 1 | S50: 2 | T50: 3 | U50: 4 | V50: 5 | W50: 6 | X50: 7 | Y50: 8 | Z50: 9 | AA50: 10 | AB50: 11 | AC50: 12 | AD50: 13 | AE50: 14 | AF50: 15 | AG50: 16 | AH50: 17 | AI50: 18 | AJ50: 19 | AK50: 20 | AL50: 21 | AM50: 22 | AN50: 23 | AO50: 24 | AP50: 25 | AQ50: 26 | AR50: 27 | AS50: 28 | AT50: 29 | AU50: 30 | AV50: 31 | AW50: 32 | AX50: 33 | AY50: 34 | AZ50: 35 | BA50: 36 | BB50: 37 | BC50: 38 | BD50: 39 | BE50: 40 | BF50: 41 | BG50: 42 | BH50: 43 | BI50: 44 | BJ50: 45 | BK50: 46 | BL50: 47 | BM50: 48
A51: R1 Duvan | B51: =SUM(R51:BM51) -> 1749 | C51: =MAX(R51:BM51) -> 44 | D51: =B51/1920 -> 0.9109375 | R51: =SUMPRODUCT(($F$6:$F$43<R$50)*($G$6:$G$43>=R$50)*BX$6:BX$43) -> 44 | S51: =SUMPRODUCT(($F$6:$F$43<S$50)*($G$6:$G$43>=S$50)*BX$6:BX$43) -> 43.5 | T51: =SUMPRODUCT(($F$6:$F$43<T$50)*($G$6:$G$43>=T$50)*BX$6:BX$43) -> 43.5 | U51: =SUMPRODUCT(($F$6:$F$43<U$50)*($G$6:$G$43>=U$50)*BX$6:BX$43) -> 25 | V51: =SUMPRODUCT(($F$6:$F$43<V$50)*($G$6:$G$43>=V$50)*BX$6:BX$43) -> 25 | W51: =SUMPRODUCT(($F$6:$F$43<W$50)*($G$6:$G$43>=W$50)*BX$6:BX$43) -> 25 | X51: =SUMPRODUCT(($F$6:$F$43<X$50)*($G$6:$G$43>=X$50)*BX$6:BX$43) -> 25 | Y51: =SUMPRODUCT(($F$6:$F$43<Y$50)*($G$6:$G$43>=Y$50)*BX$6:BX$43) -> 36.2 | Z51: =SUMPRODUCT(($F$6:$F$43<Z$50)*($G$6:$G$43>=Z$50)*BX$6:BX$43) -> 36.2 | AA51: =SUMPRODUCT(($F$6:$F$43<AA$50)*($G$6:$G$43>=AA$50)*BX$6:BX$43) -> 36.2 | AB51: =SUMPRODUCT(($F$6:$F$43<AB$50)*($G$6:$G$43>=AB$50)*BX$6:BX$43) -> 36.2 | AC51: =SUMPRODUCT(($F$6:$F$43<AC$50)*($G$6:$G$43>=AC$50)*BX$6:BX$43) -> 37.6 | AD51: =SUMPRODUCT(($F$6:$F$43<AD$50)*($G$6:$G$43>=AD$50)*BX$6:BX$43) -> 43.733333 | AE51: =SUMPRODUCT(($F$6:$F$43<AE$50)*($G$6:$G$43>=AE$50)*BX$6:BX$43) -> 43.733333 | AF51: =SUMPRODUCT(($F$6:$F$43<AF$50)*($G$6:$G$43>=AF$50)*BX$6:BX$43) -> 43.733333 | AG51: =SUMPRODUCT(($F$6:$F$43<AG$50)*($G$6:$G$43>=AG$50)*BX$6:BX$43) -> 33.066667 | AH51: =SUMPRODUCT(($F$6:$F$43<AH$50)*($G$6:$G$43>=AH$50)*BX$6:BX$43) -> 41.066667 | AI51: =SUMPRODUCT(($F$6:$F$43<AI$50)*($G$6:$G$43>=AI$50)*BX$6:BX$43) -> 41.066667 | AJ51: =SUMPRODUCT(($F$6:$F$43<AJ$50)*($G$6:$G$43>=AJ$50)*BX$6:BX$43) -> 41.066667 | AK51: =SUMPRODUCT(($F$6:$F$43<AK$50)*($G$6:$G$43>=AK$50)*BX$6:BX$43) -> 41.066667 | AL51: =SUMPRODUCT(($F$6:$F$43<AL$50)*($G$6:$G$43>=AL$50)*BX$6:BX$43) -> 41.066667 | AM51: =SUMPRODUCT(($F$6:$F$43<AM$50)*($G$6:$G$43>=AM$50)*BX$6:BX$43) -> 41.066667 | AN51: =SUMPRODUCT(($F$6:$F$43<AN$50)*($G$6:$G$43>=AN$50)*BX$6:BX$43) -> 41.066667 | AO51: =SUMPRODUCT(($F$6:$F$43<AO$50)*($G$6:$G$43>=AO$50)*BX$6:BX$43) -> 41.066667 | AP51: =SUMPRODUCT(($F$6:$F$43<AP$50)*($G$6:$G$43>=AP$50)*BX$6:BX$43) -> 41.066667 | AQ51: =SUMPRODUCT(($F$6:$F$43<AQ$50)*($G$6:$G$43>=AQ$50)*BX$6:BX$43) -> 41.066667 | AR51: =SUMPRODUCT(($F$6:$F$43<AR$50)*($G$6:$G$43>=AR$50)*BX$6:BX$43) -> 33.066667 | AS51: =SUMPRODUCT(($F$6:$F$43<AS$50)*($G$6:$G$43>=AS$50)*BX$6:BX$43) -> 43.566667 | AT51: =SUMPRODUCT(($F$6:$F$43<AT$50)*($G$6:$G$43>=AT$50)*BX$6:BX$43) -> 43.566667 | AU51: =SUMPRODUCT(($F$6:$F$43<AU$50)*($G$6:$G$43>=AU$50)*BX$6:BX$43) -> 43.566667 | AV51: =SUMPRODUCT(($F$6:$F$43<AV$50)*($G$6:$G$43>=AV$50)*BX$6:BX$43) -> 43.566667 | AW51: =SUMPRODUCT(($F$6:$F$43<AW$50)*($G$6:$G$43>=AW$50)*BX$6:BX$43) -> 42.166667 | AX51: =SUMPRODUCT(($F$6:$F$43<AX$50)*($G$6:$G$43>=AX$50)*BX$6:BX$43) -> 42.166667 | AY51: =SUMPRODUCT(($F$6:$F$43<AY$50)*($G$6:$G$43>=AY$50)*BX$6:BX$43) -> 25 | AZ51: =SUMPRODUCT(($F$6:$F$43<AZ$50)*($G$6:$G$43>=AZ$50)*BX$6:BX$43) -> 25 | BA51: =SUMPRODUCT(($F$6:$F$43<BA$50)*($G$6:$G$43>=BA$50)*BX$6:BX$43) -> 44 | BB51: =SUMPRODUCT(($F$6:$F$43<BB$50)*($G$6:$G$43>=BB$50)*BX$6:BX$43) -> 44 | BC51: =SUMPRODUCT(($F$6:$F$43<BC$50)*($G$6:$G$43>=BC$50)*BX$6:BX$43) -> 43.5 | BD51: =SUMPRODUCT(($F$6:$F$43<BD$50)*($G$6:$G$43>=BD$50)*BX$6:BX$43) -> 43.5 | BE51: =SUMPRODUCT(($F$6:$F$43<BE$50)*($G$6:$G$43>=BE$50)*BX$6:BX$43) -> 25 | BF51: =SUMPRODUCT(($F$6:$F$43<BF$50)*($G$6:$G$43>=BF$50)*BX$6:BX$43) -> 25 | BG51: =SUMPRODUCT(($F$6:$F$43<BG$50)*($G$6:$G$43>=BG$50)*BX$6:BX$43) -> 25 | BH51: =SUMPRODUCT(($F$6:$F$43<BH$50)*($G$6:$G$43>=BH$50)*BX$6:BX$43) -> 25 | BI51: =SUMPRODUCT(($F$6:$F$43<BI$50)*($G$6:$G$43>=BI$50)*BX$6:BX$43) -> 25 | BJ51: =SUMPRODUCT(($F$6:$F$43<BJ$50)*($G$6:$G$43>=BJ$50)*BX$6:BX$43) -> 25 | BK51: =SUMPRODUCT(($F$6:$F$43<BK$50)*($G$6:$G$43>=BK$50)*BX$6:BX$43) -> 25 | BL51: =SUMPRODUCT(($F$6:$F$43<BL$50)*($G$6:$G$43>=BL$50)*BX$6:BX$43) -> 25 | BM51: =SUMPRODUCT(($F$6:$F$43<BM$50)*($G$6:$G$43>=BM$50)*BX$6:BX$43) -> 44
A52: R2 Paula | B52: =SUM(R52:BM52) -> 1486 | C52: =MAX(R52:BM52) -> 44 | D52: =B52/1920 -> 0.77395833 | R52: =SUMPRODUCT(($F$6:$F$43<R$50)*($G$6:$G$43>=R$50)*BY$6:BY$43) -> 0 | S52: =SUMPRODUCT(($F$6:$F$43<S$50)*($G$6:$G$43>=S$50)*BY$6:BY$43) -> 43.5 | T52: =SUMPRODUCT(($F$6:$F$43<T$50)*($G$6:$G$43>=T$50)*BY$6:BY$43) -> 43.5 | U52: =SUMPRODUCT(($F$6:$F$43<U$50)*($G$6:$G$43>=U$50)*BY$6:BY$43) -> 7 | V52: =SUMPRODUCT(($F$6:$F$43<V$50)*($G$6:$G$43>=V$50)*BY$6:BY$43) -> 43.666667 | W52: =SUMPRODUCT(($F$6:$F$43<W$50)*($G$6:$G$43>=W$50)*BY$6:BY$43) -> 43.666667 | X52: =SUMPRODUCT(($F$6:$F$43<X$50)*($G$6:$G$43>=X$50)*BY$6:BY$43) -> 43.666667 | Y52: =SUMPRODUCT(($F$6:$F$43<Y$50)*($G$6:$G$43>=Y$50)*BY$6:BY$43) -> 43 | Z52: =SUMPRODUCT(($F$6:$F$43<Z$50)*($G$6:$G$43>=Z$50)*BY$6:BY$43) -> 43 | AA52: =SUMPRODUCT(($F$6:$F$43<AA$50)*($G$6:$G$43>=AA$50)*BY$6:BY$43) -> 43 | AB52: =SUMPRODUCT(($F$6:$F$43<AB$50)*($G$6:$G$43>=AB$50)*BY$6:BY$43) -> 43 | AC52: =SUMPRODUCT(($F$6:$F$43<AC$50)*($G$6:$G$43>=AC$50)*BY$6:BY$43) -> 43 | AD52: =SUMPRODUCT(($F$6:$F$43<AD$50)*($G$6:$G$43>=AD$50)*BY$6:BY$43) -> 43 | AE52: =SUMPRODUCT(($F$6:$F$43<AE$50)*($G$6:$G$43>=AE$50)*BY$6:BY$43) -> 43 | AF52: =SUMPRODUCT(($F$6:$F$43<AF$50)*($G$6:$G$43>=AF$50)*BY$6:BY$43) -> 12.333333 | AG52: =SUMPRODUCT(($F$6:$F$43<AG$50)*($G$6:$G$43>=AG$50)*BY$6:BY$43) -> 44 | AH52: =SUMPRODUCT(($F$6:$F$43<AH$50)*($G$6:$G$43>=AH$50)*BY$6:BY$43) -> 15 | AI52: =SUMPRODUCT(($F$6:$F$43<AI$50)*($G$6:$G$43>=AI$50)*BY$6:BY$43) -> 43.571429 | AJ52: =SUMPRODUCT(($F$6:$F$43<AJ$50)*($G$6:$G$43>=AJ$50)*BY$6:BY$43) -> 43.571429 | AK52: =SUMPRODUCT(($F$6:$F$43<AK$50)*($G$6:$G$43>=AK$50)*BY$6:BY$43) -> 43.571429 | AL52: =SUMPRODUCT(($F$6:$F$43<AL$50)*($G$6:$G$43>=AL$50)*BY$6:BY$43) -> 43.571429 | AM52: =SUMPRODUCT(($F$6:$F$43<AM$50)*($G$6:$G$43>=AM$50)*BY$6:BY$43) -> 43.571429 | AN52: =SUMPRODUCT(($F$6:$F$43<AN$50)*($G$6:$G$43>=AN$50)*BY$6:BY$43) -> 43.571429 | AO52: =SUMPRODUCT(($F$6:$F$43<AO$50)*($G$6:$G$43>=AO$50)*BY$6:BY$43) -> 43.571429 | AP52: =SUMPRODUCT(($F$6:$F$43<AP$50)*($G$6:$G$43>=AP$50)*BY$6:BY$43) -> 43.571429 | AQ52: =SUMPRODUCT(($F$6:$F$43<AQ$50)*($G$6:$G$43>=AQ$50)*BY$6:BY$43) -> 43.571429 | AR52: =SUMPRODUCT(($F$6:$F$43<AR$50)*($G$6:$G$43>=AR$50)*BY$6:BY$43) -> 31.238095 | AS52: =SUMPRODUCT(($F$6:$F$43<AS$50)*($G$6:$G$43>=AS$50)*BY$6:BY$43) -> 43.571429 | AT52: =SUMPRODUCT(($F$6:$F$43<AT$50)*($G$6:$G$43>=AT$50)*BY$6:BY$43) -> 43.571429 | AU52: =SUMPRODUCT(($F$6:$F$43<AU$50)*($G$6:$G$43>=AU$50)*BY$6:BY$43) -> 43.571429 | AV52: =SUMPRODUCT(($F$6:$F$43<AV$50)*($G$6:$G$43>=AV$50)*BY$6:BY$43) -> 43.571429 | AW52: =SUMPRODUCT(($F$6:$F$43<AW$50)*($G$6:$G$43>=AW$50)*BY$6:BY$43) -> 15 | AX52: =SUMPRODUCT(($F$6:$F$43<AX$50)*($G$6:$G$43>=AX$50)*BY$6:BY$43) -> 15 | AY52: =SUMPRODUCT(($F$6:$F$43<AY$50)*($G$6:$G$43>=AY$50)*BY$6:BY$43) -> 43.5 | AZ52: =SUMPRODUCT(($F$6:$F$43<AZ$50)*($G$6:$G$43>=AZ$50)*BY$6:BY$43) -> 43.5 | BA52: =SUMPRODUCT(($F$6:$F$43<BA$50)*($G$6:$G$43>=BA$50)*BY$6:BY$43) -> 43.5 | BB52: =SUMPRODUCT(($F$6:$F$43<BB$50)*($G$6:$G$43>=BB$50)*BY$6:BY$43) -> 43.5 | BC52: =SUMPRODUCT(($F$6:$F$43<BC$50)*($G$6:$G$43>=BC$50)*BY$6:BY$43) -> 43.5 | BD52: =SUMPRODUCT(($F$6:$F$43<BD$50)*($G$6:$G$43>=BD$50)*BY$6:BY$43) -> 43.5 | BE52: =SUMPRODUCT(($F$6:$F$43<BE$50)*($G$6:$G$43>=BE$50)*BY$6:BY$43) -> 0 | BF52: =SUMPRODUCT(($F$6:$F$43<BF$50)*($G$6:$G$43>=BF$50)*BY$6:BY$43) -> 0 | BG52: =SUMPRODUCT(($F$6:$F$43<BG$50)*($G$6:$G$43>=BG$50)*BY$6:BY$43) -> 0 | BH52: =SUMPRODUCT(($F$6:$F$43<BH$50)*($G$6:$G$43>=BH$50)*BY$6:BY$43) -> 0 | BI52: =SUMPRODUCT(($F$6:$F$43<BI$50)*($G$6:$G$43>=BI$50)*BY$6:BY$43) -> 0 | BJ52: =SUMPRODUCT(($F$6:$F$43<BJ$50)*($G$6:$G$43>=BJ$50)*BY$6:BY$43) -> 0 | BK52: =SUMPRODUCT(($F$6:$F$43<BK$50)*($G$6:$G$43>=BK$50)*BY$6:BY$43) -> 0 | BL52: =SUMPRODUCT(($F$6:$F$43<BL$50)*($G$6:$G$43>=BL$50)*BY$6:BY$43) -> 0 | BM52: =SUMPRODUCT(($F$6:$F$43<BM$50)*($G$6:$G$43>=BM$50)*BY$6:BY$43) -> 0
A53: R3 David Felipe | B53: =SUM(R53:BM53) -> 1799 | C53: =MAX(R53:BM53) -> 46.5 | D53: =B53/1920 -> 0.93697917 | R53: =SUMPRODUCT(($F$6:$F$43<R$50)*($G$6:$G$43>=R$50)*BZ$6:BZ$43) -> 0 | S53: =SUMPRODUCT(($F$6:$F$43<S$50)*($G$6:$G$43>=S$50)*BZ$6:BZ$43) -> 43.666667 | T53: =SUMPRODUCT(($F$6:$F$43<T$50)*($G$6:$G$43>=T$50)*BZ$6:BZ$43) -> 43.666667 | U53: =SUMPRODUCT(($F$6:$F$43<U$50)*($G$6:$G$43>=U$50)*BZ$6:BZ$43) -> 43.666667 | V53: =SUMPRODUCT(($F$6:$F$43<V$50)*($G$6:$G$43>=V$50)*BZ$6:BZ$43) -> 45.333333 | W53: =SUMPRODUCT(($F$6:$F$43<W$50)*($G$6:$G$43>=W$50)*BZ$6:BZ$43) -> 45.333333 | X53: =SUMPRODUCT(($F$6:$F$43<X$50)*($G$6:$G$43>=X$50)*BZ$6:BZ$43) -> 45.333333 | Y53: =SUMPRODUCT(($F$6:$F$43<Y$50)*($G$6:$G$43>=Y$50)*BZ$6:BZ$43) -> 43.6 | Z53: =SUMPRODUCT(($F$6:$F$43<Z$50)*($G$6:$G$43>=Z$50)*BZ$6:BZ$43) -> 43.6 | AA53: =SUMPRODUCT(($F$6:$F$43<AA$50)*($G$6:$G$43>=AA$50)*BZ$6:BZ$43) -> 43.6 | AB53: =SUMPRODUCT(($F$6:$F$43<AB$50)*($G$6:$G$43>=AB$50)*BZ$6:BZ$43) -> 43.6 | AC53: =SUMPRODUCT(($F$6:$F$43<AC$50)*($G$6:$G$43>=AC$50)*BZ$6:BZ$43) -> 43.6 | AD53: =SUMPRODUCT(($F$6:$F$43<AD$50)*($G$6:$G$43>=AD$50)*BZ$6:BZ$43) -> 43.5 | AE53: =SUMPRODUCT(($F$6:$F$43<AE$50)*($G$6:$G$43>=AE$50)*BZ$6:BZ$43) -> 43.5 | AF53: =SUMPRODUCT(($F$6:$F$43<AF$50)*($G$6:$G$43>=AF$50)*BZ$6:BZ$43) -> 43.5 | AG53: =SUMPRODUCT(($F$6:$F$43<AG$50)*($G$6:$G$43>=AG$50)*BZ$6:BZ$43) -> 43.583333 | AH53: =SUMPRODUCT(($F$6:$F$43<AH$50)*($G$6:$G$43>=AH$50)*BZ$6:BZ$43) -> 43.583333 | AI53: =SUMPRODUCT(($F$6:$F$43<AI$50)*($G$6:$G$43>=AI$50)*BZ$6:BZ$43) -> 43.583333 | AJ53: =SUMPRODUCT(($F$6:$F$43<AJ$50)*($G$6:$G$43>=AJ$50)*BZ$6:BZ$43) -> 43.583333 | AK53: =SUMPRODUCT(($F$6:$F$43<AK$50)*($G$6:$G$43>=AK$50)*BZ$6:BZ$43) -> 43.583333 | AL53: =SUMPRODUCT(($F$6:$F$43<AL$50)*($G$6:$G$43>=AL$50)*BZ$6:BZ$43) -> 43.583333 | AM53: =SUMPRODUCT(($F$6:$F$43<AM$50)*($G$6:$G$43>=AM$50)*BZ$6:BZ$43) -> 43.583333 | AN53: =SUMPRODUCT(($F$6:$F$43<AN$50)*($G$6:$G$43>=AN$50)*BZ$6:BZ$43) -> 43.583333 | AO53: =SUMPRODUCT(($F$6:$F$43<AO$50)*($G$6:$G$43>=AO$50)*BZ$6:BZ$43) -> 43.583333 | AP53: =SUMPRODUCT(($F$6:$F$43<AP$50)*($G$6:$G$43>=AP$50)*BZ$6:BZ$43) -> 43.583333 | AQ53: =SUMPRODUCT(($F$6:$F$43<AQ$50)*($G$6:$G$43>=AQ$50)*BZ$6:BZ$43) -> 43.583333 | AR53: =SUMPRODUCT(($F$6:$F$43<AR$50)*($G$6:$G$43>=AR$50)*BZ$6:BZ$43) -> 41.583333 | AS53: =SUMPRODUCT(($F$6:$F$43<AS$50)*($G$6:$G$43>=AS$50)*BZ$6:BZ$43) -> 43.666667 | AT53: =SUMPRODUCT(($F$6:$F$43<AT$50)*($G$6:$G$43>=AT$50)*BZ$6:BZ$43) -> 43.666667 | AU53: =SUMPRODUCT(($F$6:$F$43<AU$50)*($G$6:$G$43>=AU$50)*BZ$6:BZ$43) -> 43.666667 | AV53: =SUMPRODUCT(($F$6:$F$43<AV$50)*($G$6:$G$43>=AV$50)*BZ$6:BZ$43) -> 43.666667 | AW53: =SUMPRODUCT(($F$6:$F$43<AW$50)*($G$6:$G$43>=AW$50)*BZ$6:BZ$43) -> 43.666667 | AX53: =SUMPRODUCT(($F$6:$F$43<AX$50)*($G$6:$G$43>=AX$50)*BZ$6:BZ$43) -> 38.166667 | AY53: =SUMPRODUCT(($F$6:$F$43<AY$50)*($G$6:$G$43>=AY$50)*BZ$6:BZ$43) -> 46.5 | AZ53: =SUMPRODUCT(($F$6:$F$43<AZ$50)*($G$6:$G$43>=AZ$50)*BZ$6:BZ$43) -> 46.5 | BA53: =SUMPRODUCT(($F$6:$F$43<BA$50)*($G$6:$G$43>=BA$50)*BZ$6:BZ$43) -> 43.5 | BB53: =SUMPRODUCT(($F$6:$F$43<BB$50)*($G$6:$G$43>=BB$50)*BZ$6:BZ$43) -> 43.5 | BC53: =SUMPRODUCT(($F$6:$F$43<BC$50)*($G$6:$G$43>=BC$50)*BZ$6:BZ$43) -> 43.5 | BD53: =SUMPRODUCT(($F$6:$F$43<BD$50)*($G$6:$G$43>=BD$50)*BZ$6:BZ$43) -> 43.5 | BE53: =SUMPRODUCT(($F$6:$F$43<BE$50)*($G$6:$G$43>=BE$50)*BZ$6:BZ$43) -> 46.333333 | BF53: =SUMPRODUCT(($F$6:$F$43<BF$50)*($G$6:$G$43>=BF$50)*BZ$6:BZ$43) -> 46.333333 | BG53: =SUMPRODUCT(($F$6:$F$43<BG$50)*($G$6:$G$43>=BG$50)*BZ$6:BZ$43) -> 46.333333 | BH53: =SUMPRODUCT(($F$6:$F$43<BH$50)*($G$6:$G$43>=BH$50)*BZ$6:BZ$43) -> 0 | BI53: =SUMPRODUCT(($F$6:$F$43<BI$50)*($G$6:$G$43>=BI$50)*BZ$6:BZ$43) -> 0 | BJ53: =SUMPRODUCT(($F$6:$F$43<BJ$50)*($G$6:$G$43>=BJ$50)*BZ$6:BZ$43) -> 0 | BK53: =SUMPRODUCT(($F$6:$F$43<BK$50)*($G$6:$G$43>=BK$50)*BZ$6:BZ$43) -> 0 | BL53: =SUMPRODUCT(($F$6:$F$43<BL$50)*($G$6:$G$43>=BL$50)*BZ$6:BZ$43) -> 0 | BM53: =SUMPRODUCT(($F$6:$F$43<BM$50)*($G$6:$G$43>=BM$50)*BZ$6:BZ$43) -> 0
A54: R4 Juan | B54: =SUM(R54:BM54) -> 1691 | C54: =MAX(R54:BM54) -> 44 | D54: =B54/1920 -> 0.88072917 | R54: =SUMPRODUCT(($F$6:$F$43<R$50)*($G$6:$G$43>=R$50)*CA$6:CA$43) -> 0 | S54: =SUMPRODUCT(($F$6:$F$43<S$50)*($G$6:$G$43>=S$50)*CA$6:CA$43) -> 43.666667 | T54: =SUMPRODUCT(($F$6:$F$43<T$50)*($G$6:$G$43>=T$50)*CA$6:CA$43) -> 43.666667 | U54: =SUMPRODUCT(($F$6:$F$43<U$50)*($G$6:$G$43>=U$50)*CA$6:CA$43) -> 43.666667 | V54: =SUMPRODUCT(($F$6:$F$43<V$50)*($G$6:$G$43>=V$50)*CA$6:CA$43) -> 43.666667 | W54: =SUMPRODUCT(($F$6:$F$43<W$50)*($G$6:$G$43>=W$50)*CA$6:CA$43) -> 43.666667 | X54: =SUMPRODUCT(($F$6:$F$43<X$50)*($G$6:$G$43>=X$50)*CA$6:CA$43) -> 43.666667 | Y54: =SUMPRODUCT(($F$6:$F$43<Y$50)*($G$6:$G$43>=Y$50)*CA$6:CA$43) -> 43.55 | Z54: =SUMPRODUCT(($F$6:$F$43<Z$50)*($G$6:$G$43>=Z$50)*CA$6:CA$43) -> 43.55 | AA54: =SUMPRODUCT(($F$6:$F$43<AA$50)*($G$6:$G$43>=AA$50)*CA$6:CA$43) -> 43.55 | AB54: =SUMPRODUCT(($F$6:$F$43<AB$50)*($G$6:$G$43>=AB$50)*CA$6:CA$43) -> 43.55 | AC54: =SUMPRODUCT(($F$6:$F$43<AC$50)*($G$6:$G$43>=AC$50)*CA$6:CA$43) -> 11.8 | AD54: =SUMPRODUCT(($F$6:$F$43<AD$50)*($G$6:$G$43>=AD$50)*CA$6:CA$43) -> 43.5 | AE54: =SUMPRODUCT(($F$6:$F$43<AE$50)*($G$6:$G$43>=AE$50)*CA$6:CA$43) -> 43.5 | AF54: =SUMPRODUCT(($F$6:$F$43<AF$50)*($G$6:$G$43>=AF$50)*CA$6:CA$43) -> 43.5 | AG54: =SUMPRODUCT(($F$6:$F$43<AG$50)*($G$6:$G$43>=AG$50)*CA$6:CA$43) -> 43.5 | AH54: =SUMPRODUCT(($F$6:$F$43<AH$50)*($G$6:$G$43>=AH$50)*CA$6:CA$43) -> 32.15 | AI54: =SUMPRODUCT(($F$6:$F$43<AI$50)*($G$6:$G$43>=AI$50)*CA$6:CA$43) -> 32.15 | AJ54: =SUMPRODUCT(($F$6:$F$43<AJ$50)*($G$6:$G$43>=AJ$50)*CA$6:CA$43) -> 32.15 | AK54: =SUMPRODUCT(($F$6:$F$43<AK$50)*($G$6:$G$43>=AK$50)*CA$6:CA$43) -> 32.15 | AL54: =SUMPRODUCT(($F$6:$F$43<AL$50)*($G$6:$G$43>=AL$50)*CA$6:CA$43) -> 16.9 | AM54: =SUMPRODUCT(($F$6:$F$43<AM$50)*($G$6:$G$43>=AM$50)*CA$6:CA$43) -> 16.9 | AN54: =SUMPRODUCT(($F$6:$F$43<AN$50)*($G$6:$G$43>=AN$50)*CA$6:CA$43) -> 16.9 | AO54: =SUMPRODUCT(($F$6:$F$43<AO$50)*($G$6:$G$43>=AO$50)*CA$6:CA$43) -> 16.9 | AP54: =SUMPRODUCT(($F$6:$F$43<AP$50)*($G$6:$G$43>=AP$50)*CA$6:CA$43) -> 16.9 | AQ54: =SUMPRODUCT(($F$6:$F$43<AQ$50)*($G$6:$G$43>=AQ$50)*CA$6:CA$43) -> 43.566667 | AR54: =SUMPRODUCT(($F$6:$F$43<AR$50)*($G$6:$G$43>=AR$50)*CA$6:CA$43) -> 26.666667 | AS54: =SUMPRODUCT(($F$6:$F$43<AS$50)*($G$6:$G$43>=AS$50)*CA$6:CA$43) -> 43.666667 | AT54: =SUMPRODUCT(($F$6:$F$43<AT$50)*($G$6:$G$43>=AT$50)*CA$6:CA$43) -> 43.666667 | AU54: =SUMPRODUCT(($F$6:$F$43<AU$50)*($G$6:$G$43>=AU$50)*CA$6:CA$43) -> 43.666667 | AV54: =SUMPRODUCT(($F$6:$F$43<AV$50)*($G$6:$G$43>=AV$50)*CA$6:CA$43) -> 43.666667 | AW54: =SUMPRODUCT(($F$6:$F$43<AW$50)*($G$6:$G$43>=AW$50)*CA$6:CA$43) -> 43.5 | AX54: =SUMPRODUCT(($F$6:$F$43<AX$50)*($G$6:$G$43>=AX$50)*CA$6:CA$43) -> 43.5 | AY54: =SUMPRODUCT(($F$6:$F$43<AY$50)*($G$6:$G$43>=AY$50)*CA$6:CA$43) -> 43.5 | AZ54: =SUMPRODUCT(($F$6:$F$43<AZ$50)*($G$6:$G$43>=AZ$50)*CA$6:CA$43) -> 43.5 | BA54: =SUMPRODUCT(($F$6:$F$43<BA$50)*($G$6:$G$43>=BA$50)*CA$6:CA$43) -> 43.5 | BB54: =SUMPRODUCT(($F$6:$F$43<BB$50)*($G$6:$G$43>=BB$50)*CA$6:CA$43) -> 43.5 | BC54: =SUMPRODUCT(($F$6:$F$43<BC$50)*($G$6:$G$43>=BC$50)*CA$6:CA$43) -> 44 | BD54: =SUMPRODUCT(($F$6:$F$43<BD$50)*($G$6:$G$43>=BD$50)*CA$6:CA$43) -> 44 | BE54: =SUMPRODUCT(($F$6:$F$43<BE$50)*($G$6:$G$43>=BE$50)*CA$6:CA$43) -> 43.666667 | BF54: =SUMPRODUCT(($F$6:$F$43<BF$50)*($G$6:$G$43>=BF$50)*CA$6:CA$43) -> 43.666667 | BG54: =SUMPRODUCT(($F$6:$F$43<BG$50)*($G$6:$G$43>=BG$50)*CA$6:CA$43) -> 43.666667 | BH54: =SUMPRODUCT(($F$6:$F$43<BH$50)*($G$6:$G$43>=BH$50)*CA$6:CA$43) -> 43.666667 | BI54: =SUMPRODUCT(($F$6:$F$43<BI$50)*($G$6:$G$43>=BI$50)*CA$6:CA$43) -> 43.666667 | BJ54: =SUMPRODUCT(($F$6:$F$43<BJ$50)*($G$6:$G$43>=BJ$50)*CA$6:CA$43) -> 43.666667 | BK54: =SUMPRODUCT(($F$6:$F$43<BK$50)*($G$6:$G$43>=BK$50)*CA$6:CA$43) -> 0 | BL54: =SUMPRODUCT(($F$6:$F$43<BL$50)*($G$6:$G$43>=BL$50)*CA$6:CA$43) -> 0 | BM54: =SUMPRODUCT(($F$6:$F$43<BM$50)*($G$6:$G$43>=BM$50)*CA$6:CA$43) -> 0
A55: R5 Jose Luis | B55: =SUM(R55:BM55) -> 1772 | C55: =MAX(R55:BM55) -> 43.721429 | D55: =B55/1920 -> 0.92291667 | R55: =SUMPRODUCT(($F$6:$F$43<R$50)*($G$6:$G$43>=R$50)*CB$6:CB$43) -> 36 | S55: =SUMPRODUCT(($F$6:$F$43<S$50)*($G$6:$G$43>=S$50)*CB$6:CB$43) -> 22 | T55: =SUMPRODUCT(($F$6:$F$43<T$50)*($G$6:$G$43>=T$50)*CB$6:CB$43) -> 22 | U55: =SUMPRODUCT(($F$6:$F$43<U$50)*($G$6:$G$43>=U$50)*CB$6:CB$43) -> 22 | V55: =SUMPRODUCT(($F$6:$F$43<V$50)*($G$6:$G$43>=V$50)*CB$6:CB$43) -> 43.666667 | W55: =SUMPRODUCT(($F$6:$F$43<W$50)*($G$6:$G$43>=W$50)*CB$6:CB$43) -> 43.666667 | X55: =SUMPRODUCT(($F$6:$F$43<X$50)*($G$6:$G$43>=X$50)*CB$6:CB$43) -> 43.666667 | Y55: =SUMPRODUCT(($F$6:$F$43<Y$50)*($G$6:$G$43>=Y$50)*CB$6:CB$43) -> 43.721429 | Z55: =SUMPRODUCT(($F$6:$F$43<Z$50)*($G$6:$G$43>=Z$50)*CB$6:CB$43) -> 43.721429 | AA55: =SUMPRODUCT(($F$6:$F$43<AA$50)*($G$6:$G$43>=AA$50)*CB$6:CB$43) -> 43.721429 | AB55: =SUMPRODUCT(($F$6:$F$43<AB$50)*($G$6:$G$43>=AB$50)*CB$6:CB$43) -> 43.721429 | AC55: =SUMPRODUCT(($F$6:$F$43<AC$50)*($G$6:$G$43>=AC$50)*CB$6:CB$43) -> 43.571429 | AD55: =SUMPRODUCT(($F$6:$F$43<AD$50)*($G$6:$G$43>=AD$50)*CB$6:CB$43) -> 34.921429 | AE55: =SUMPRODUCT(($F$6:$F$43<AE$50)*($G$6:$G$43>=AE$50)*CB$6:CB$43) -> 34.921429 | AF55: =SUMPRODUCT(($F$6:$F$43<AF$50)*($G$6:$G$43>=AF$50)*CB$6:CB$43) -> 43.683333 | AG55: =SUMPRODUCT(($F$6:$F$43<AG$50)*($G$6:$G$43>=AG$50)*CB$6:CB$43) -> 43.683333 | AH55: =SUMPRODUCT(($F$6:$F$43<AH$50)*($G$6:$G$43>=AH$50)*CB$6:CB$43) -> 43.683333 | AI55: =SUMPRODUCT(($F$6:$F$43<AI$50)*($G$6:$G$43>=AI$50)*CB$6:CB$43) -> 43.683333 | AJ55: =SUMPRODUCT(($F$6:$F$43<AJ$50)*($G$6:$G$43>=AJ$50)*CB$6:CB$43) -> 43.683333 | AK55: =SUMPRODUCT(($F$6:$F$43<AK$50)*($G$6:$G$43>=AK$50)*CB$6:CB$43) -> 43.683333 | AL55: =SUMPRODUCT(($F$6:$F$43<AL$50)*($G$6:$G$43>=AL$50)*CB$6:CB$43) -> 38.933333 | AM55: =SUMPRODUCT(($F$6:$F$43<AM$50)*($G$6:$G$43>=AM$50)*CB$6:CB$43) -> 38.933333 | AN55: =SUMPRODUCT(($F$6:$F$43<AN$50)*($G$6:$G$43>=AN$50)*CB$6:CB$43) -> 38.933333 | AO55: =SUMPRODUCT(($F$6:$F$43<AO$50)*($G$6:$G$43>=AO$50)*CB$6:CB$43) -> 38.933333 | AP55: =SUMPRODUCT(($F$6:$F$43<AP$50)*($G$6:$G$43>=AP$50)*CB$6:CB$43) -> 38.933333 | AQ55: =SUMPRODUCT(($F$6:$F$43<AQ$50)*($G$6:$G$43>=AQ$50)*CB$6:CB$43) -> 38.933333 | AR55: =SUMPRODUCT(($F$6:$F$43<AR$50)*($G$6:$G$43>=AR$50)*CB$6:CB$43) -> 43.6 | AS55: =SUMPRODUCT(($F$6:$F$43<AS$50)*($G$6:$G$43>=AS$50)*CB$6:CB$43) -> 43.6 | AT55: =SUMPRODUCT(($F$6:$F$43<AT$50)*($G$6:$G$43>=AT$50)*CB$6:CB$43) -> 43.6 | AU55: =SUMPRODUCT(($F$6:$F$43<AU$50)*($G$6:$G$43>=AU$50)*CB$6:CB$43) -> 43.6 | AV55: =SUMPRODUCT(($F$6:$F$43<AV$50)*($G$6:$G$43>=AV$50)*CB$6:CB$43) -> 19.1 | AW55: =SUMPRODUCT(($F$6:$F$43<AW$50)*($G$6:$G$43>=AW$50)*CB$6:CB$43) -> 43.5 | AX55: =SUMPRODUCT(($F$6:$F$43<AX$50)*($G$6:$G$43>=AX$50)*CB$6:CB$43) -> 29 | AY55: =SUMPRODUCT(($F$6:$F$43<AY$50)*($G$6:$G$43>=AY$50)*CB$6:CB$43) -> 40 | AZ55: =SUMPRODUCT(($F$6:$F$43<AZ$50)*($G$6:$G$43>=AZ$50)*CB$6:CB$43) -> 40 | BA55: =SUMPRODUCT(($F$6:$F$43<BA$50)*($G$6:$G$43>=BA$50)*CB$6:CB$43) -> 27 | BB55: =SUMPRODUCT(($F$6:$F$43<BB$50)*($G$6:$G$43>=BB$50)*CB$6:CB$43) -> 27 | BC55: =SUMPRODUCT(($F$6:$F$43<BC$50)*($G$6:$G$43>=BC$50)*CB$6:CB$43) -> 43.5 | BD55: =SUMPRODUCT(($F$6:$F$43<BD$50)*($G$6:$G$43>=BD$50)*CB$6:CB$43) -> 43.5 | BE55: =SUMPRODUCT(($F$6:$F$43<BE$50)*($G$6:$G$43>=BE$50)*CB$6:CB$43) -> 43.333333 | BF55: =SUMPRODUCT(($F$6:$F$43<BF$50)*($G$6:$G$43>=BF$50)*CB$6:CB$43) -> 43.333333 | BG55: =SUMPRODUCT(($F$6:$F$43<BG$50)*($G$6:$G$43>=BG$50)*CB$6:CB$43) -> 43.333333 | BH55: =SUMPRODUCT(($F$6:$F$43<BH$50)*($G$6:$G$43>=BH$50)*CB$6:CB$43) -> 9.6666667 | BI55: =SUMPRODUCT(($F$6:$F$43<BI$50)*($G$6:$G$43>=BI$50)*CB$6:CB$43) -> 9.6666667 | BJ55: =SUMPRODUCT(($F$6:$F$43<BJ$50)*($G$6:$G$43>=BJ$50)*CB$6:CB$43) -> 9.6666667 | BK55: =SUMPRODUCT(($F$6:$F$43<BK$50)*($G$6:$G$43>=BK$50)*CB$6:CB$43) -> 36.5 | BL55: =SUMPRODUCT(($F$6:$F$43<BL$50)*($G$6:$G$43>=BL$50)*CB$6:CB$43) -> 36.5 | BM55: =SUMPRODUCT(($F$6:$F$43<BM$50)*($G$6:$G$43>=BM$50)*CB$6:CB$43) -> 36
A56: R6 Ian | B56: =SUM(R56:BM56) -> 1663 | C56: =MAX(R56:BM56) -> 46.5 | D56: =B56/1920 -> 0.86614583 | R56: =SUMPRODUCT(($F$6:$F$43<R$50)*($G$6:$G$43>=R$50)*CC$6:CC$43) -> 0 | S56: =SUMPRODUCT(($F$6:$F$43<S$50)*($G$6:$G$43>=S$50)*CC$6:CC$43) -> 43.666667 | T56: =SUMPRODUCT(($F$6:$F$43<T$50)*($G$6:$G$43>=T$50)*CC$6:CC$43) -> 43.666667 | U56: =SUMPRODUCT(($F$6:$F$43<U$50)*($G$6:$G$43>=U$50)*CC$6:CC$43) -> 43.666667 | V56: =SUMPRODUCT(($F$6:$F$43<V$50)*($G$6:$G$43>=V$50)*CC$6:CC$43) -> 43.666667 | W56: =SUMPRODUCT(($F$6:$F$43<W$50)*($G$6:$G$43>=W$50)*CC$6:CC$43) -> 43.666667 | X56: =SUMPRODUCT(($F$6:$F$43<X$50)*($G$6:$G$43>=X$50)*CC$6:CC$43) -> 43.666667 | Y56: =SUMPRODUCT(($F$6:$F$43<Y$50)*($G$6:$G$43>=Y$50)*CC$6:CC$43) -> 43.5 | Z56: =SUMPRODUCT(($F$6:$F$43<Z$50)*($G$6:$G$43>=Z$50)*CC$6:CC$43) -> 43.5 | AA56: =SUMPRODUCT(($F$6:$F$43<AA$50)*($G$6:$G$43>=AA$50)*CC$6:CC$43) -> 43.5 | AB56: =SUMPRODUCT(($F$6:$F$43<AB$50)*($G$6:$G$43>=AB$50)*CC$6:CC$43) -> 43.5 | AC56: =SUMPRODUCT(($F$6:$F$43<AC$50)*($G$6:$G$43>=AC$50)*CC$6:CC$43) -> 40 | AD56: =SUMPRODUCT(($F$6:$F$43<AD$50)*($G$6:$G$43>=AD$50)*CC$6:CC$43) -> 44.25 | AE56: =SUMPRODUCT(($F$6:$F$43<AE$50)*($G$6:$G$43>=AE$50)*CC$6:CC$43) -> 44.25 | AF56: =SUMPRODUCT(($F$6:$F$43<AF$50)*($G$6:$G$43>=AF$50)*CC$6:CC$43) -> 44.25 | AG56: =SUMPRODUCT(($F$6:$F$43<AG$50)*($G$6:$G$43>=AG$50)*CC$6:CC$43) -> 43.166667 | AH56: =SUMPRODUCT(($F$6:$F$43<AH$50)*($G$6:$G$43>=AH$50)*CC$6:CC$43) -> 43.516667 | AI56: =SUMPRODUCT(($F$6:$F$43<AI$50)*($G$6:$G$43>=AI$50)*CC$6:CC$43) -> 43.516667 | AJ56: =SUMPRODUCT(($F$6:$F$43<AJ$50)*($G$6:$G$43>=AJ$50)*CC$6:CC$43) -> 43.516667 | AK56: =SUMPRODUCT(($F$6:$F$43<AK$50)*($G$6:$G$43>=AK$50)*CC$6:CC$43) -> 43.516667 | AL56: =SUMPRODUCT(($F$6:$F$43<AL$50)*($G$6:$G$43>=AL$50)*CC$6:CC$43) -> 43.516667 | AM56: =SUMPRODUCT(($F$6:$F$43<AM$50)*($G$6:$G$43>=AM$50)*CC$6:CC$43) -> 43.516667 | AN56: =SUMPRODUCT(($F$6:$F$43<AN$50)*($G$6:$G$43>=AN$50)*CC$6:CC$43) -> 43.516667 | AO56: =SUMPRODUCT(($F$6:$F$43<AO$50)*($G$6:$G$43>=AO$50)*CC$6:CC$43) -> 43.516667 | AP56: =SUMPRODUCT(($F$6:$F$43<AP$50)*($G$6:$G$43>=AP$50)*CC$6:CC$43) -> 43.516667 | AQ56: =SUMPRODUCT(($F$6:$F$43<AQ$50)*($G$6:$G$43>=AQ$50)*CC$6:CC$43) -> 43.516667 | AR56: =SUMPRODUCT(($F$6:$F$43<AR$50)*($G$6:$G$43>=AR$50)*CC$6:CC$43) -> 43.416667 | AS56: =SUMPRODUCT(($F$6:$F$43<AS$50)*($G$6:$G$43>=AS$50)*CC$6:CC$43) -> 34.833333 | AT56: =SUMPRODUCT(($F$6:$F$43<AT$50)*($G$6:$G$43>=AT$50)*CC$6:CC$43) -> 34.833333 | AU56: =SUMPRODUCT(($F$6:$F$43<AU$50)*($G$6:$G$43>=AU$50)*CC$6:CC$43) -> 34.833333 | AV56: =SUMPRODUCT(($F$6:$F$43<AV$50)*($G$6:$G$43>=AV$50)*CC$6:CC$43) -> 19.333333 | AW56: =SUMPRODUCT(($F$6:$F$43<AW$50)*($G$6:$G$43>=AW$50)*CC$6:CC$43) -> 43.833333 | AX56: =SUMPRODUCT(($F$6:$F$43<AX$50)*($G$6:$G$43>=AX$50)*CC$6:CC$43) -> 43.833333 | AY56: =SUMPRODUCT(($F$6:$F$43<AY$50)*($G$6:$G$43>=AY$50)*CC$6:CC$43) -> 46.5 | AZ56: =SUMPRODUCT(($F$6:$F$43<AZ$50)*($G$6:$G$43>=AZ$50)*CC$6:CC$43) -> 46.5 | BA56: =SUMPRODUCT(($F$6:$F$43<BA$50)*($G$6:$G$43>=BA$50)*CC$6:CC$43) -> 43.5 | BB56: =SUMPRODUCT(($F$6:$F$43<BB$50)*($G$6:$G$43>=BB$50)*CC$6:CC$43) -> 43.5 | BC56: =SUMPRODUCT(($F$6:$F$43<BC$50)*($G$6:$G$43>=BC$50)*CC$6:CC$43) -> 27 | BD56: =SUMPRODUCT(($F$6:$F$43<BD$50)*($G$6:$G$43>=BD$50)*CC$6:CC$43) -> 27 | BE56: =SUMPRODUCT(($F$6:$F$43<BE$50)*($G$6:$G$43>=BE$50)*CC$6:CC$43) -> 0 | BF56: =SUMPRODUCT(($F$6:$F$43<BF$50)*($G$6:$G$43>=BF$50)*CC$6:CC$43) -> 0 | BG56: =SUMPRODUCT(($F$6:$F$43<BG$50)*($G$6:$G$43>=BG$50)*CC$6:CC$43) -> 0 | BH56: =SUMPRODUCT(($F$6:$F$43<BH$50)*($G$6:$G$43>=BH$50)*CC$6:CC$43) -> 0 | BI56: =SUMPRODUCT(($F$6:$F$43<BI$50)*($G$6:$G$43>=BI$50)*CC$6:CC$43) -> 0 | BJ56: =SUMPRODUCT(($F$6:$F$43<BJ$50)*($G$6:$G$43>=BJ$50)*CC$6:CC$43) -> 0 | BK56: =SUMPRODUCT(($F$6:$F$43<BK$50)*($G$6:$G$43>=BK$50)*CC$6:CC$43) -> 43.5 | BL56: =SUMPRODUCT(($F$6:$F$43<BL$50)*($G$6:$G$43>=BL$50)*CC$6:CC$43) -> 43.5 | BM56: =SUMPRODUCT(($F$6:$F$43<BM$50)*($G$6:$G$43>=BM$50)*CC$6:CC$43) -> 0
A57: Equipo | B57: =SUM(R57:BM57) -> 10160 | C57: =MAX(R57:BM57) -> 254.2381 | R57: =SUM(R51:R56) -> 80 | S57: =SUM(S51:S56) -> 240 | T57: =SUM(T51:T56) -> 240 | U57: =SUM(U51:U56) -> 185 | V57: =SUM(V51:V56) -> 245 | W57: =SUM(W51:W56) -> 245 | X57: =SUM(X51:X56) -> 245 | Y57: =SUM(Y51:Y56) -> 253.57143 | ... BM57: =SUM(BM51:BM56) -> 80
A58: Capacidad (6 × 42 h) | R58: 252 | S58: 252 | T58: 252 | U58: 252 | V58: 252 | W58: 252 | X58: 252 | Y58: 252 | Z58: 252 | AA58: 252 | AB58: 252 | AC58: 252 | AD58: 252 | AE58: 252 | AF58: 252 | AG58: 252 | AH58: 252 | AI58: 252 | AJ58: 252 | AK58: 252 | AL58: 252 | AM58: 252 | AN58: 252 | AO58: 252 | AP58: 252 | AQ58: 252 | AR58: 252 | AS58: 252 | AT58: 252 | AU58: 252 | AV58: 252 | AW58: 252 | AX58: 252 | AY58: 252 | AZ58: 252 | BA58: 252 | BB58: 252 | BC58: 252 | BD58: 252 | BE58: 252 | BF58: 252 | BG58: 252 | BH58: 252 | BI58: 252 | BJ58: 252 | BK58: 252 | BL58: 252 | BM58: 252
A60: Horas por encima de 42 h/semana (horas extra) | B60: =SUMPRODUCT((R51:BM51>42)*(R51:BM51-42))+SUMPRODUCT((R52:BM52>42)*(R52:BM52-42))+SUMPRODUCT((R53:BM53>42)*(R53:BM53-42))+SUMPRODUCT((R54:BM54>42)*(R54:BM54-42))+SUMPRODUCT((R55:BM55>42)*(R55:BM55-42))+SUMPRODUCT((R56:BM56>42)*(R56:BM56-42)) -> 304.53571
A61: Nivelación: las actividades con holgura se desplazan (columna Q) o se alargan dentro de su holgura, y las horas de cada paquete se reparten entre el responsable y los integrantes de apoyo (columnas BQ a BV). La carga del equipo no supera 254 h/semana (≈ 42 h por persona) y la duración sigue en 48 semanas.
A62: Paso hacia atrás: la columna I usa los sucesores escritos a mano (MIN de los LS de los sucesores), derivados de la columna de predecesoras; si se cambia una predecesora hay que actualizar también esa fórmula.

Sheet Precio_Kuajo
A1: Construcción del precio de la oferta de Kuajo Automation a Lácteos Pomar (Fase 1)
A2: Costo para Kuajo → precio de venta. Valores en COP sin IVA.
A4: Concepto | B4: Costo para Kuajo (COP) | C4: Precio para Pomar (COP) | D4: Equivalente (US$) | E4: Participación en el precio | F4: Cómo se calcula
A5: Suministro: Instrumentación | B5: =SUMIFS(Cotizaciones!$J$5:$J$70,Cotizaciones!$B$5:$B$70,"Instrumentación") -> 6.039566e+08 | C5: =B5*(1+Supuestos!$B$50) -> 6.6435225e+08 | D5: =C5/Supuestos!$B$6 -> 202949.22 | E5: =C5/$C$19 -> 0.077921486 | F5: Suma de la hoja Cotizaciones × (1 + margen sobre suministros)
A6: Suministro: Inspección | B6: =SUMIFS(Cotizaciones!$J$5:$J$70,Cotizaciones!$B$5:$B$70,"Inspección") -> 4.5252726e+08 | C6: =B6*(1+Supuestos!$B$50) -> 4.9777998e+08 | D6: =C6/Supuestos!$B$6 -> 152064 | E6: =C6/$C$19 -> 0.058384322 | F6: Suma de la hoja Cotizaciones × (1 + margen sobre suministros)
A7: Suministro: Válvulas y actuadores | B7: =SUMIFS(Cotizaciones!$J$5:$J$70,Cotizaciones!$B$5:$B$70,"Válvulas y actuadores") -> 6.6995246e+08 | C7: =B7*(1+Supuestos!$B$50) -> 7.3694771e+08 | D7: =C7/Supuestos!$B$6 -> 225126 | E7: =C7/$C$19 -> 0.086436164 | F7: Suma de la hoja Cotizaciones × (1 + margen sobre suministros)
A8: Suministro: Control | B8: =SUMIFS(Cotizaciones!$J$5:$J$70,Cotizaciones!$B$5:$B$70,"Control") -> 2.7929417e+08 | C8: =B8*(1+Supuestos!$B$50) -> 3.0722358e+08 | D8: =C8/Supuestos!$B$6 -> 93852 | E8: =C8/$C$19 -> 0.036034074 | F8: Suma de la hoja Cotizaciones × (1 + margen sobre suministros)
A9: Suministro: TI/OT | B9: =SUMIFS(Cotizaciones!$J$5:$J$70,Cotizaciones!$B$5:$B$70,"TI/OT") -> 4.8454199e+08 | C9: =B9*(1+Supuestos!$B$50) -> 5.3299619e+08 | D9: =C9/Supuestos!$B$6 -> 162822 | E9: =C9/$C$19 -> 0.06251481 | F9: Suma de la hoja Cotizaciones × (1 + margen sobre suministros)
A10: Suministro: Robótica | B10: =SUMIFS(Cotizaciones!$J$5:$J$70,Cotizaciones!$B$5:$B$70,"Robótica") -> 1466671836 | C10: =B10*(1+Supuestos!$B$50) -> 1.613339e+09 | D10: =C10/Supuestos!$B$6 -> 492849.84 | E10: =C10/$C$19 -> 0.18922759 | F10: Suma de la hoja Cotizaciones × (1 + margen sobre suministros)
A11: Suministro: Software | B11: =SUMIFS(Cotizaciones!$J$5:$J$70,Cotizaciones!$B$5:$B$70,"Software") -> 5.4944711e+08 | C11: =B11*(1+Supuestos!$B$50) -> 6.0439182e+08 | D11: =C11/Supuestos!$B$6 -> 184632.25 | E11: =C11/$C$19 -> 0.070888762 | F11: Suma de la hoja Cotizaciones × (1 + margen sobre suministros)
A12: Suministro: Obras y montaje locales | B12: =SUMIFS(Cotizaciones!$J$5:$J$70,Cotizaciones!$B$5:$B$70,"Obras y montaje locales") -> 1265000000 | C12: =B12*(1+Supuestos!$B$50) -> 1391500000 | D12: =C12/Supuestos!$B$6 -> 425081.49 | E12: =C12/$C$19 -> 0.16320822 | F12: Suma de la hoja Cotizaciones × (1 + margen sobre suministros)
A13: Subtotal suministros | B13: =SUM(B5:B12) -> 5.7713914e+09 | C13: =SUM(C5:C12) -> 6.3485306e+09 | D13: =C13/Supuestos!$B$6 -> 1939376.8 | E13: =C13/$C$19 -> 0.74461542
A14: Servicios de ingeniería, gestión, comisionamiento y capacitación (Kuajo) | B14: =Nomina_Kuajo!$G$11 -> 574938360 | C14: =Cronograma!$L$44*Supuestos!$B$47 -> 1524000000 | D14: =C14/Supuestos!$B$6 -> 465558.17 | E14: =C14/$C$19 -> 0.17874906 | F14: Costo = nómina del equipo; precio = horas del cronograma × tarifa
A15: Gastos generales de Kuajo | B15: =Nomina_Kuajo!$G$27 -> 268478190 | C15: 0 | D15: =C15/Supuestos!$B$6 -> 0 | E15: =C15/$C$19 -> 0 | F15: Cubiertos por la tarifa de ingeniería
A16: Contingencia | B16: =(B13+B14)*Supuestos!$B$51 -> 4.4424308e+08 | C16: =(C13+C14)*Supuestos!$B$51 -> 5.5107714e+08 | D16: =C16/Supuestos!$B$6 -> 168345.45 | E16: =C16/$C$19 -> 0.064635514 | F16: Contingencia × (suministros + ingeniería)
A17: Subtotal antes de póliza | B17: =B13+B14+B15+B16 -> 7.0590511e+09 | C17: =C13+C14+C15+C16 -> 8.4236077e+09 | D17: =C17/Supuestos!$B$6 -> 2573280.4 | E17: =C17/$C$19 -> 0.988
A18: Póliza de cumplimiento y calidad | B18: =C18 -> 1.0231102e+08 | C18: =C17/(1-Supuestos!$B$52)-C17 -> 1.0231102e+08 | D18: =C18/Supuestos!$B$6 -> 31254.418 | E18: =C18/$C$19 -> 0.012 | F18: El precio se ajusta para que la póliza quede cubierta
A19: PRECIO DE LA OFERTA (sin IVA) | B19: =B17+B18 -> 7.1613621e+09 | C19: =C17+C18 -> 8.5259187e+09 | D19: =C19/Supuestos!$B$6 -> 2604534.8 | E19: =C19/$C$19 -> 1 | F19: Costo total de Kuajo (columna B) vs. precio a Pomar (columna C)
A20: IVA 19 % (informativo; descontable para Pomar) | C20: =C19*Supuestos!$B$55 -> 1.6199246e+09 | D20: =C20/Supuestos!$B$6 -> 494861.62 | E20: =C20/$C$19 -> 0.19
A21: Precio total con IVA | C21: =C19+C20 -> 1.0145843e+10 | D21: =C21/Supuestos!$B$6 -> 3099396.5 | E21: =C21/$C$19 -> 1.19
A23: Control: valor planificado del cronograma = precio | C23: =Cronograma!$N$44-C19 -> 0 | F23: Debe dar 0 (la curva S suma el precio)
A24: Margen bruto esperado de Kuajo (antes de ICA, GMF e impuestos) | C24: =C19-B19+B16*(1-Supuestos!$B$56) -> 1.5866782e+09 | E24: =C24/C19 -> 0.18610055 | F24: Precio − costos, con el 50 % de la contingencia sin consumir
A26: Base de depreciación para Pomar
A27: Precio asignado a TI y software (vida útil 5 años) | C27: =SUMIFS(Cotizaciones!$J$5:$J$70,Cotizaciones!$N$5:$N$70,"TI/Software")*(1+Supuestos!$B$50)*(1+Supuestos!$B$51)/(1-Supuestos!$B$52) -> 1.3032643e+09 | F27: Suministros de TI y software a precio, con contingencia y póliza
A28: Precio asignado a maquinaria, equipo e ingeniería capitalizable (10 años) | C28: =C19-C27 -> 7.2226544e+09

Sheet Curva_S
A1: Curva S del proyecto: valor planificado por mes (COP)
A2: Cada actividad reparte su valor planificado de forma uniforme entre sus semanas. Mes = 52/12 semanas.
A4: Código | B4: Actividad | C4: Mes 1 | D4: Mes 2 | E4: Mes 3 | F4: Mes 4 | G4: Mes 5 | H4: Mes 6 | I4: Mes 7 | J4: Mes 8 | K4: Mes 9 | L4: Mes 10 | M4: Mes 11 | N4: Mes 12 | O4: Total
A5: 1.1 | B5: Acta de constitución y reunión de arranque | C5: =IF(Cronograma!$D$6=0,0,Cronograma!$N$6*MAX(0,MIN(Cronograma!$G$6,1*52/12)-MAX(Cronograma!$F$6,(1-1)*52/12))/Cronograma!$D$6) -> 12995951 | D5: =IF(Cronograma!$D$6=0,0,Cronograma!$N$6*MAX(0,MIN(Cronograma!$G$6,2*52/12)-MAX(Cronograma!$F$6,(2-1)*52/12))/Cronograma!$D$6) -> 0 | E5: =IF(Cronograma!$D$6=0,0,Cronograma!$N$6*MAX(0,MIN(Cronograma!$G$6,3*52/12)-MAX(Cronograma!$F$6,(3-1)*52/12))/Cronograma!$D$6) -> 0 | F5: =IF(Cronograma!$D$6=0,0,Cronograma!$N$6*MAX(0,MIN(Cronograma!$G$6,4*52/12)-MAX(Cronograma!$F$6,(4-1)*52/12))/Cronograma!$D$6) -> 0 | G5: =IF(Cronograma!$D$6=0,0,Cronograma!$N$6*MAX(0,MIN(Cronograma!$G$6,5*52/12)-MAX(Cronograma!$F$6,(5-1)*52/12))/Cronograma!$D$6) -> 0 | H5: =IF(Cronograma!$D$6=0,0,Cronograma!$N$6*MAX(0,MIN(Cronograma!$G$6,6*52/12)-MAX(Cronograma!$F$6,(6-1)*52/12))/Cronograma!$D$6) -> 0 | I5: =IF(Cronograma!$D$6=0,0,Cronograma!$N$6*MAX(0,MIN(Cronograma!$G$6,7*52/12)-MAX(Cronograma!$F$6,(7-1)*52/12))/Cronograma!$D$6) -> 0 | J5: =IF(Cronograma!$D$6=0,0,Cronograma!$N$6*MAX(0,MIN(Cronograma!$G$6,8*52/12)-MAX(Cronograma!$F$6,(8-1)*52/12))/Cronograma!$D$6) -> 0 | K5: =IF(Cronograma!$D$6=0,0,Cronograma!$N$6*MAX(0,MIN(Cronograma!$G$6,9*52/12)-MAX(Cronograma!$F$6,(9-1)*52/12))/Cronograma!$D$6) -> 0 | L5: =IF(Cronograma!$D$6=0,0,Cronograma!$N$6*MAX(0,MIN(Cronograma!$G$6,10*52/12)-MAX(Cronograma!$F$6,(10-1)*52/12))/Cronograma!$D$6) -> 0 | M5: =IF(Cronograma!$D$6=0,0,Cronograma!$N$6*MAX(0,MIN(Cronograma!$G$6,11*52/12)-MAX(Cronograma!$F$6,(11-1)*52/12))/Cronograma!$D$6) -> 0 | N5: =IF(Cronograma!$D$6=0,0,Cronograma!$N$6*MAX(0,MIN(Cronograma!$G$6,12*52/12)-MAX(Cronograma!$F$6,(12-1)*52/12))/Cronograma!$D$6) -> 0 | O5: =SUM(C5:N5) -> 12995951
A6: 1.2 | B6: Plan de proyecto PM4R (alcance, cronograma, costos, riesgos) | C6: =IF(Cronograma!$D$7=0,0,Cronograma!$N$7*MAX(0,MIN(Cronograma!$G$7,1*52/12)-MAX(Cronograma!$F$7,(1-1)*52/12))/Cronograma!$D$7) -> 25991903 | D6: =IF(Cronograma!$D$7=0,0,Cronograma!$N$7*MAX(0,MIN(Cronograma!$G$7,2*52/12)-MAX(Cronograma!$F$7,(2-1)*52/12))/Cronograma!$D$7) -> 0 | E6: =IF(Cronograma!$D$7=0,0,Cronograma!$N$7*MAX(0,MIN(Cronograma!$G$7,3*52/12)-MAX(Cronograma!$F$7,(3-1)*52/12))/Cronograma!$D$7) -> 0 | F6: =IF(Cronograma!$D$7=0,0,Cronograma!$N$7*MAX(0,MIN(Cronograma!$G$7,4*52/12)-MAX(Cronograma!$F$7,(4-1)*52/12))/Cronograma!$D$7) -> 0 | G6: =IF(Cronograma!$D$7=0,0,Cronograma!$N$7*MAX(0,MIN(Cronograma!$G$7,5*52/12)-MAX(Cronograma!$F$7,(5-1)*52/12))/Cronograma!$D$7) -> 0 | H6: =IF(Cronograma!$D$7=0,0,Cronograma!$N$7*MAX(0,MIN(Cronograma!$G$7,6*52/12)-MAX(Cronograma!$F$7,(6-1)*52/12))/Cronograma!$D$7) -> 0 | I6: =IF(Cronograma!$D$7=0,0,Cronograma!$N$7*MAX(0,MIN(Cronograma!$G$7,7*52/12)-MAX(Cronograma!$F$7,(7-1)*52/12))/Cronograma!$D$7) -> 0 | J6: =IF(Cronograma!$D$7=0,0,Cronograma!$N$7*MAX(0,MIN(Cronograma!$G$7,8*52/12)-MAX(Cronograma!$F$7,(8-1)*52/12))/Cronograma!$D$7) -> 0 | K6: =IF(Cronograma!$D$7=0,0,Cronograma!$N$7*MAX(0,MIN(Cronograma!$G$7,9*52/12)-MAX(Cronograma!$F$7,(9-1)*52/12))/Cronograma!$D$7) -> 0 | L6: =IF(Cronograma!$D$7=0,0,Cronograma!$N$7*MAX(0,MIN(Cronograma!$G$7,10*52/12)-MAX(Cronograma!$F$7,(10-1)*52/12))/Cronograma!$D$7) -> 0 | M6: =IF(Cronograma!$D$7=0,0,Cronograma!$N$7*MAX(0,MIN(Cronograma!$G$7,11*52/12)-MAX(Cronograma!$F$7,(11-1)*52/12))/Cronograma!$D$7) -> 0 | N6: =IF(Cronograma!$D$7=0,0,Cronograma!$N$7*MAX(0,MIN(Cronograma!$G$7,12*52/12)-MAX(Cronograma!$F$7,(12-1)*52/12))/Cronograma!$D$7) -> 0 | O6: =SUM(C6:N6) -> 25991903
A7: 1.3 | B7: Seguimiento, control de cambios e informes (nivel de esfuerzo) | C7: =IF(Cronograma!$D$8=0,0,Cronograma!$N$8*MAX(0,MIN(Cronograma!$G$8,1*52/12)-MAX(Cronograma!$F$8,(1-1)*52/12))/Cronograma!$D$8) -> 5414979.8 | D7: =IF(Cronograma!$D$8=0,0,Cronograma!$N$8*MAX(0,MIN(Cronograma!$G$8,2*52/12)-MAX(Cronograma!$F$8,(2-1)*52/12))/Cronograma!$D$8) -> 17598684 | E7: =IF(Cronograma!$D$8=0,0,Cronograma!$N$8*MAX(0,MIN(Cronograma!$G$8,3*52/12)-MAX(Cronograma!$F$8,(3-1)*52/12))/Cronograma!$D$8) -> 17598684 | F7: =IF(Cronograma!$D$8=0,0,Cronograma!$N$8*MAX(0,MIN(Cronograma!$G$8,4*52/12)-MAX(Cronograma!$F$8,(4-1)*52/12))/Cronograma!$D$8) -> 17598684 | G7: =IF(Cronograma!$D$8=0,0,Cronograma!$N$8*MAX(0,MIN(Cronograma!$G$8,5*52/12)-MAX(Cronograma!$F$8,(5-1)*52/12))/Cronograma!$D$8) -> 17598684 | H7: =IF(Cronograma!$D$8=0,0,Cronograma!$N$8*MAX(0,MIN(Cronograma!$G$8,6*52/12)-MAX(Cronograma!$F$8,(6-1)*52/12))/Cronograma!$D$8) -> 17598684 | I7: =IF(Cronograma!$D$8=0,0,Cronograma!$N$8*MAX(0,MIN(Cronograma!$G$8,7*52/12)-MAX(Cronograma!$F$8,(7-1)*52/12))/Cronograma!$D$8) -> 17598684 | J7: =IF(Cronograma!$D$8=0,0,Cronograma!$N$8*MAX(0,MIN(Cronograma!$G$8,8*52/12)-MAX(Cronograma!$F$8,(8-1)*52/12))/Cronograma!$D$8) -> 17598684 | K7: =IF(Cronograma!$D$8=0,0,Cronograma!$N$8*MAX(0,MIN(Cronograma!$G$8,9*52/12)-MAX(Cronograma!$F$8,(9-1)*52/12))/Cronograma!$D$8) -> 17598684 | L7: =IF(Cronograma!$D$8=0,0,Cronograma!$N$8*MAX(0,MIN(Cronograma!$G$8,10*52/12)-MAX(Cronograma!$F$8,(10-1)*52/12))/Cronograma!$D$8) -> 17598684 | M7: =IF(Cronograma!$D$8=0,0,Cronograma!$N$8*MAX(0,MIN(Cronograma!$G$8,11*52/12)-MAX(Cronograma!$F$8,(11-1)*52/12))/Cronograma!$D$8) -> 14891194 | N7: =IF(Cronograma!$D$8=0,0,Cronograma!$N$8*MAX(0,MIN(Cronograma!$G$8,12*52/12)-MAX(Cronograma!$F$8,(12-1)*52/12))/Cronograma!$D$8) -> 0 | O7: =SUM(C7:N7) -> 1.7869433e+08
A8: 2.1 | B8: Levantamiento en planta y diagnóstico de la situación actual | C8: =IF(Cronograma!$D$9=0,0,Cronograma!$N$9*MAX(0,MIN(Cronograma!$G$9,1*52/12)-MAX(Cronograma!$F$9,(1-1)*52/12))/Cronograma!$D$9) -> 77975709 | D8: =IF(Cronograma!$D$9=0,0,Cronograma!$N$9*MAX(0,MIN(Cronograma!$G$9,2*52/12)-MAX(Cronograma!$F$9,(2-1)*52/12))/Cronograma!$D$9) -> 0 | E8: =IF(Cronograma!$D$9=0,0,Cronograma!$N$9*MAX(0,MIN(Cronograma!$G$9,3*52/12)-MAX(Cronograma!$F$9,(3-1)*52/12))/Cronograma!$D$9) -> 0 | F8: =IF(Cronograma!$D$9=0,0,Cronograma!$N$9*MAX(0,MIN(Cronograma!$G$9,4*52/12)-MAX(Cronograma!$F$9,(4-1)*52/12))/Cronograma!$D$9) -> 0 | G8: =IF(Cronograma!$D$9=0,0,Cronograma!$N$9*MAX(0,MIN(Cronograma!$G$9,5*52/12)-MAX(Cronograma!$F$9,(5-1)*52/12))/Cronograma!$D$9) -> 0 | H8: =IF(Cronograma!$D$9=0,0,Cronograma!$N$9*MAX(0,MIN(Cronograma!$G$9,6*52/12)-MAX(Cronograma!$F$9,(6-1)*52/12))/Cronograma!$D$9) -> 0 | I8: =IF(Cronograma!$D$9=0,0,Cronograma!$N$9*MAX(0,MIN(Cronograma!$G$9,7*52/12)-MAX(Cronograma!$F$9,(7-1)*52/12))/Cronograma!$D$9) -> 0 | J8: =IF(Cronograma!$D$9=0,0,Cronograma!$N$9*MAX(0,MIN(Cronograma!$G$9,8*52/12)-MAX(Cronograma!$F$9,(8-1)*52/12))/Cronograma!$D$9) -> 0 | K8: =IF(Cronograma!$D$9=0,0,Cronograma!$N$9*MAX(0,MIN(Cronograma!$G$9,9*52/12)-MAX(Cronograma!$F$9,(9-1)*52/12))/Cronograma!$D$9) -> 0 | L8: =IF(Cronograma!$D$9=0,0,Cronograma!$N$9*MAX(0,MIN(Cronograma!$G$9,10*52/12)-MAX(Cronograma!$F$9,(10-1)*52/12))/Cronograma!$D$9) -> 0 | M8: =IF(Cronograma!$D$9=0,0,Cronograma!$N$9*MAX(0,MIN(Cronograma!$G$9,11*52/12)-MAX(Cronograma!$F$9,(11-1)*52/12))/Cronograma!$D$9) -> 0 | N8: =IF(Cronograma!$D$9=0,0,Cronograma!$N$9*MAX(0,MIN(Cronograma!$G$9,12*52/12)-MAX(Cronograma!$F$9,(12-1)*52/12))/Cronograma!$D$9) -> 0 | O8: =SUM(C8:N8) -> 77975709
A9: 2.2 | B9: VSM actual y línea base de KPIs | C9: =IF(Cronograma!$D$10=0,0,Cronograma!$N$10*MAX(0,MIN(Cronograma!$G$10,1*52/12)-MAX(Cronograma!$F$10,(1-1)*52/12))/Cronograma!$D$10) -> 5414979.8 | D9: =IF(Cronograma!$D$10=0,0,Cronograma!$N$10*MAX(0,MIN(Cronograma!$G$10,2*52/12)-MAX(Cronograma!$F$10,(2-1)*52/12))/Cronograma!$D$10) -> 43319838 | E9: =IF(Cronograma!$D$10=0,0,Cronograma!$N$10*MAX(0,MIN(Cronograma!$G$10,3*52/12)-MAX(Cronograma!$F$10,(3-1)*52/12))/Cronograma!$D$10) -> 0 | F9: =IF(Cronograma!$D$10=0,0,Cronograma!$N$10*MAX(0,MIN(Cronograma!$G$10,4*52/12)-MAX(Cronograma!$F$10,(4-1)*52/12))/Cronograma!$D$10) -> 0 | G9: =IF(Cronograma!$D$10=0,0,Cronograma!$N$10*MAX(0,MIN(Cronograma!$G$10,5*52/12)-MAX(Cronograma!$F$10,(5-1)*52/12))/Cronograma!$D$10) -> 0 | H9: =IF(Cronograma!$D$10=0,0,Cronograma!$N$10*MAX(0,MIN(Cronograma!$G$10,6*52/12)-MAX(Cronograma!$F$10,(6-1)*52/12))/Cronograma!$D$10) -> 0 | I9: =IF(Cronograma!$D$10=0,0,Cronograma!$N$10*MAX(0,MIN(Cronograma!$G$10,7*52/12)-MAX(Cronograma!$F$10,(7-1)*52/12))/Cronograma!$D$10) -> 0 | J9: =IF(Cronograma!$D$10=0,0,Cronograma!$N$10*MAX(0,MIN(Cronograma!$G$10,8*52/12)-MAX(Cronograma!$F$10,(8-1)*52/12))/Cronograma!$D$10) -> 0 | K9: =IF(Cronograma!$D$10=0,0,Cronograma!$N$10*MAX(0,MIN(Cronograma!$G$10,9*52/12)-MAX(Cronograma!$F$10,(9-1)*52/12))/Cronograma!$D$10) -> 0 | L9: =IF(Cronograma!$D$10=0,0,Cronograma!$N$10*MAX(0,MIN(Cronograma!$G$10,10*52/12)-MAX(Cronograma!$F$10,(10-1)*52/12))/Cronograma!$D$10) -> 0 | M9: =IF(Cronograma!$D$10=0,0,Cronograma!$N$10*MAX(0,MIN(Cronograma!$G$10,11*52/12)-MAX(Cronograma!$F$10,(11-1)*52/12))/Cronograma!$D$10) -> 0 | N9: =IF(Cronograma!$D$10=0,0,Cronograma!$N$10*MAX(0,MIN(Cronograma!$G$10,12*52/12)-MAX(Cronograma!$F$10,(12-1)*52/12))/Cronograma!$D$10) -> 0 | O9: =SUM(C9:N9) -> 48734818
A10: 2.3 | B10: Arquitectura ISA-95 / ISA-88 y requerimientos | C10: =IF(Cronograma!$D$11=0,0,Cronograma!$N$11*MAX(0,MIN(Cronograma!$G$11,1*52/12)-MAX(Cronograma!$F$11,(1-1)*52/12))/Cronograma!$D$11) -> 6497975.7 | D10: =IF(Cronograma!$D$11=0,0,Cronograma!$N$11*MAX(0,MIN(Cronograma!$G$11,2*52/12)-MAX(Cronograma!$F$11,(2-1)*52/12))/Cronograma!$D$11) -> 51983806 | E10: =IF(Cronograma!$D$11=0,0,Cronograma!$N$11*MAX(0,MIN(Cronograma!$G$11,3*52/12)-MAX(Cronograma!$F$11,(3-1)*52/12))/Cronograma!$D$11) -> 0 | F10: =IF(Cronograma!$D$11=0,0,Cronograma!$N$11*MAX(0,MIN(Cronograma!$G$11,4*52/12)-MAX(Cronograma!$F$11,(4-1)*52/12))/Cronograma!$D$11) -> 0 | G10: =IF(Cronograma!$D$11=0,0,Cronograma!$N$11*MAX(0,MIN(Cronograma!$G$11,5*52/12)-MAX(Cronograma!$F$11,(5-1)*52/12))/Cronograma!$D$11) -> 0 | H10: =IF(Cronograma!$D$11=0,0,Cronograma!$N$11*MAX(0,MIN(Cronograma!$G$11,6*52/12)-MAX(Cronograma!$F$11,(6-1)*52/12))/Cronograma!$D$11) -> 0 | I10: =IF(Cronograma!$D$11=0,0,Cronograma!$N$11*MAX(0,MIN(Cronograma!$G$11,7*52/12)-MAX(Cronograma!$F$11,(7-1)*52/12))/Cronograma!$D$11) -> 0 | J10: =IF(Cronograma!$D$11=0,0,Cronograma!$N$11*MAX(0,MIN(Cronograma!$G$11,8*52/12)-MAX(Cronograma!$F$11,(8-1)*52/12))/Cronograma!$D$11) -> 0 | K10: =IF(Cronograma!$D$11=0,0,Cronograma!$N$11*MAX(0,MIN(Cronograma!$G$11,9*52/12)-MAX(Cronograma!$F$11,(9-1)*52/12))/Cronograma!$D$11) -> 0 | L10: =IF(Cronograma!$D$11=0,0,Cronograma!$N$11*MAX(0,MIN(Cronograma!$G$11,10*52/12)-MAX(Cronograma!$F$11,(10-1)*52/12))/Cronograma!$D$11) -> 0 | M10: =IF(Cronograma!$D$11=0,0,Cronograma!$N$11*MAX(0,MIN(Cronograma!$G$11,11*52/12)-MAX(Cronograma!$F$11,(11-1)*52/12))/Cronograma!$D$11) -> 0 | N10: =IF(Cronograma!$D$11=0,0,Cronograma!$N$11*MAX(0,MIN(Cronograma!$G$11,12*52/12)-MAX(Cronograma!$F$11,(12-1)*52/12))/Cronograma!$D$11) -> 0 | O10: =SUM(C10:N10) -> 58481781
A11: 2.4 | B11: Hito: aprobación de la ingeniería conceptual | C11: =IF(Cronograma!$D$12=0,0,Cronograma!$N$12*MAX(0,MIN(Cronograma!$G$12,1*52/12)-MAX(Cronograma!$F$12,(1-1)*52/12))/Cronograma!$D$12) -> 0 | D11: =IF(Cronograma!$D$12=0,0,Cronograma!$N$12*MAX(0,MIN(Cronograma!$G$12,2*52/12)-MAX(Cronograma!$F$12,(2-1)*52/12))/Cronograma!$D$12) -> 0 | E11: =IF(Cronograma!$D$12=0,0,Cronograma!$N$12*MAX(0,MIN(Cronograma!$G$12,3*52/12)-MAX(Cronograma!$F$12,(3-1)*52/12))/Cronograma!$D$12) -> 0 | F11: =IF(Cronograma!$D$12=0,0,Cronograma!$N$12*MAX(0,MIN(Cronograma!$G$12,4*52/12)-MAX(Cronograma!$F$12,(4-1)*52/12))/Cronograma!$D$12) -> 0 | G11: =IF(Cronograma!$D$12=0,0,Cronograma!$N$12*MAX(0,MIN(Cronograma!$G$12,5*52/12)-MAX(Cronograma!$F$12,(5-1)*52/12))/Cronograma!$D$12) -> 0 | H11: =IF(Cronograma!$D$12=0,0,Cronograma!$N$12*MAX(0,MIN(Cronograma!$G$12,6*52/12)-MAX(Cronograma!$F$12,(6-1)*52/12))/Cronograma!$D$12) -> 0 | I11: =IF(Cronograma!$D$12=0,0,Cronograma!$N$12*MAX(0,MIN(Cronograma!$G$12,7*52/12)-MAX(Cronograma!$F$12,(7-1)*52/12))/Cronograma!$D$12) -> 0 | J11: =IF(Cronograma!$D$12=0,0,Cronograma!$N$12*MAX(0,MIN(Cronograma!$G$12,8*52/12)-MAX(Cronograma!$F$12,(8-1)*52/12))/Cronograma!$D$12) -> 0 | K11: =IF(Cronograma!$D$12=0,0,Cronograma!$N$12*MAX(0,MIN(Cronograma!$G$12,9*52/12)-MAX(Cronograma!$F$12,(9-1)*52/12))/Cronograma!$D$12) -> 0 | L11: =IF(Cronograma!$D$12=0,0,Cronograma!$N$12*MAX(0,MIN(Cronograma!$G$12,10*52/12)-MAX(Cronograma!$F$12,(10-1)*52/12))/Cronograma!$D$12) -> 0 | M11: =IF(Cronograma!$D$12=0,0,Cronograma!$N$12*MAX(0,MIN(Cronograma!$G$12,11*52/12)-MAX(Cronograma!$F$12,(11-1)*52/12))/Cronograma!$D$12) -> 0 | N11: =IF(Cronograma!$D$12=0,0,Cronograma!$N$12*MAX(0,MIN(Cronograma!$G$12,12*52/12)-MAX(Cronograma!$F$12,(12-1)*52/12))/Cronograma!$D$12) -> 0 | O11: =SUM(C11:N11) -> 0
A12: 3.1 | B12: P&ID, lista de instrumentos y hojas de datos | C12: =IF(Cronograma!$D$13=0,0,Cronograma!$N$13*MAX(0,MIN(Cronograma!$G$13,1*52/12)-MAX(Cronograma!$F$13,(1-1)*52/12))/Cronograma!$D$13) -> 0 | D12: =IF(Cronograma!$D$13=0,0,Cronograma!$N$13*MAX(0,MIN(Cronograma!$G$13,2*52/12)-MAX(Cronograma!$F$13,(2-1)*52/12))/Cronograma!$D$13) -> 21659919 | E12: =IF(Cronograma!$D$13=0,0,Cronograma!$N$13*MAX(0,MIN(Cronograma!$G$13,3*52/12)-MAX(Cronograma!$F$13,(3-1)*52/12))/Cronograma!$D$13) -> 43319838 | F12: =IF(Cronograma!$D$13=0,0,Cronograma!$N$13*MAX(0,MIN(Cronograma!$G$13,4*52/12)-MAX(Cronograma!$F$13,(4-1)*52/12))/Cronograma!$D$13) -> 0 | G12: =IF(Cronograma!$D$13=0,0,Cronograma!$N$13*MAX(0,MIN(Cronograma!$G$13,5*52/12)-MAX(Cronograma!$F$13,(5-1)*52/12))/Cronograma!$D$13) -> 0 | H12: =IF(Cronograma!$D$13=0,0,Cronograma!$N$13*MAX(0,MIN(Cronograma!$G$13,6*52/12)-MAX(Cronograma!$F$13,(6-1)*52/12))/Cronograma!$D$13) -> 0 | I12: =IF(Cronograma!$D$13=0,0,Cronograma!$N$13*MAX(0,MIN(Cronograma!$G$13,7*52/12)-MAX(Cronograma!$F$13,(7-1)*52/12))/Cronograma!$D$13) -> 0 | J12: =IF(Cronograma!$D$13=0,0,Cronograma!$N$13*MAX(0,MIN(Cronograma!$G$13,8*52/12)-MAX(Cronograma!$F$13,(8-1)*52/12))/Cronograma!$D$13) -> 0 | K12: =IF(Cronograma!$D$13=0,0,Cronograma!$N$13*MAX(0,MIN(Cronograma!$G$13,9*52/12)-MAX(Cronograma!$F$13,(9-1)*52/12))/Cronograma!$D$13) -> 0 | L12: =IF(Cronograma!$D$13=0,0,Cronograma!$N$13*MAX(0,MIN(Cronograma!$G$13,10*52/12)-MAX(Cronograma!$F$13,(10-1)*52/12))/Cronograma!$D$13) -> 0 | M12: =IF(Cronograma!$D$13=0,0,Cronograma!$N$13*MAX(0,MIN(Cronograma!$G$13,11*52/12)-MAX(Cronograma!$F$13,(11-1)*52/12))/Cronograma!$D$13) -> 0 | N12: =IF(Cronograma!$D$13=0,0,Cronograma!$N$13*MAX(0,MIN(Cronograma!$G$13,12*52/12)-MAX(Cronograma!$F$13,(12-1)*52/12))/Cronograma!$D$13) -> 0 | O12: =SUM(C12:N12) -> 64979757
A13: 3.2 | B13: Especificación funcional (FDS) y recetas ISA-88 | C13: =IF(Cronograma!$D$14=0,0,Cronograma!$N$14*MAX(0,MIN(Cronograma!$G$14,1*52/12)-MAX(Cronograma!$F$14,(1-1)*52/12))/Cronograma!$D$14) -> 0 | D13: =IF(Cronograma!$D$14=0,0,Cronograma!$N$14*MAX(0,MIN(Cronograma!$G$14,2*52/12)-MAX(Cronograma!$F$14,(2-1)*52/12))/Cronograma!$D$14) -> 18565645 | E13: =IF(Cronograma!$D$14=0,0,Cronograma!$N$14*MAX(0,MIN(Cronograma!$G$14,3*52/12)-MAX(Cronograma!$F$14,(3-1)*52/12))/Cronograma!$D$14) -> 48270677 | F13: =IF(Cronograma!$D$14=0,0,Cronograma!$N$14*MAX(0,MIN(Cronograma!$G$14,4*52/12)-MAX(Cronograma!$F$14,(4-1)*52/12))/Cronograma!$D$14) -> 11139387 | G13: =IF(Cronograma!$D$14=0,0,Cronograma!$N$14*MAX(0,MIN(Cronograma!$G$14,5*52/12)-MAX(Cronograma!$F$14,(5-1)*52/12))/Cronograma!$D$14) -> 0 | H13: =IF(Cronograma!$D$14=0,0,Cronograma!$N$14*MAX(0,MIN(Cronograma!$G$14,6*52/12)-MAX(Cronograma!$F$14,(6-1)*52/12))/Cronograma!$D$14) -> 0 | I13: =IF(Cronograma!$D$14=0,0,Cronograma!$N$14*MAX(0,MIN(Cronograma!$G$14,7*52/12)-MAX(Cronograma!$F$14,(7-1)*52/12))/Cronograma!$D$14) -> 0 | J13: =IF(Cronograma!$D$14=0,0,Cronograma!$N$14*MAX(0,MIN(Cronograma!$G$14,8*52/12)-MAX(Cronograma!$F$14,(8-1)*52/12))/Cronograma!$D$14) -> 0 | K13: =IF(Cronograma!$D$14=0,0,Cronograma!$N$14*MAX(0,MIN(Cronograma!$G$14,9*52/12)-MAX(Cronograma!$F$14,(9-1)*52/12))/Cronograma!$D$14) -> 0 | L13: =IF(Cronograma!$D$14=0,0,Cronograma!$N$14*MAX(0,MIN(Cronograma!$G$14,10*52/12)-MAX(Cronograma!$F$14,(10-1)*52/12))/Cronograma!$D$14) -> 0 | M13: =IF(Cronograma!$D$14=0,0,Cronograma!$N$14*MAX(0,MIN(Cronograma!$G$14,11*52/12)-MAX(Cronograma!$F$14,(11-1)*52/12))/Cronograma!$D$14) -> 0 | N13: =IF(Cronograma!$D$14=0,0,Cronograma!$N$14*MAX(0,MIN(Cronograma!$G$14,12*52/12)-MAX(Cronograma!$F$14,(12-1)*52/12))/Cronograma!$D$14) -> 0 | O13: =SUM(C13:N13) -> 77975709
A14: 3.3 | B14: Ingeniería eléctrica y diseño de tableros | C14: =IF(Cronograma!$D$15=0,0,Cronograma!$N$15*MAX(0,MIN(Cronograma!$G$15,1*52/12)-MAX(Cronograma!$F$15,(1-1)*52/12))/Cronograma!$D$15) -> 0 | D14: =IF(Cronograma!$D$15=0,0,Cronograma!$N$15*MAX(0,MIN(Cronograma!$G$15,2*52/12)-MAX(Cronograma!$F$15,(2-1)*52/12))/Cronograma!$D$15) -> 0 | E14: =IF(Cronograma!$D$15=0,0,Cronograma!$N$15*MAX(0,MIN(Cronograma!$G$15,3*52/12)-MAX(Cronograma!$F$15,(3-1)*52/12))/Cronograma!$D$15) -> 9746963.6 | F14: =IF(Cronograma!$D$15=0,0,Cronograma!$N$15*MAX(0,MIN(Cronograma!$G$15,4*52/12)-MAX(Cronograma!$F$15,(4-1)*52/12))/Cronograma!$D$15) -> 29240891 | G14: =IF(Cronograma!$D$15=0,0,Cronograma!$N$15*MAX(0,MIN(Cronograma!$G$15,5*52/12)-MAX(Cronograma!$F$15,(5-1)*52/12))/Cronograma!$D$15) -> 0 | H14: =IF(Cronograma!$D$15=0,0,Cronograma!$N$15*MAX(0,MIN(Cronograma!$G$15,6*52/12)-MAX(Cronograma!$F$15,(6-1)*52/12))/Cronograma!$D$15) -> 0 | I14: =IF(Cronograma!$D$15=0,0,Cronograma!$N$15*MAX(0,MIN(Cronograma!$G$15,7*52/12)-MAX(Cronograma!$F$15,(7-1)*52/12))/Cronograma!$D$15) -> 0 | J14: =IF(Cronograma!$D$15=0,0,Cronograma!$N$15*MAX(0,MIN(Cronograma!$G$15,8*52/12)-MAX(Cronograma!$F$15,(8-1)*52/12))/Cronograma!$D$15) -> 0 | K14: =IF(Cronograma!$D$15=0,0,Cronograma!$N$15*MAX(0,MIN(Cronograma!$G$15,9*52/12)-MAX(Cronograma!$F$15,(9-1)*52/12))/Cronograma!$D$15) -> 0 | L14: =IF(Cronograma!$D$15=0,0,Cronograma!$N$15*MAX(0,MIN(Cronograma!$G$15,10*52/12)-MAX(Cronograma!$F$15,(10-1)*52/12))/Cronograma!$D$15) -> 0 | M14: =IF(Cronograma!$D$15=0,0,Cronograma!$N$15*MAX(0,MIN(Cronograma!$G$15,11*52/12)-MAX(Cronograma!$F$15,(11-1)*52/12))/Cronograma!$D$15) -> 0 | N14: =IF(Cronograma!$D$15=0,0,Cronograma!$N$15*MAX(0,MIN(Cronograma!$G$15,12*52/12)-MAX(Cronograma!$F$15,(12-1)*52/12))/Cronograma!$D$15) -> 0 | O14: =SUM(C14:N14) -> 38987854
A15: 3.4 | B15: Diseño de la celda robotizada y layout de la línea | C15: =IF(Cronograma!$D$16=0,0,Cronograma!$N$16*MAX(0,MIN(Cronograma!$G$16,1*52/12)-MAX(Cronograma!$F$16,(1-1)*52/12))/Cronograma!$D$16) -> 0 | D15: =IF(Cronograma!$D$16=0,0,Cronograma!$N$16*MAX(0,MIN(Cronograma!$G$16,2*52/12)-MAX(Cronograma!$F$16,(2-1)*52/12))/Cronograma!$D$16) -> 21659919 | E15: =IF(Cronograma!$D$16=0,0,Cronograma!$N$16*MAX(0,MIN(Cronograma!$G$16,3*52/12)-MAX(Cronograma!$F$16,(3-1)*52/12))/Cronograma!$D$16) -> 30323887 | F15: =IF(Cronograma!$D$16=0,0,Cronograma!$N$16*MAX(0,MIN(Cronograma!$G$16,4*52/12)-MAX(Cronograma!$F$16,(4-1)*52/12))/Cronograma!$D$16) -> 0 | G15: =IF(Cronograma!$D$16=0,0,Cronograma!$N$16*MAX(0,MIN(Cronograma!$G$16,5*52/12)-MAX(Cronograma!$F$16,(5-1)*52/12))/Cronograma!$D$16) -> 0 | H15: =IF(Cronograma!$D$16=0,0,Cronograma!$N$16*MAX(0,MIN(Cronograma!$G$16,6*52/12)-MAX(Cronograma!$F$16,(6-1)*52/12))/Cronograma!$D$16) -> 0 | I15: =IF(Cronograma!$D$16=0,0,Cronograma!$N$16*MAX(0,MIN(Cronograma!$G$16,7*52/12)-MAX(Cronograma!$F$16,(7-1)*52/12))/Cronograma!$D$16) -> 0 | J15: =IF(Cronograma!$D$16=0,0,Cronograma!$N$16*MAX(0,MIN(Cronograma!$G$16,8*52/12)-MAX(Cronograma!$F$16,(8-1)*52/12))/Cronograma!$D$16) -> 0 | K15: =IF(Cronograma!$D$16=0,0,Cronograma!$N$16*MAX(0,MIN(Cronograma!$G$16,9*52/12)-MAX(Cronograma!$F$16,(9-1)*52/12))/Cronograma!$D$16) -> 0 | L15: =IF(Cronograma!$D$16=0,0,Cronograma!$N$16*MAX(0,MIN(Cronograma!$G$16,10*52/12)-MAX(Cronograma!$F$16,(10-1)*52/12))/Cronograma!$D$16) -> 0 | M15: =IF(Cronograma!$D$16=0,0,Cronograma!$N$16*MAX(0,MIN(Cronograma!$G$16,11*52/12)-MAX(Cronograma!$F$16,(11-1)*52/12))/Cronograma!$D$16) -> 0 | N15: =IF(Cronograma!$D$16=0,0,Cronograma!$N$16*MAX(0,MIN(Cronograma!$G$16,12*52/12)-MAX(Cronograma!$F$16,(12-1)*52/12))/Cronograma!$D$16) -> 0 | O15: =SUM(C15:N15) -> 51983806
